Workbook
Name SegmentaçãodeDados_A_receber: #N/A
Name SegmentaçãodeDados_Ano: #N/A
Name SegmentaçãodeDados_ano1: #N/A
Name SegmentaçãodeDados_Anos2: #N/A
Name SegmentaçãodeDados_Atrasado: #N/A
Name SegmentaçãodeDados_Descrição_Resumida: #N/A
Name SegmentaçãodeDados_Descrição_Resumida1: #N/A
Name SegmentaçãodeDados_FORNECEDOR: #N/A
Name SegmentaçãodeDados_SEMANA: #N/A

Sheet DashBoard Vendas

Sheet DBO Vendas
A1: ID | B1: N° do Pedido | C1: N° do Pedido na Loja Virtual | D1: Data | E1: ID contato | F1: Nome do contato | G1: Cpf/Cnpj | H1: Endereco | I1: Bairro | J1: Município | K1: Cep | L1: Estado | M1: E-mail | N1: Telefone | O1: Desconto pedido | P1: Frete | Q1: Observações | R1: Situação | S1: ID produto | T1: Descrição | U1: Quantidade | V1: Valor unitário | W1: Desconto item | X1: Preço de Custo | Y1: Preço Total | Z1: Código do contato | AA1: Código do produto | AB1: Frete proporcional | AC1: Desconto proporcional | AD1: Vendedor | AE1: Nº da NFe | AF1: Natureza da NFe | AG1: Situação da NFe | AH1: Última ocorrência | AI1: Outras despesas | AJ1: Outras despesas proporcional | AK1: Descrição Resumida | AL1: Peso
A2: 15284244295 | B2: 66 | D2: 44405 | E2: 15020006032 | F2: =VLOOKUP(RANDBETWEEN(1,20),'DBO Compras'!AA:AC,3,0) -> Comprador 01 | G2: 28.561.609/0001-59 | H2: Rodovia BR-277 Curitiba-Paranaguá, 3641 | I2: Cajuru | J2: Curitiba | K2: 82960015 | L2: PR | M2: teste@share-inc.com.br | N2: 41996838559 | O2: 0 | P2: 0 | R2: Atendido | S2: 15015085610 | T2: =VLOOKUP(RANDBETWEEN(1,17),'Auxiliar Vendas'!D:G,2,0) -> Produto 04 | U2: 10 | V2: 13.9 | W2: 0 | X2: 10.23 | Y2: 139 | Z2: 16 | AA2: PRFL.00.0001 | AB2: 0 | AC2: 0 | AH2: 44405.385 | AI2: 0 | AJ2: 0 | AK2: =VLOOKUP(T2,'Auxiliar Vendas'!E:F,2,FALSE) -> Produto 04 | AL2: =U2*VLOOKUP(T2,'Auxiliar Vendas'!E:G,3,FALSE) -> 6
A3: 15020046998 | B3: 1 | D3: 44407 | E3: 15020006032 | F3: =VLOOKUP(RANDBETWEEN(1,20),'DBO Compras'!AA:AC,3,0) -> Comprador 06 | G3: 28.561.609/0001-59 | H3: Rodovia BR-277 Curitiba-Paranaguá, 3641 | I3: Cajuru | J3: Curitiba | K3: 82960015 | L3: PR | M3: teste@share-inc.com.br | N3: 41996838559 | O3: 0 | P3: 0 | R3: Atendido | S3: 15015353721 | T3: =VLOOKUP(RANDBETWEEN(1,17),'Auxiliar Vendas'!D:G,2,0) -> Produto 17 | U3: 1000 | V3: 8.2 | W3: 0 | X3: 5.58 | Y3: 8200 | Z3: 16 | AA3: PRFL.00.0002 | AB3: 0 | AC3: 0 | AH3: 44407.585 | AI3: 0 | AJ3: 0 | AK3: =VLOOKUP(T3,'Auxiliar Vendas'!E:F,2,FALSE) -> Produto 17 | AL3: =U3*VLOOKUP(T3,'Auxiliar Vendas'!E:G,3,FALSE) -> 1420
A4: 15269414721 | B4: 23 | D4: 44408 | E4: 15058669306 | F4: =VLOOKUP(RANDBETWEEN(1,20),'DBO Compras'!AA:AC,3,0) -> Comprador 19 | G4: 03.387.992/0001-40 | H4: RUA ANTONIO GRECA, 91 | I4: AHU | J4: Curitiba | K4: 82200430 | L4: PR | M4: willian@walls.com.br | N4: 4191036801 | O4: 0 | P4: 0 | Q4: Ref. faturamento NFE saída 614. PAGO VM. | R4: Atendido | S4: 15016043939 | T4: =VLOOKUP(RANDBETWEEN(1,17),'Auxiliar Vendas'!D:G,2,0) -> Produto 01 | U4: 1000 | V4: 13.85 | W4: 0 | X4: 10.747 | Y4: 13850 | Z4: 17 | AA4: PRFL.00.0019 | AB4: 0 | AC4: 0 | AD4: AMANDA HUBBE | AH4: 44408.572 | AI4: 0 | AJ4: 0 | AK4: =VLOOKUP(T4,'Auxiliar Vendas'!E:F,2,FALSE) -> Produto 01 | AL4: =U4*VLOOKUP(T4,'Auxiliar Vendas'!E:G,3,FALSE) -> 400
A5: 15269487249 | B5: 24 | D5: 44408 | E5: 15020006032 | F5: =VLOOKUP(RANDBETWEEN(1,20),'DBO Compras'!AA:AC,3,0) -> Comprador 17 | G5: 28.561.609/0001-59 | H5: Rodovia BR-277 Curitiba-Paranaguá, 3641 | I5: Cajuru | J5: Curitiba | K5: 82960015 | L5: PR | M5: teste@share-inc.com.br | N5: 41996838559 | O5: 0 | P5: 0 | Q5: Ref. faturamento NFE saída 619. PAGO VM. | R5: Atendido | S5: 15015511068 | T5: =VLOOKUP(RANDBETWEEN(1,17),'Auxiliar Vendas'!D:G,2,0) -> Produto 15 | U5: 300 | V5: 16.2 | W5: 0 | X5: 10.23 | Y5: 4860 | Z5: 16 | AA5: PRFL.00.0005 | AB5: 0 | AC5: 0 | AH5: 44408.573 | AI5: 0 | AJ5: 0 | AK5: =VLOOKUP(T5,'Auxiliar Vendas'!E:F,2,FALSE) -> Produto 15 | AL5: =U5*VLOOKUP(T5,'Auxiliar Vendas'!E:G,3,FALSE) -> 426
A6: 15269550609 | B6: 25 | D6: 44408 | E6: 15179581888 | F6: =VLOOKUP(RANDBETWEEN(1,20),'DBO Compras'!AA:AC,3,0) -> Comprador 17 | G6: 44.114.658/0001-08 | H6: RUA JOAO RAPHAEL MACHADO, 496 | I6: Araucaria | J6: Curitiba | K6: 81350610 | L6: PR | M6: Marcio@destak.com.br | N6: 41996849234 | O6: 0 | P6: 0 | R6: Atendido | S6: 15015085610 | T6: =VLOOKUP(RANDBETWEEN(1,17),'Auxiliar Vendas'!D:G,2,0) -> Produto 15 | U6: 2340 | V6: 13.9 | W6: 0 | X6: 10.23 | Y6: 32526 | Z6: 41 | AA6: PRFL.00.0001 | AB6: 0 | AC6: 0 | AD6: HENRIQUE | AH6: 44408.385 | AI6: 0 | AJ6: 0 | AK6: =VLOOKUP(T6,'Auxiliar Vendas'!E:F,2,FALSE) -> Produto 15 | AL6: =U6*VLOOKUP(T6,'Auxiliar Vendas'!E:G,3,FALSE) -> 3322.8
A7: 15269550609 | B7: 25 | D7: 44408 | E7: 15179581888 | F7: =VLOOKUP(RANDBETWEEN(1,20),'DBO Compras'!AA:AC,3,0) -> Comprador 08 | G7: 44.114.658/0001-08 | H7: RUA JOAO RAPHAEL MACHADO, 496 | I7: Araucaria | J7: Curitiba | K7: 81350610 | L7: PR | M7: Marcio@destak.com.br | N7: 41996849234 | O7: 0 | P7: 0 | R7: Atendido | S7: 15015353721 | T7: =VLOOKUP(RANDBETWEEN(1,17),'Auxiliar Vendas'!D:G,2,0) -> Produto 11 | U7: 1452 | V7: 8.2 | W7: 0 | X7: 5.58 | Y7: 11906.4 | Z7: 41 | AA7: PRFL.00.0002 | AB7: 0 | AC7: 0 | AD7: HENRIQUE | AH7: 44408.385 | AI7: 0 | AJ7: 0 | AK7: =VLOOKUP(T7,'Auxiliar Vendas'!E:F,2,FALSE) -> Produto 11 | AL7: =U7*VLOOKUP(T7,'Auxiliar Vendas'!E:G,3,FALSE) -> 1597.2
A8: 15269550609 | B8: 25 | D8: 44408 | E8: 15179581888 | F8: =VLOOKUP(RANDBETWEEN(1,20),'DBO Compras'!AA:AC,3,0) -> Comprador 11 | G8: 44.114.658/0001-08 | H8: RUA JOAO RAPHAEL MACHADO, 496 | I8: Araucaria | J8: Curitiba | K8: 81350610 | L8: PR | M8: Marcio@destak.com.br | N8: 41996849234 | O8: 0 | P8: 0 | R8: Atendido | S8: 15015918644 | T8: =VLOOKUP(RANDBETWEEN(1,17),'Auxiliar Vendas'!D:G,2,0) -> Produto 04 | U8: 1000 | V8: 7.5 | W8: 0 | X8: 5.61 | Y8: 7500 | Z8: 41 | AA8: PRFL.00.0011 | AB8: 0 | AC8: 0 | AD8: HENRIQUE | AH8: 44408.385 | AI8: 0 | AJ8: 0 | AK8: =VLOOKUP(T8,'Auxiliar Vendas'!E:F,2,FALSE) -> Produto 04 | AL8: =U8*VLOOKUP(T8,'Auxiliar Vendas'!E:G,3,FALSE) -> 600
A9: 15280180552 | B9: 64 | D9: 44433 | E9: 15179608501 | F9: =VLOOKUP(RANDBETWEEN(1,20),'DBO Compras'!AA:AC,3,0) -> Comprador 04 | G9: 25.195.001/0001-60 | H9: RUA ITACIANO MARCONDES, 47 | I9: SANTA CANDIDA | J9: Curitiba | K9: 82720070 | L9: PR | M9: Delta@Delta.com.br | N9: 41992354686 | O9: 0 | P9: 0 | R9: Atendido | S9: 15016087271 | T9: =VLOOKUP(RANDBETWEEN(1,17),'Auxiliar Vendas'!D:G,2,0) -> Produto 01 | U9: 200 | V9: 18.2 | W9: 0 | X9: 14.4596 | Y9: 3640 | Z9: 42 | AA9: PRFL.00.0025 | AB9: 0 | AC9: 0 | AH9: 44433.49 | AI9: 0 | AJ9: 0 | AK9: =VLOOKUP(T9,'Auxiliar Vendas'!E:F,2,FALSE) -> Produto 01 | AL9: =U9*VLOOKUP(T9,'Auxiliar Vendas'!E:G,3,FALSE) -> 80
A10: 15280180552 | B10: 64 | D10: 44433 | E10: 15179608501 | F10: =VLOOKUP(RANDBETWEEN(1,20),'DBO Compras'!AA:AC,3,0) -> Comprador 14 | G10: 25.195.001/0001-60 | H10: RUA ITACIANO MARCONDES, 47 | I10: SANTA CANDIDA | J10: Curitiba | K10: 82720070 | L10: PR | M10: Delta@Delta.com.br | N10: 41992354686 | O10: 0 | P10: 0 | R10: Atendido | S10: 15016093155 | T10: =VLOOKUP(RANDBETWEEN(1,17),'Auxiliar Vendas'!D:G,2,0) -> Produto 07 | U10: 400 | V10: 16.17 | W10: 0 | X10: 14.4596 | Y10: 6468 | Z10: 42 | AA10: PRFL.00.0026 | AB10: 0 | AC10: 0 | AH10: 44433.49 | AI10: 0 | AJ10: 0 | AK10: =VLOOKUP(T10,'Auxiliar Vendas'!E:F,2,FALSE) -> Produto 07 | AL10: =U10*VLOOKUP(T10,'Auxiliar Vendas'!E:G,3,FALSE) -> 440
A11: 15280180552 | B11: 64 | D11: 44433 | E11: 15179608501 | F11: =VLOOKUP(RANDBETWEEN(1,20),'DBO Compras'!AA:AC,3,0) -> Comprador 18 | G11: 25.195.001/0001-60 | H11: RUA ITACIANO MARCONDES, 47 | I11: SANTA CANDIDA | J11: Curitiba | K11: 82720070 | L11: PR | M11: Delta@Delta.com.br | N11: 41992354686 | O11: 0 | P11: 0 | R11: Atendido | S11: 15015886084 | T11: =VLOOKUP(RANDBETWEEN(1,17),'Auxiliar Vendas'!D:G,2,0) -> Produto 15 | U11: 200 | V11: 18.13 | W11: 0 | X11: 15.996 | Y11: 3626 | Z11: 42 | AA11: PRFL.00.0009 | AB11: 0 | AC11: 0 | AH11: 44433.49 | AI11: 0 | AJ11: 0 | AK11: =VLOOKUP(T11,'Auxiliar Vendas'!E:F,2,FALSE) -> Produto 15 | AL11: =U11*VLOOKUP(T11,'Auxiliar Vendas'!E:G,3,FALSE) -> 284
A12: 15269564434 | B12: 26 | D12: 44438 | E12: 15058698393 | F12: =VLOOKUP(RANDBETWEEN(1,20),'DBO Compras'!AA:AC,3,0) -> Comprador 17 | G12: 21.267.641/0001-87 | H12: LOC RODOVIA DEP JOAO LEOPOLDO JA, 11432 | I12: CENTRO | J12: PINHAIS | K12: 83320382 | L12: PR | M12: Fabio@Install.com.br | N12: 41998972354 | O12: 0 | P12: 0 | R12: Atendido | S12: 15016043939 | T12: =VLOOKUP(RANDBETWEEN(1,17),'Auxiliar Vendas'!D:G,2,0) -> Produto 07 | U12: 500 | V12: 13.9 | W12: 0 | X12: 10.747 | Y12: 6950 | Z12: 18 | AA12: PRFL.00.0019 | AB12: 0 | AC12: 0 | AH12: 44438.573 | AI12: 0 | AJ12: 0 | AK12: =VLOOKUP(T12,'Auxiliar Vendas'!E:F,2,FALSE) -> Produto 07 | AL12: =U12*VLOOKUP(T12,'Auxiliar Vendas'!E:G,3,FALSE) -> 550
A13: 15269655769 | B13: 27 | D13: 44438 | E13: 15020006032 | F13: =VLOOKUP(RANDBETWEEN(1,20),'DBO Compras'!AA:AC,3,0) -> Comprador 19 | G13: 28.561.609/0001-59 | H13: Rodovia BR-277 Curitiba-Paranaguá, 3641 | I13: Cajuru | J13: Curitiba | K13: 82960015 | L13: PR | M13: teste@share-inc.com.br | N13: 41996838559 | O13: 0 | P13: 0 | R13: Atendido | S13: 15015511068 | T13: =VLOOKUP(RANDBETWEEN(1,17),'Auxiliar Vendas'!D:G,2,0) -> Produto 17 | U13: 500 | V13: 16.2 | W13: 0 | X13: 10.23 | Y13: 8100 | Z13: 16 | AA13: PRFL.00.0005 | AB13: 0 | AC13: 0 | AH13: 44438.574 | AI13: 0 | AJ13: 0 | AK13: =VLOOKUP(T13,'Auxiliar Vendas'!E:F,2,FALSE) -> Produto 17 | AL13: =U13*VLOOKUP(T13,'Auxiliar Vendas'!E:G,3,FALSE) -> 710
A14: 15269655769 | B14: 27 | D14: 44438 | E14: 15020006032 | F14: =VLOOKUP(RANDBETWEEN(1,20),'DBO Compras'!AA:AC,3,0) -> Comprador 05 | G14: 28.561.609/0001-59 | H14: Rodovia BR-277 Curitiba-Paranaguá, 3641 | I14: Cajuru | J14: Curitiba | K14: 82960015 | L14: PR | M14: teste@share-inc.com.br | N14: 41996838559 | O14: 0 | P14: 0 | R14: Atendido | S14: 15016043939 | T14: =VLOOKUP(RANDBETWEEN(1,17),'Auxiliar Vendas'!D:G,2,0) -> Produto 10 | U14: 500 | V14: 13.9 | W14: 0 | X14: 10.747 | Y14: 6950 | Z14: 16 | AA14: PRFL.00.0019 | AB14: 0 | AC14: 0 | AH14: 44438.574 | AI14: 0 | AJ14: 0 | AK14: =VLOOKUP(T14,'Auxiliar Vendas'!E:F,2,FALSE) -> Produto 10 | AL14: =U14*VLOOKUP(T14,'Auxiliar Vendas'!E:G,3,FALSE) -> 550
A15: 15269655769 | B15: 27 | D15: 44438 | E15: 15020006032 | F15: =VLOOKUP(RANDBETWEEN(1,20),'DBO Compras'!AA:AC,3,0) -> Comprador 02 | G15: 28.561.609/0001-59 | H15: Rodovia BR-277 Curitiba-Paranaguá, 3641 | I15: Cajuru | J15: Curitiba | K15: 82960015 | L15: PR | M15: teste@share-inc.com.br | N15: 41996838559 | O15: 0 | P15: 0 | R15: Atendido | S15: 15015918644 | T15: =VLOOKUP(RANDBETWEEN(1,17),'Auxiliar Vendas'!D:G,2,0) -> Produto 09 | U15: 2000 | V15: 8.2 | W15: 0 | X15: 5.61 | Y15: 16400 | Z15: 16 | AA15: PRFL.00.0011 | AB15: 0 | AC15: 0 | AH15: 44438.574 | AI15: 0 | AJ15: 0 | AK15: =VLOOKUP(T15,'Auxiliar Vendas'!E:F,2,FALSE) -> Produto 09 | AL15: =U15*VLOOKUP(T15,'Auxiliar Vendas'!E:G,3,FALSE) -> 2200
A16: 15269738581 | B16: 28 | D16: 44438 | E16: 15058719469 | F16: =VLOOKUP(RANDBETWEEN(1,20),'DBO Compras'!AA:AC,3,0) -> Comprador 10 | G16: 30.641.041/0001-28 | H16: RUA LEONARDO NOVICKI, 1554 | I16: CAJURU | J16: CURITIBA | K16: 82930548 | L16: PR | O16: 0 | P16: 0 | R16: Atendido | S16: 15016043939 | T16: =VLOOKUP(RANDBETWEEN(1,17),'Auxiliar Vendas'!D:G,2,0) -> Produto 04 | U16: 250 | V16: 13.9 | W16: 0 | X16: 10.747 | Y16: 3475 | Z16: 19 | AA16: PRFL.00.0019 | AB16: 0 | AC16: 0 | AH16: 44438.574 | AI16: 0 | AJ16: 0 | AK16: =VLOOKUP(T16,'Auxiliar Vendas'!E:F,2,FALSE) -> Produto 04 | AL16: =U16*VLOOKUP(T16,'Auxiliar Vendas'!E:G,3,FALSE) -> 150
A17: 15269738581 | B17: 28 | D17: 44438 | E17: 15058719469 | F17: =VLOOKUP(RANDBETWEEN(1,20),'DBO Compras'!AA:AC,3,0) -> Comprador 19 | G17: 30.641.041/0001-28 | H17: RUA LEONARDO NOVICKI, 1554 | I17: CAJURU | J17: CURITIBA | K17: 82930548 | L17: PR | O17: 0 | P17: 0 | R17: Atendido | S17: 15015918644 | T17: =VLOOKUP(RANDBETWEEN(1,17),'Auxiliar Vendas'!D:G,2,0) -> Produto 06 | U17: 250 | V17: 8.2 | W17: 0 | X17: 5.61 | Y17: 2050 | Z17: 19 | AA17: PRFL.00.0011 | AB17: 0 | AC17: 0 | AH17: 44438.574 | AI17: 0 | AJ17: 0 | AK17: =VLOOKUP(T17,'Auxiliar Vendas'!E:F,2,FALSE) -> Produto 06 | AL17: =U17*VLOOKUP(T17,'Auxiliar Vendas'!E:G,3,FALSE) -> 125
A18: 15269778195 | B18: 29 | D18: 44438 | E18: 15058741746 | F18: =VLOOKUP(RANDBETWEEN(1,20),'DBO Compras'!AA:AC,3,0) -> Comprador 01 | G18: 26.509.761/0001-67 | H18: AV JUSCELINO KUBITSCHEK DE OLIVEIRA, 2046, BRCAO A | I18: CIDADE INDUSTRIAL | J18: CURITIBA | K18: 81290000 | L18: PR | O18: 0 | P18: 0 | R18: Atendido | S18: 15015911944 | T18: =VLOOKUP(RANDBETWEEN(1,17),'Auxiliar Vendas'!D:G,2,0) -> Produto 01 | U18: 1000 | V18: 13.8 | W18: 0 | X18: 10.285 | Y18: 13800 | Z18: 20 | AA18: PRFL.00.0010 | AB18: 0 | AC18: 0 | AH18: 44438.574 | AI18: 0 | AJ18: 0 | AK18: =VLOOKUP(T18,'Auxiliar Vendas'!E:F,2,FALSE) -> Produto 01 | AL18: =U18*VLOOKUP(T18,'Auxiliar Vendas'!E:G,3,FALSE) -> 400
A19: 15269822282 | B19: 30 | D19: 44438 | E19: 15058669306 | F19: =VLOOKUP(RANDBETWEEN(1,20),'DBO Compras'!AA:AC,3,0) -> Comprador 18 | G19: 03.387.992/0001-40 | H19: RUA ANTONIO GRECA, 91 | I19: AHU | J19: Curitiba | K19: 82200430 | L19: PR | M19: willian@walls.com.br | N19: 4191036801 | O19: 0 | P19: 0 | R19: Atendido | S19: 15015911944 | T19: =VLOOKUP(RANDBETWEEN(1,17),'Auxiliar Vendas'!D:G,2,0) -> Produto 11 | U19: 300 | V19: 18.2 | W19: 0 | X19: 10.285 | Y19: 5460 | Z19: 17 | AA19: PRFL.00.0010 | AB19: 0 | AC19: 0 | AD19: AMANDA HUBBE | AH19: 44438.574 | AI19: 0 | AJ19: 0 | AK19: =VLOOKUP(T19,'Auxiliar Vendas'!E:F,2,FALSE) -> Produto 11 | AL19: =U19*VLOOKUP(T19,'Auxiliar Vendas'!E:G,3,FALSE) -> 330
A20: 15269822282 | B20: 30 | D20: 44438 | E20: 15058669306 | F20: =VLOOKUP(RANDBETWEEN(1,20),'DBO Compras'!AA:AC,3,0) -> Comprador 11 | G20: 03.387.992/0001-40 | H20: RUA ANTONIO GRECA, 91 | I20: AHU | J20: Curitiba | K20: 82200430 | L20: PR | M20: willian@walls.com.br | N20: 4191036801 | O20: 0 | P20: 0 | R20: Atendido | S20: 15016099089 | T20: =VLOOKUP(RANDBETWEEN(1,17),'Auxiliar Vendas'!D:G,2,0) -> Produto 16 | U20: 200 | V20: 21.3 | W20: 0 | X20: 16.8044 | Y20: 4260 | Z20: 17 | AA20: PRFL.00.0027 | AB20: 0 | AC20: 0 | AD20: AMANDA HUBBE | AH20: 44438.574 | AI20: 0 | AJ20: 0 | AK20: =VLOOKUP(T20,'Auxiliar Vendas'!E:F,2,FALSE) -> Produto 16 | AL20: =U20*VLOOKUP(T20,'Auxiliar Vendas'!E:G,3,FALSE) -> 254
A21: 15271227781 | B21: 41 | D21: 44438 | E21: 15179581888 | F21: =VLOOKUP(RANDBETWEEN(1,20),'DBO Compras'!AA:AC,3,0) -> Comprador 10 | G21: 44.114.658/0001-08 | H21: RUA JOAO RAPHAEL MACHADO, 496 | I21: Araucaria | J21: Curitiba | K21: 81350610 | L21: PR | M21: Marcio@destak.com.br | N21: 41996849234 | O21: 0 | P21: 0 | R21: Atendido | S21: 15015911944 | T21: =VLOOKUP(RANDBETWEEN(1,17),'Auxiliar Vendas'!D:G,2,0) -> Produto 02 | U21: 12040 | V21: 13.9 | W21: 0 | X21: 10.285 | Y21: 167356 | Z21: 41 | AA21: PRFL.00.0010 | AB21: 0 | AC21: 0 | AD21: HENRIQUE | AH21: 44438.383 | AI21: 0 | AJ21: 0 | AK21: =VLOOKUP(T21,'Auxiliar Vendas'!E:F,2,FALSE) -> Produto 02 | AL21: =U21*VLOOKUP(T21,'Auxiliar Vendas'!E:G,3,FALSE) -> 3250.8
A22: 15271227781 | B22: 41 | D22: 44438 | E22: 15179581888 | F22: =VLOOKUP(RANDBETWEEN(1,20),'DBO Compras'!AA:AC,3,0) -> Comprador 13 | G22: 44.114.658/0001-08 | H22: RUA JOAO RAPHAEL MACHADO, 496 | I22: Araucaria | J22: Curitiba | K22: 81350610 | L22: PR | M22: Marcio@destak.com.br | N22: 41996849234 | O22: 0 | P22: 0 | R22: Atendido | S22: 15016043939 | T22: =VLOOKUP(RANDBETWEEN(1,17),'Auxiliar Vendas'!D:G,2,0) -> Produto 04 | U22: 1000 | V22: 14 | W22: 0 | X22: 10.747 | Y22: 14000 | Z22: 41 | AA22: PRFL.00.0019 | AB22: 0 | AC22: 0 | AD22: HENRIQUE | AH22: 44438.383 | AI22: 0 | AJ22: 0 | AK22: =VLOOKUP(T22,'Auxiliar Vendas'!E:F,2,FALSE) -> Produto 04 | AL22: =U22*VLOOKUP(T22,'Auxiliar Vendas'!E:G,3,FALSE) -> 600
A23: 15271227781 | B23: 41 | D23: 44438 | E23: 15179581888 | F23: =VLOOKUP(RANDBETWEEN(1,20),'DBO Compras'!AA:AC,3,0) -> Comprador 06 | G23: 44.114.658/0001-08 | H23: RUA JOAO RAPHAEL MACHADO, 496 | I23: Araucaria | J23: Curitiba | K23: 81350610 | L23: PR | M23: Marcio@destak.com.br | N23: 41996849234 | O23: 0 | P23: 0 | R23: Atendido | S23: 15015085610 | T23: =VLOOKUP(RANDBETWEEN(1,17),'Auxiliar Vendas'!D:G,2,0) -> Produto 13 | U23: 100 | V23: 14.2 | W23: 0 | X23: 10.23 | Y23: 1420 | Z23: 41 | AA23: PRFL.00.0001 | AB23: 0 | AC23: 0 | AD23: HENRIQUE | AH23: 44438.383 | AI23: 0 | AJ23: 0 | AK23: =VLOOKUP(T23,'Auxiliar Vendas'!E:F,2,FALSE) -> Produto 13 | AL23: =U23*VLOOKUP(T23,'Auxiliar Vendas'!E:G,3,FALSE) -> 140
A24: 15271227781 | B24: 41 | D24: 44438 | E24: 15179581888 | F24: =VLOOKUP(RANDBETWEEN(1,20),'DBO Compras'!AA:AC,3,0) -> Comprador 19 | G24: 44.114.658/0001-08 | H24: RUA JOAO RAPHAEL MACHADO, 496 | I24: Araucaria | J24: Curitiba | K24: 81350610 | L24: PR | M24: Marcio@destak.com.br | N24: 41996849234 | O24: 0 | P24: 0 | R24: Atendido | S24: 15016043939 | T24: =VLOOKUP(RANDBETWEEN(1,17),'Auxiliar Vendas'!D:G,2,0) -> Produto 02 | U24: 200 | V24: 14.25 | W24: 0 | X24: 10.747 | Y24: 2850 | Z24: 41 | AA24: PRFL.00.0019 | AB24: 0 | AC24: 0 | AD24: HENRIQUE | AH24: 44438.383 | AI24: 0 | AJ24: 0 | AK24: =VLOOKUP(T24,'Auxiliar Vendas'!E:F,2,FALSE) -> Produto 02 | AL24: =U24*VLOOKUP(T24,'Auxiliar Vendas'!E:G,3,FALSE) -> 54
A25: 15271227781 | B25: 41 | D25: 44438 | E25: 15179581888 | F25: =VLOOKUP(RANDBETWEEN(1,20),'DBO Compras'!AA:AC,3,0) -> Comprador 07 | G25: 44.114.658/0001-08 | H25: RUA JOAO RAPHAEL MACHADO, 496 | I25: Araucaria | J25: Curitiba | K25: 81350610 | L25: PR | M25: Marcio@destak.com.br | N25: 41996849234 | O25: 0 | P25: 0 | R25: Atendido | S25: 15015085610 | T25: =VLOOKUP(RANDBETWEEN(1,17),'Auxiliar Vendas'!D:G,2,0) -> Produto 15 | U25: 20 | V25: 14.7 | W25: 0 | X25: 10.23 | Y25: 294 | Z25: 41 | AA25: PRFL.00.0001 | AB25: 0 | AC25: 0 | AD25: HENRIQUE | AH25: 44438.383 | AI25: 0 | AJ25: 0 | AK25: =VLOOKUP(T25,'Auxiliar Vendas'!E:F,2,FALSE) -> Produto 15 | AL25: =U25*VLOOKUP(T25,'Auxiliar Vendas'!E:G,3,FALSE) -> 28.4
A26: 15271227781 | B26: 41 | D26: 44438 | E26: 15179581888 | F26: =VLOOKUP(RANDBETWEEN(1,20),'DBO Compras'!AA:AC,3,0) -> Comprador 12 | G26: 44.114.658/0001-08 | H26: RUA JOAO RAPHAEL MACHADO, 496 | I26: Araucaria | J26: Curitiba | K26: 81350610 | L26: PR | M26: Marcio@destak.com.br | N26: 41996849234 | O26: 0 | P26: 0 | R26: Atendido | S26: 15015911944 | T26: =VLOOKUP(RANDBETWEEN(1,17),'Auxiliar Vendas'!D:G,2,0) -> Produto 17 | U26: 140 | V26: 14.9 | W26: 0 | X26: 10.285 | Y26: 2086 | Z26: 41 | AA26: PRFL.00.0010 | AB26: 0 | AC26: 0 | AD26: HENRIQUE | AH26: 44438.383 | AI26: 0 | AJ26: 0 | AK26: =VLOOKUP(T26,'Auxiliar Vendas'!E:F,2,FALSE) -> Produto 17 | AL26: =U26*VLOOKUP(T26,'Auxiliar Vendas'!E:G,3,FALSE) -> 198.8
A27: 15271227781 | B27: 41 | D27: 44438 | E27: 15179581888 | F27: =VLOOKUP(RANDBETWEEN(1,20),'DBO Compras'!AA:AC,3,0) -> Comprador 03 | G27: 44.114.658/0001-08 | H27: RUA JOAO RAPHAEL MACHADO, 496 | I27: Araucaria | J27: Curitiba | K27: 81350610 | L27: PR | M27: Marcio@destak.com.br | N27: 41996849234 | O27: 0 | P27: 0 | R27: Atendido | S27: 15015511068 | T27: =VLOOKUP(RANDBETWEEN(1,17),'Auxiliar Vendas'!D:G,2,0) -> Produto 09 | U27: 425 | V27: 13.9 | W27: 0 | X27: 10.23 | Y27: 5907.5 | Z27: 41 | AA27: PRFL.00.0005 | AB27: 0 | AC27: 0 | AD27: HENRIQUE | AH27: 44438.383 | AI27: 0 | AJ27: 0 | AK27: =VLOOKUP(T27,'Auxiliar Vendas'!E:F,2,FALSE) -> Produto 09 | AL27: =U27*VLOOKUP(T27,'Auxiliar Vendas'!E:G,3,FALSE) -> 467.5
A28: 15271227781 | B28: 41 | D28: 44438 | E28: 15179581888 | F28: =VLOOKUP(RANDBETWEEN(1,20),'DBO Compras'!AA:AC,3,0) -> Comprador 14 | G28: 44.114.658/0001-08 | H28: RUA JOAO RAPHAEL MACHADO, 496 | I28: Araucaria | J28: Curitiba | K28: 81350610 | L28: PR | M28: Marcio@destak.com.br | N28: 41996849234 | O28: 0 | P28: 0 | R28: Atendido | S28: 15015511068 | T28: =VLOOKUP(RANDBETWEEN(1,17),'Auxiliar Vendas'!D:G,2,0) -> Produto 05 | U28: 250 | V28: 16.7 | W28: 0 | X28: 10.23 | Y28: 4175 | Z28: 41 | AA28: PRFL.00.0005 | AB28: 0 | AC28: 0 | AD28: HENRIQUE | AH28: 44438.383 | AI28: 0 | AJ28: 0 | AK28: =VLOOKUP(T28,'Auxiliar Vendas'!E:F,2,FALSE) -> Produto 05 | AL28: =U28*VLOOKUP(T28,'Auxiliar Vendas'!E:G,3,FALSE) -> 150
A29: 15271227781 | B29: 41 | D29: 44438 | E29: 15179581888 | F29: =VLOOKUP(RANDBETWEEN(1,20),'DBO Compras'!AA:AC,3,0) -> Comprador 01 | G29: 44.114.658/0001-08 | H29: RUA JOAO RAPHAEL MACHADO, 496 | I29: Araucaria | J29: Curitiba | K29: 81350610 | L29: PR | M29: Marcio@destak.com.br | N29: 41996849234 | O29: 0 | P29: 0 | R29: Atendido | S29: 15015511068 | T29: =VLOOKUP(RANDBETWEEN(1,17),'Auxiliar Vendas'!D:G,2,0) -> Produto 03 | U29: 38 | V29: 17.7 | W29: 0 | X29: 10.23 | Y29: 672.6 | Z29: 41 | AA29: PRFL.00.0005 | AB29: 0 | AC29: 0 | AD29: HENRIQUE | AH29: 44438.383 | AI29: 0 | AJ29: 0 | AK29: =VLOOKUP(T29,'Auxiliar Vendas'!E:F,2,FALSE) -> Produto 03 | AL29: =U29*VLOOKUP(T29,'Auxiliar Vendas'!E:G,3,FALSE) -> 22.8
A30: 15271227781 | B30: 41 | D30: 44438 | E30: 15179581888 | F30: =VLOOKUP(RANDBETWEEN(1,20),'DBO Compras'!AA:AC,3,0) -> Comprador 13 | G30: 44.114.658/0001-08 | H30: RUA JOAO RAPHAEL MACHADO, 496 | I30: Araucaria | J30: Curitiba | K30: 81350610 | L30: PR | M30: Marcio@destak.com.br | N30: 41996849234 | O30: 0 | P30: 0 | R30: Atendido | S30: 15015918644 | T30: =VLOOKUP(RANDBETWEEN(1,17),'Auxiliar Vendas'!D:G,2,0) -> Produto 15 | U30: 6059 | V30: 8.2 | W30: 0 | X30: 5.61 | Y30: 49683.8 | Z30: 41 | AA30: PRFL.00.0011 | AB30: 0 | AC30: 0 | AD30: HENRIQUE | AH30: 44438.383 | AI30: 0 | AJ30: 0 | AK30: =VLOOKUP(T30,'Auxiliar Vendas'!E:F,2,FALSE) -> Produto 15 | AL30: =U30*VLOOKUP(T30,'Auxiliar Vendas'!E:G,3,FALSE) -> 8603.78
... A38: 15271227781 | B38: 41 | D38: 44438 | E38: 15179581888 | F38: =VLOOKUP(RANDBETWEEN(1,20),'DBO Compras'!AA:AC,3,0) -> Comprador 15 | G38: 44.114.658/0001-08 | H38: RUA JOAO RAPHAEL MACHADO, 496 | I38: Araucaria | J38: Curitiba | K38: 81350610 | L38: PR | M38: Marcio@destak.com.br | N38: 41996849234 | O38: 0 | P38: 0 | R38: Atendido | S38: 15015925662 | T38: =VLOOKUP(RANDBETWEEN(1,17),'Auxiliar Vendas'!D:G,2,0) -> Produto 16 | U38: 120 | V38: 4.99 | W38: 0 | X38: 3.74 | Y38: 598.8 | Z38: 41 | AA38: PRFL.00.0012 | AB38: 0 | AC38: 0 | AD38: HENRIQUE | AH38: 44438.383 | AI38: 0 | AJ38: 0 | AK38: =VLOOKUP(T38,'Auxiliar Vendas'!E:F,2,FALSE) -> Produto 16 | AL38: =U38*VLOOKUP(T38,'Auxiliar Vendas'!E:G,3,FALSE) -> 152.4
A39: 15279376352 | B39: 60 | D39: 44438 | E39: 15279322250 | F39: =VLOOKUP(RANDBETWEEN(1,20),'DBO Compras'!AA:AC,3,0) -> Comprador 15 | G39: 15.651.626/0001-35 | H39: RUA BRIGADEIRO FRANCO, 5024, LOJA 01 | I39: REBOUCAS | J39: Curitiba | K39: 80220100 | L39: PR | M39: Diego@Drywall.com.br | N39: 41993330017 | O39: 0 | P39: 0 | R39: Atendido | S39: 15015085610 | T39: =VLOOKUP(RANDBETWEEN(1,17),'Auxiliar Vendas'!D:G,2,0) -> Produto 07 | U39: 700 | V39: 13.9 | W39: 0 | X39: 10.23 | Y39: 9730 | Z39: 68 | AA39: PRFL.00.0001 | AB39: 0 | AC39: 0 | AH39: 44438.469 | AI39: 0 | AJ39: 0 | AK39: =VLOOKUP(T39,'Auxiliar Vendas'!E:F,2,FALSE) -> Produto 07 | AL39: =U39*VLOOKUP(T39,'Auxiliar Vendas'!E:G,3,FALSE) -> 770
A40: 15279376352 | B40: 60 | D40: 44438 | E40: 15279322250 | F40: =VLOOKUP(RANDBETWEEN(1,20),'DBO Compras'!AA:AC,3,0) -> Comprador 07 | G40: 15.651.626/0001-35 | H40: RUA BRIGADEIRO FRANCO, 5024, LOJA 01 | I40: REBOUCAS | J40: Curitiba | K40: 80220100 | L40: PR | M40: Diego@Drywall.com.br | N40: 41993330017 | O40: 0 | P40: 0 | R40: Atendido | S40: 15015353721 | T40: =VLOOKUP(RANDBETWEEN(1,17),'Auxiliar Vendas'!D:G,2,0) -> Produto 14 | U40: 700 | V40: 8.2 | W40: 0 | X40: 5.58 | Y40: 5740 | Z40: 68 | AA40: PRFL.00.0002 | AB40: 0 | AC40: 0 | AH40: 44438.469 | AI40: 0 | AJ40: 0 | AK40: =VLOOKUP(T40,'Auxiliar Vendas'!E:F,2,FALSE) -> Produto 14 | AL40: =U40*VLOOKUP(T40,'Auxiliar Vendas'!E:G,3,FALSE) -> 980
A41: 15279376352 | B41: 60 | D41: 44438 | E41: 15279322250 | F41: =VLOOKUP(RANDBETWEEN(1,20),'DBO Compras'!AA:AC,3,0) -> Comprador 09 | G41: 15.651.626/0001-35 | H41: RUA BRIGADEIRO FRANCO, 5024, LOJA 01 | I41: REBOUCAS | J41: Curitiba | K41: 80220100 | L41: PR | M41: Diego@Drywall.com.br | N41: 41993330017 | O41: 0 | P41: 0 | R41: Atendido | S41: 15015867005 | T41: =VLOOKUP(RANDBETWEEN(1,17),'Auxiliar Vendas'!D:G,2,0) -> Produto 12 | U41: 194 | V41: 18.2 | W41: 0 | X41: 13.764 | Y41: 3530.8 | Z41: 68 | AA41: PRFL.00.0008 | AB41: 0 | AC41: 0 | AH41: 44438.469 | AI41: 0 | AJ41: 0 | AK41: =VLOOKUP(T41,'Auxiliar Vendas'!E:F,2,FALSE) -> Produto 12 | AL41: =U41*VLOOKUP(T41,'Auxiliar Vendas'!E:G,3,FALSE) -> 271.6
A42: 15279376352 | B42: 60 | D42: 44438 | E42: 15279322250 | F42: =VLOOKUP(RANDBETWEEN(1,20),'DBO Compras'!AA:AC,3,0) -> Comprador 08 | G42: 15.651.626/0001-35 | H42: RUA BRIGADEIRO FRANCO, 5024, LOJA 01 | I42: REBOUCAS | J42: Curitiba | K42: 80220100 | L42: PR | M42: Diego@Drywall.com.br | N42: 41993330017 | O42: 0 | P42: 0 | R42: Atendido | S42: 15016093155 | T42: =VLOOKUP(RANDBETWEEN(1,17),'Auxiliar Vendas'!D:G,2,0) -> Produto 14 | U42: 6 | V42: 18.2 | W42: 0 | X42: 14.4596 | Y42: 109.2 | Z42: 68 | AA42: PRFL.00.0026 | AB42: 0 | AC42: 0 | AH42: 44438.469 | AI42: 0 | AJ42: 0 | AK42: =VLOOKUP(T42,'Auxiliar Vendas'!E:F,2,FALSE) -> Produto 14 | AL42: =U42*VLOOKUP(T42,'Auxiliar Vendas'!E:G,3,FALSE) -> 8.4
A43: 15293132741 | B43: 95 | D43: 44442 | E43: 15291803674 | F43: =VLOOKUP(RANDBETWEEN(1,20),'DBO Compras'!AA:AC,3,0) -> Comprador 10 | G43: 42.010.522/0001-14 | H43: RUA BLUMENAU, 101, GALPAO:01 | I43: centro | J43: Balneário Camboriú | K43: 88337440 | L43: SC | M43: Elizeu@Decorgesso.com.br | N43: 47996529345 | O43: 0 | P43: 0 | R43: Atendido | S43: 15016043939 | T43: =VLOOKUP(RANDBETWEEN(1,17),'Auxiliar Vendas'!D:G,2,0) -> Produto 16 | U43: 1000 | V43: 13.99 | W43: 0 | X43: 10.747 | Y43: 13990 | Z43: 73 | AA43: PRFL.00.0019 | AB43: 0 | AC43: 0 | AH43: 44442.578 | AI43: 0 | AJ43: 0 | AK43: =VLOOKUP(T43,'Auxiliar Vendas'!E:F,2,FALSE) -> Produto 16 | AL43: =U43*VLOOKUP(T43,'Auxiliar Vendas'!E:G,3,FALSE) -> 1270
A44: 15280230788 | B44: 65 | D44: 44466 | E44: 15179608501 | F44: =VLOOKUP(RANDBETWEEN(1,20),'DBO Compras'!AA:AC,3,0) -> Comprador 06 | G44: 25.195.001/0001-60 | H44: RUA ITACIANO MARCONDES, 47 | I44: SANTA CANDIDA | J44: Curitiba | K44: 82720070 | L44: PR | M44: Delta@Delta.com.br | N44: 41992354686 | O44: 0 | P44: 0 | R44: Atendido | S44: 15016099089 | T44: =VLOOKUP(RANDBETWEEN(1,17),'Auxiliar Vendas'!D:G,2,0) -> Produto 13 | U44: 200 | V44: 19.17 | W44: 0 | X44: 16.8044 | Y44: 3834 | Z44: 42 | AA44: PRFL.00.0027 | AB44: 0 | AC44: 0 | AH44: 44466.492 | AI44: 0 | AJ44: 0 | AK44: =VLOOKUP(T44,'Auxiliar Vendas'!E:F,2,FALSE) -> Produto 13 | AL44: =U44*VLOOKUP(T44,'Auxiliar Vendas'!E:G,3,FALSE) -> 280
A45: 15280230788 | B45: 65 | D45: 44466 | E45: 15179608501 | F45: =VLOOKUP(RANDBETWEEN(1,20),'DBO Compras'!AA:AC,3,0) -> Comprador 04 | G45: 25.195.001/0001-60 | H45: RUA ITACIANO MARCONDES, 47 | I45: SANTA CANDIDA | J45: Curitiba | K45: 82720070 | L45: PR | M45: Delta@Delta.com.br | N45: 41992354686 | O45: 0 | P45: 0 | R45: Atendido | S45: 15016099089 | T45: =VLOOKUP(RANDBETWEEN(1,17),'Auxiliar Vendas'!D:G,2,0) -> Produto 08 | U45: 200 | V45: 21.3 | W45: 0 | X45: 16.8044 | Y45: 4260 | Z45: 42 | AA45: PRFL.00.0027 | AB45: 0 | AC45: 0 | AH45: 44466.492 | AI45: 0 | AJ45: 0 | AK45: =VLOOKUP(T45,'Auxiliar Vendas'!E:F,2,FALSE) -> Produto 08 | AL45: =U45*VLOOKUP(T45,'Auxiliar Vendas'!E:G,3,FALSE) -> 220
A46: 15294739206 | B46: 102 | D46: 44468 | E46: 15179784707 | F46: =VLOOKUP(RANDBETWEEN(1,20),'DBO Compras'!AA:AC,3,0) -> Comprador 13 | G46: 18.552.908/0001-73 | H46: Rua Rio Tibagi, 787 | I46: Jardim Santo Amaro | J46: Cambé | K46: 86185130 | L46: PR | M46: amanda.hubbe@perfilar.ind.br | N46: 41996084664 | O46: 0 | P46: 0 | R46: Atendido | S46: 15015511068 | T46: =VLOOKUP(RANDBETWEEN(1,17),'Auxiliar Vendas'!D:G,2,0) -> Produto 05 | U46: 100 | V46: 16.7 | W46: 0 | X46: 10.23 | Y46: 1670 | Z46: 49 | AA46: PRFL.00.0005 | AB46: 0 | AC46: 0 | AH46: 44468.363 | AI46: 0 | AJ46: 0 | AK46: =VLOOKUP(T46,'Auxiliar Vendas'!E:F,2,FALSE) -> Produto 05 | AL46: =U46*VLOOKUP(T46,'Auxiliar Vendas'!E:G,3,FALSE) -> 60
A47: 15294739206 | B47: 102 | D47: 44468 | E47: 15179784707 | F47: =VLOOKUP(RANDBETWEEN(1,20),'DBO Compras'!AA:AC,3,0) -> Comprador 18 | G47: 18.552.908/0001-73 | H47: Rua Rio Tibagi, 787 | I47: Jardim Santo Amaro | J47: Cambé | K47: 86185130 | L47: PR | M47: amanda.hubbe@perfilar.ind.br | N47: 41996084664 | O47: 0 | P47: 0 | R47: Atendido | S47: 15016080333 | T47: =VLOOKUP(RANDBETWEEN(1,17),'Auxiliar Vendas'!D:G,2,0) -> Produto 08 | U47: 100 | V47: 15.5 | W47: 0 | X47: 10.747 | Y47: 1550 | Z47: 49 | AA47: PRFL.00.0024 | AB47: 0 | AC47: 0 | AH47: 44468.363 | AI47: 0 | AJ47: 0 | AK47: =VLOOKUP(T47,'Auxiliar Vendas'!E:F,2,FALSE) -> Produto 08 | AL47: =U47*VLOOKUP(T47,'Auxiliar Vendas'!E:G,3,FALSE) -> 110
A48: 15294739206 | B48: 102 | D48: 44468 | E48: 15179784707 | F48: =VLOOKUP(RANDBETWEEN(1,20),'DBO Compras'!AA:AC,3,0) -> Comprador 19 | G48: 18.552.908/0001-73 | H48: Rua Rio Tibagi, 787 | I48: Jardim Santo Amaro | J48: Cambé | K48: 86185130 | L48: PR | M48: amanda.hubbe@perfilar.ind.br | N48: 41996084664 | O48: 0 | P48: 0 | R48: Atendido | S48: 15016093155 | T48: =VLOOKUP(RANDBETWEEN(1,17),'Auxiliar Vendas'!D:G,2,0) -> Produto 06 | U48: 150 | V48: 18.6 | W48: 0 | X48: 14.4596 | Y48: 2790 | Z48: 49 | AA48: PRFL.00.0026 | AB48: 0 | AC48: 0 | AH48: 44468.363 | AI48: 0 | AJ48: 0 | AK48: =VLOOKUP(T48,'Auxiliar Vendas'!E:F,2,FALSE) -> Produto 06 | AL48: =U48*VLOOKUP(T48,'Auxiliar Vendas'!E:G,3,FALSE) -> 75
A49: 15270293212 | B49: 31 | D49: 44469 | E49: 15058764044 | F49: =VLOOKUP(RANDBETWEEN(1,20),'DBO Compras'!AA:AC,3,0) -> Comprador 10 | G49: 36.957.725/0001-10 | H49: RUA BENJAMIM CONSTANT, 322 | I49: CENTRO | J49: UNIAO DA VITORIA | K49: 84600290 | L49: PR | O49: 0 | P49: 0 | R49: Atendido | S49: 15016043939 | T49: =VLOOKUP(RANDBETWEEN(1,17),'Auxiliar Vendas'!D:G,2,0) -> Produto 05 | U49: 200 | V49: 14.25 | W49: 0 | X49: 10.747 | Y49: 2850 | Z49: 21 | AA49: PRFL.00.0019 | AB49: 0 | AC49: 0 | AH49: 44469.574 | AI49: 0 | AJ49: 0 | AK49: =VLOOKUP(T49,'Auxiliar Vendas'!E:F,2,FALSE) -> Produto 05 | AL49: =U49*VLOOKUP(T49,'Auxiliar Vendas'!E:G,3,FALSE) -> 120
A50: 15270293212 | B50: 31 | D50: 44469 | E50: 15058764044 | F50: =VLOOKUP(RANDBETWEEN(1,20),'DBO Compras'!AA:AC,3,0) -> Comprador 16 | G50: 36.957.725/0001-10 | H50: RUA BENJAMIM CONSTANT, 322 | I50: CENTRO | J50: UNIAO DA VITORIA | K50: 84600290 | L50: PR | O50: 0 | P50: 0 | R50: Atendido | S50: 15015511068 | T50: =VLOOKUP(RANDBETWEEN(1,17),'Auxiliar Vendas'!D:G,2,0) -> Produto 17 | U50: 150 | V50: 16.7001 | W50: 0 | X50: 10.23 | Y50: 2505.015 | Z50: 21 | AA50: PRFL.00.0005 | AB50: 0 | AC50: 0 | AH50: 44469.574 | AI50: 0 | AJ50: 0 | AK50: =VLOOKUP(T50,'Auxiliar Vendas'!E:F,2,FALSE) -> Produto 17 | AL50: =U50*VLOOKUP(T50,'Auxiliar Vendas'!E:G,3,FALSE) -> 213
A51: 15270293212 | B51: 31 | D51: 44469 | E51: 15058764044 | F51: =VLOOKUP(RANDBETWEEN(1,20),'DBO Compras'!AA:AC,3,0) -> Comprador 14 | G51: 36.957.725/0001-10 | H51: RUA BENJAMIM CONSTANT, 322 | I51: CENTRO | J51: UNIAO DA VITORIA | K51: 84600290 | L51: PR | O51: 0 | P51: 0 | R51: Atendido | S51: 15015918644 | T51: =VLOOKUP(RANDBETWEEN(1,17),'Auxiliar Vendas'!D:G,2,0) -> Produto 05 | U51: 160 | V51: 8.3801 | W51: 0 | X51: 5.61 | Y51: 1340.816 | Z51: 21 | AA51: PRFL.00.0011 | AB51: 0 | AC51: 0 | AH51: 44469.574 | AI51: 0 | AJ51: 0 | AK51: =VLOOKUP(T51,'Auxiliar Vendas'!E:F,2,FALSE) -> Produto 05 | AL51: =U51*VLOOKUP(T51,'Auxiliar Vendas'!E:G,3,FALSE) -> 96
A52: 15270293212 | B52: 31 | D52: 44469 | E52: 15058764044 | F52: =VLOOKUP(RANDBETWEEN(1,20),'DBO Compras'!AA:AC,3,0) -> Comprador 12 | G52: 36.957.725/0001-10 | H52: RUA BENJAMIM CONSTANT, 322 | I52: CENTRO | J52: UNIAO DA VITORIA | K52: 84600290 | L52: PR | O52: 0 | P52: 0 | R52: Atendido | S52: 15016087271 | T52: =VLOOKUP(RANDBETWEEN(1,17),'Auxiliar Vendas'!D:G,2,0) -> Produto 14 | U52: 100 | V52: 18.7 | W52: 0 | X52: 14.4596 | Y52: 1870 | Z52: 21 | AA52: PRFL.00.0025 | AB52: 0 | AC52: 0 | AH52: 44469.574 | AI52: 0 | AJ52: 0 | AK52: =VLOOKUP(T52,'Auxiliar Vendas'!E:F,2,FALSE) -> Produto 14 | AL52: =U52*VLOOKUP(T52,'Auxiliar Vendas'!E:G,3,FALSE) -> 140
A53: 15270293212 | B53: 31 | D53: 44469 | E53: 15058764044 | F53: =VLOOKUP(RANDBETWEEN(1,20),'DBO Compras'!AA:AC,3,0) -> Comprador 02 | G53: 36.957.725/0001-10 | H53: RUA BENJAMIM CONSTANT, 322 | I53: CENTRO | J53: UNIAO DA VITORIA | K53: 84600290 | L53: PR | O53: 0 | P53: 0 | R53: Atendido | S53: 15016099089 | T53: =VLOOKUP(RANDBETWEEN(1,17),'Auxiliar Vendas'!D:G,2,0) -> Produto 05 | U53: 230 | V53: 21.3 | W53: 0 | X53: 16.8044 | Y53: 4899 | Z53: 21 | AA53: PRFL.00.0027 | AB53: 0 | AC53: 0 | AH53: 44469.574 | AI53: 0 | AJ53: 0 | AK53: =VLOOKUP(T53,'Auxiliar Vendas'!E:F,2,FALSE) -> Produto 05 | AL53: =U53*VLOOKUP(T53,'Auxiliar Vendas'!E:G,3,FALSE) -> 138
A54: 15270673210 | B54: 32 | D54: 44469 | E54: 15058669306 | F54: =VLOOKUP(RANDBETWEEN(1,20),'DBO Compras'!AA:AC,3,0) -> Comprador 11 | G54: 03.387.992/0001-40 | H54: RUA ANTONIO GRECA, 91 | I54: AHU | J54: Curitiba | K54: 82200430 | L54: PR | M54: willian@walls.com.br | N54: 4191036801 | O54: 0 | P54: 0 | R54: Atendido | S54: 15015511068 | T54: =VLOOKUP(RANDBETWEEN(1,17),'Auxiliar Vendas'!D:G,2,0) -> Produto 17 | U54: 200 | V54: 16.2 | W54: 0 | X54: 10.23 | Y54: 3240 | Z54: 17 | AA54: PRFL.00.0005 | AB54: 0 | AC54: 0 | AH54: 44469.574 | AI54: 0 | AJ54: 0 | AK54: =VLOOKUP(T54,'Auxiliar Vendas'!E:F,2,FALSE) -> Produto 17 | AL54: =U54*VLOOKUP(T54,'Auxiliar Vendas'!E:G,3,FALSE) -> 284
A55: 15270673210 | B55: 32 | D55: 44469 | E55: 15058669306 | F55: =VLOOKUP(RANDBETWEEN(1,20),'DBO Compras'!AA:AC,3,0) -> Comprador 20 | G55: 03.387.992/0001-40 | H55: RUA ANTONIO GRECA, 91 | I55: AHU | J55: Curitiba | K55: 82200430 | L55: PR | M55: willian@walls.com.br | N55: 4191036801 | O55: 0 | P55: 0 | R55: Atendido | S55: 15016099089 | T55: =VLOOKUP(RANDBETWEEN(1,17),'Auxiliar Vendas'!D:G,2,0) -> Produto 01 | U55: 300 | V55: 21.3 | W55: 0 | X55: 16.8044 | Y55: 6390 | Z55: 17 | AA55: PRFL.00.0027 | AB55: 0 | AC55: 0 | AH55: 44469.574 | AI55: 0 | AJ55: 0 | AK55: =VLOOKUP(T55,'Auxiliar Vendas'!E:F,2,FALSE) -> Produto 01 | AL55: =U55*VLOOKUP(T55,'Auxiliar Vendas'!E:G,3,FALSE) -> 120
A56: 15270673210 | B56: 32 | D56: 44469 | E56: 15058669306 | F56: =VLOOKUP(RANDBETWEEN(1,20),'DBO Compras'!AA:AC,3,0) -> Comprador 14 | G56: 03.387.992/0001-40 | H56: RUA ANTONIO GRECA, 91 | I56: AHU | J56: Curitiba | K56: 82200430 | L56: PR | M56: willian@walls.com.br | N56: 4191036801 | O56: 0 | P56: 0 | R56: Atendido | S56: 15016087271 | T56: =VLOOKUP(RANDBETWEEN(1,17),'Auxiliar Vendas'!D:G,2,0) -> Produto 03 | U56: 200 | V56: 18.2 | W56: 0 | X56: 14.4596 | Y56: 3640 | Z56: 17 | AA56: PRFL.00.0025 | AB56: 0 | AC56: 0 | AH56: 44469.574 | AI56: 0 | AJ56: 0 | AK56: =VLOOKUP(T56,'Auxiliar Vendas'!E:F,2,FALSE) -> Produto 03 | AL56: =U56*VLOOKUP(T56,'Auxiliar Vendas'!E:G,3,FALSE) -> 120
A57: 15270738302 | B57: 33 | D57: 44469 | E57: 15058814973 | F57: =VLOOKUP(RANDBETWEEN(1,20),'DBO Compras'!AA:AC,3,0) -> Comprador 14 | G57: 03.101.294/0001-36 | H57: R MARECHAL DEODORO, 869, 19 ANDAR | I57: CENTRO | J57: Curitiba | K57: 80060-010 | L57: PR | O57: 0 | P57: 0 | R57: Atendido | S57: 15015918644 | T57: =VLOOKUP(RANDBETWEEN(1,17),'Auxiliar Vendas'!D:G,2,0) -> Produto 12 | U57: 250 | V57: 8.2 | W57: 0 | X57: 5.61 | Y57: 2050 | Z57: 22 | AA57: PRFL.00.0011 | AB57: 0 | AC57: 0 | AH57: 44469.574 | AI57: 0 | AJ57: 0 | AK57: =VLOOKUP(T57,'Auxiliar Vendas'!E:F,2,FALSE) -> Produto 12 | AL57: =U57*VLOOKUP(T57,'Auxiliar Vendas'!E:G,3,FALSE) -> 350
A58: 15270798343 | B58: 34 | D58: 44469 | E58: 15058861864 | F58: =VLOOKUP(RANDBETWEEN(1,20),'DBO Compras'!AA:AC,3,0) -> Comprador 14 | G58: 24.623.275/0001-40 | H58: AV PARANA , 8455 | I58: ZONA I | J58: Umuarama | K58: 87502-000 | L58: PR | O58: 0 | P58: 0 | R58: Atendido | S58: 15016099089 | T58: =VLOOKUP(RANDBETWEEN(1,17),'Auxiliar Vendas'!D:G,2,0) -> Produto 14 | U58: 122 | V58: 21.3 | W58: 0 | X58: 16.8044 | Y58: 2598.6 | Z58: 23 | AA58: PRFL.00.0027 | AB58: 0 | AC58: 0 | AH58: 44469.574 | AI58: 0 | AJ58: 0 | AK58: =VLOOKUP(T58,'Auxiliar Vendas'!E:F,2,FALSE) -> Produto 14 | AL58: =U58*VLOOKUP(T58,'Auxiliar Vendas'!E:G,3,FALSE) -> 170.8
A59: 15270798343 | B59: 34 | D59: 44469 | E59: 15058861864 | F59: =VLOOKUP(RANDBETWEEN(1,20),'DBO Compras'!AA:AC,3,0) -> Comprador 12 | G59: 24.623.275/0001-40 | H59: AV PARANA , 8455 | I59: ZONA I | J59: Umuarama | K59: 87502-000 | L59: PR | O59: 0 | P59: 0 | R59: Atendido | S59: 15016087271 | T59: =VLOOKUP(RANDBETWEEN(1,17),'Auxiliar Vendas'!D:G,2,0) -> Produto 13 | U59: 34 | V59: 18.2 | W59: 0 | X59: 14.4596 | Y59: 618.8 | Z59: 23 | AA59: PRFL.00.0025 | AB59: 0 | AC59: 0 | AH59: 44469.574 | AI59: 0 | AJ59: 0 | AK59: =VLOOKUP(T59,'Auxiliar Vendas'!E:F,2,FALSE) -> Produto 13 | AL59: =U59*VLOOKUP(T59,'Auxiliar Vendas'!E:G,3,FALSE) -> 47.6
A60: 15270933856 | B60: 36 | D60: 44469 | E60: 15058741746 | F60: =VLOOKUP(RANDBETWEEN(1,20),'DBO Compras'!AA:AC,3,0) -> Comprador 15 | G60: 26.509.761/0001-67 | H60: AV JUSCELINO KUBITSCHEK DE OLIVEIRA, 2046, BRCAO A | I60: CIDADE INDUSTRIAL | J60: CURITIBA | K60: 81290000 | L60: PR | O60: 0 | P60: 0 | R60: Atendido | S60: 15016099089 | T60: =VLOOKUP(RANDBETWEEN(1,17),'Auxiliar Vendas'!D:G,2,0) -> Produto 01 | U60: 200 | V60: 21.3 | W60: 0 | X60: 16.8044 | Y60: 4260 | Z60: 20 | AA60: PRFL.00.0027 | AB60: 0 | AC60: 0 | AH60: 44469.574 | AI60: 0 | AJ60: 0 | AK60: =VLOOKUP(T60,'Auxiliar Vendas'!E:F,2,FALSE) -> Produto 01 | AL60: =U60*VLOOKUP(T60,'Auxiliar Vendas'!E:G,3,FALSE) -> 80
A61: 15270933856 | B61: 36 | D61: 44469 | E61: 15058741746 | F61: =VLOOKUP(RANDBETWEEN(1,20),'DBO Compras'!AA:AC,3,0) -> Comprador 03 | G61: 26.509.761/0001-67 | H61: AV JUSCELINO KUBITSCHEK DE OLIVEIRA, 2046, BRCAO A | I61: CIDADE INDUSTRIAL | J61: CURITIBA | K61: 81290000 | L61: PR | O61: 0 | P61: 0 | R61: Atendido | S61: 15015918644 | T61: =VLOOKUP(RANDBETWEEN(1,17),'Auxiliar Vendas'!D:G,2,0) -> Produto 07 | U61: 500 | V61: 8.2 | W61: 0 | X61: 5.61 | Y61: 4100 | Z61: 20 | AA61: PRFL.00.0011 | AB61: 0 | AC61: 0 | AH61: 44469.574 | AI61: 0 | AJ61: 0 | AK61: =VLOOKUP(T61,'Auxiliar Vendas'!E:F,2,FALSE) -> Produto 07 | AL61: =U61*VLOOKUP(T61,'Auxiliar Vendas'!E:G,3,FALSE) -> 550
A62: 15271037296 | B62: 37 | D62: 44469 | E62: 15058915459 | F62: =VLOOKUP(RANDBETWEEN(1,20),'DBO Compras'!AA:AC,3,0) -> Comprador 10 | G62: 172.265.119-91 | H62: Rua Arthur Thomas, 235, AP 1702 | I62: Zona 01 | J62: Maringá | K62: 87013250 | L62: PR | O62: 0 | P62: 0 | R62: Atendido | S62: 15015511068 | T62: =VLOOKUP(RANDBETWEEN(1,17),'Auxiliar Vendas'!D:G,2,0) -> Produto 13 | U62: 78 | V62: 16.7 | W62: 0 | X62: 10.23 | Y62: 1302.6 | Z62: 25 | AA62: PRFL.00.0005 | AB62: 0 | AC62: 0 | AH62: 44469.575 | AI62: 0 | AJ62: 0 | AK62: =VLOOKUP(T62,'Auxiliar Vendas'!E:F,2,FALSE) -> Produto 13 | AL62: =U62*VLOOKUP(T62,'Auxiliar Vendas'!E:G,3,FALSE) -> 109.2
A63: 15271037296 | B63: 37 | D63: 44469 | E63: 15058915459 | F63: =VLOOKUP(RANDBETWEEN(1,20),'DBO Compras'!AA:AC,3,0) -> Comprador 01 | G63: 172.265.119-91 | H63: Rua Arthur Thomas, 235, AP 1702 | I63: Zona 01 | J63: Maringá | K63: 87013250 | L63: PR | O63: 0 | P63: 0 | R63: Atendido | S63: 15015911944 | T63: =VLOOKUP(RANDBETWEEN(1,17),'Auxiliar Vendas'!D:G,2,0) -> Produto 05 | U63: 155 | V63: 14.25 | W63: 0 | X63: 10.285 | Y63: 2208.75 | Z63: 25 | AA63: PRFL.00.0010 | AB63: 0 | AC63: 0 | AH63: 44469.575 | AI63: 0 | AJ63: 0 | AK63: =VLOOKUP(T63,'Auxiliar Vendas'!E:F,2,FALSE) -> Produto 05 | AL63: =U63*VLOOKUP(T63,'Auxiliar Vendas'!E:G,3,FALSE) -> 93
A64: 15271071632 | B64: 38 | D64: 44469 | E64: 15058876151 | F64: =VLOOKUP(RANDBETWEEN(1,20),'DBO Compras'!AA:AC,3,0) -> Comprador 19 | G64: 14.709.771/0001-67 | H64: RUA SANTA TEREZINHA, 669 | I64: JD SAO RAFAEL | J64: Londrina | K64: 86027620 | L64: PR | M64: genio.gesso@gmail.com | N64: 43996560102 | O64: 0 | P64: 0 | R64: Atendido | S64: 15016099089 | T64: =VLOOKUP(RANDBETWEEN(1,17),'Auxiliar Vendas'!D:G,2,0) -> Produto 12 | U64: 460 | V64: 21.75 | W64: 0 | X64: 16.8044 | Y64: 10005 | Z64: 24 | AA64: PRFL.00.0027 | AB64: 0 | AC64: 0 | AH64: 44469.575 | AI64: 0 | AJ64: 0 | AK64: =VLOOKUP(T64,'Auxiliar Vendas'!E:F,2,FALSE) -> Produto 12 | AL64: =U64*VLOOKUP(T64,'Auxiliar Vendas'!E:G,3,FALSE) -> 644
A65: 15271183865 | B65: 39 | D65: 44469 | E65: 15058959920 | F65: =VLOOKUP(RANDBETWEEN(1,20),'DBO Compras'!AA:AC,3,0) -> Comprador 11 | G65: 14.972.161/0001-51 | H65: Rua Poeta Carlos Drumond de Andrade, S/N, CASA B | I65: Parque Avenida | J65: Maringá | K65: 87025540 | L65: PR | M65: amanda.hubbe@perfilar.ind.br | N65: 4441413353 | O65: 0 | P65: 0 | R65: Atendido | S65: 15016043939 | T65: =VLOOKUP(RANDBETWEEN(1,17),'Auxiliar Vendas'!D:G,2,0) -> Produto 12 | U65: 122 | V65: 14.25 | W65: 0 | X65: 10.747 | Y65: 1738.5 | Z65: 26 | AA65: PRFL.00.0019 | AB65: 0 | AC65: 0 | AH65: 44469.575 | AI65: 0 | AJ65: 0 | AK65: =VLOOKUP(T65,'Auxiliar Vendas'!E:F,2,FALSE) -> Produto 12 | AL65: =U65*VLOOKUP(T65,'Auxiliar Vendas'!E:G,3,FALSE) -> 170.8
A66: 15271183865 | B66: 39 | D66: 44469 | E66: 15058959920 | F66: =VLOOKUP(RANDBETWEEN(1,20),'DBO Compras'!AA:AC,3,0) -> Comprador 19 | G66: 14.972.161/0001-51 | H66: Rua Poeta Carlos Drumond de Andrade, S/N, CASA B | I66: Parque Avenida | J66: Maringá | K66: 87025540 | L66: PR | M66: amanda.hubbe@perfilar.ind.br | N66: 4441413353 | O66: 0 | P66: 0 | R66: Atendido | S66: 15015511068 | T66: =VLOOKUP(RANDBETWEEN(1,17),'Auxiliar Vendas'!D:G,2,0) -> Produto 02 | U66: 78 | V66: 14.7 | W66: 0 | X66: 10.23 | Y66: 1146.6 | Z66: 26 | AA66: PRFL.00.0005 | AB66: 0 | AC66: 0 | AH66: 44469.575 | AI66: 0 | AJ66: 0 | AK66: =VLOOKUP(T66,'Auxiliar Vendas'!E:F,2,FALSE) -> Produto 02 | AL66: =U66*VLOOKUP(T66,'Auxiliar Vendas'!E:G,3,FALSE) -> 21.06
A67: 15271183865 | B67: 39 | D67: 44469 | E67: 15058959920 | F67: =VLOOKUP(RANDBETWEEN(1,20),'DBO Compras'!AA:AC,3,0) -> Comprador 20 | G67: 14.972.161/0001-51 | H67: Rua Poeta Carlos Drumond de Andrade, S/N, CASA B | I67: Parque Avenida | J67: Maringá | K67: 87025540 | L67: PR | M67: amanda.hubbe@perfilar.ind.br | N67: 4441413353 | O67: 0 | P67: 0 | R67: Atendido | S67: 15015918644 | T67: =VLOOKUP(RANDBETWEEN(1,17),'Auxiliar Vendas'!D:G,2,0) -> Produto 01 | U67: 100 | V67: 8.38 | W67: 0 | X67: 5.61 | Y67: 838 | Z67: 26 | AA67: PRFL.00.0011 | AB67: 0 | AC67: 0 | AH67: 44469.575 | AI67: 0 | AJ67: 0 | AK67: =VLOOKUP(T67,'Auxiliar Vendas'!E:F,2,FALSE) -> Produto 01 | AL67: =U67*VLOOKUP(T67,'Auxiliar Vendas'!E:G,3,FALSE) -> 40
A68: 15271183865 | B68: 39 | D68: 44469 | E68: 15058959920 | F68: =VLOOKUP(RANDBETWEEN(1,20),'DBO Compras'!AA:AC,3,0) -> Comprador 08 | G68: 14.972.161/0001-51 | H68: Rua Poeta Carlos Drumond de Andrade, S/N, CASA B | I68: Parque Avenida | J68: Maringá | K68: 87025540 | L68: PR | M68: amanda.hubbe@perfilar.ind.br | N68: 4441413353 | O68: 0 | P68: 0 | R68: Atendido | S68: 15016093155 | T68: =VLOOKUP(RANDBETWEEN(1,17),'Auxiliar Vendas'!D:G,2,0) -> Produto 07 | U68: 60 | V68: 18.65 | W68: 0 | X68: 14.4596 | Y68: 1119 | Z68: 26 | AA68: PRFL.00.0026 | AB68: 0 | AC68: 0 | AH68: 44469.575 | AI68: 0 | AJ68: 0 | AK68: =VLOOKUP(T68,'Auxiliar Vendas'!E:F,2,FALSE) -> Produto 07 | AL68: =U68*VLOOKUP(T68,'Auxiliar Vendas'!E:G,3,FALSE) -> 66
A69: 15271183865 | B69: 39 | D69: 44469 | E69: 15058959920 | F69: =VLOOKUP(RANDBETWEEN(1,20),'DBO Compras'!AA:AC,3,0) -> Comprador 10 | G69: 14.972.161/0001-51 | H69: Rua Poeta Carlos Drumond de Andrade, S/N, CASA B | I69: Parque Avenida | J69: Maringá | K69: 87025540 | L69: PR | M69: amanda.hubbe@perfilar.ind.br | N69: 4441413353 | O69: 0 | P69: 0 | R69: Atendido | S69: 15016080333 | T69: =VLOOKUP(RANDBETWEEN(1,17),'Auxiliar Vendas'!D:G,2,0) -> Produto 01 | U69: 20 | V69: 15.5 | W69: 0 | X69: 10.747 | Y69: 310 | Z69: 26 | AA69: PRFL.00.0024 | AB69: 0 | AC69: 0 | AH69: 44469.575 | AI69: 0 | AJ69: 0 | AK69: =VLOOKUP(T69,'Auxiliar Vendas'!E:F,2,FALSE) -> Produto 01 | AL69: =U69*VLOOKUP(T69,'Auxiliar Vendas'!E:G,3,FALSE) -> 8
A70: 15271224426 | B70: 40 | D70: 44469 | E70: 15058990861 | F70: =VLOOKUP(RANDBETWEEN(1,20),'DBO Compras'!AA:AC,3,0) -> Comprador 08 | G70: 913.178.439-91 | H70: Avenida Cerro Azul, 2649 | I70: Jardim Novo Horizonte | J70: Maringá | K70: 87010055 | L70: PR | O70: 0 | P70: 0 | R70: Atendido | S70: 15016043939 | T70: =VLOOKUP(RANDBETWEEN(1,17),'Auxiliar Vendas'!D:G,2,0) -> Produto 06 | U70: 153 | V70: 14.25 | W70: 0 | X70: 10.747 | Y70: 2180.25 | Z70: 27 | AA70: PRFL.00.0019 | AB70: 0 | AC70: 0 | AH70: 44469.575 | AI70: 0 | AJ70: 0 | AK70: =VLOOKUP(T70,'Auxiliar Vendas'!E:F,2,FALSE) -> Produto 06 | AL70: =U70*VLOOKUP(T70,'Auxiliar Vendas'!E:G,3,FALSE) -> 76.5
A71: 15271224426 | B71: 40 | D71: 44469 | E71: 15058990861 | F71: =VLOOKUP(RANDBETWEEN(1,20),'DBO Compras'!AA:AC,3,0) -> Comprador 04 | G71: 913.178.439-91 | H71: Avenida Cerro Azul, 2649 | I71: Jardim Novo Horizonte | J71: Maringá | K71: 87010055 | L71: PR | O71: 0 | P71: 0 | R71: Atendido | S71: 15015511068 | T71: =VLOOKUP(RANDBETWEEN(1,17),'Auxiliar Vendas'!D:G,2,0) -> Produto 09 | U71: 33 | V71: 14.7 | W71: 0 | X71: 10.23 | Y71: 485.1 | Z71: 27 | AA71: PRFL.00.0005 | AB71: 0 | AC71: 0 | AH71: 44469.575 | AI71: 0 | AJ71: 0 | AK71: =VLOOKUP(T71,'Auxiliar Vendas'!E:F,2,FALSE) -> Produto 09 | AL71: =U71*VLOOKUP(T71,'Auxiliar Vendas'!E:G,3,FALSE) -> 36.3
A72: 15272077365 | B72: 49 | D72: 44469 | E72: 15179581888 | F72: =VLOOKUP(RANDBETWEEN(1,20),'DBO Compras'!AA:AC,3,0) -> Comprador 01 | G72: 44.114.658/0001-08 | H72: RUA JOAO RAPHAEL MACHADO, 496 | I72: Araucaria | J72: Curitiba | K72: 81350610 | L72: PR | M72: Marcio@destak.com.br | N72: 41996849234 | O72: 0 | P72: 0 | R72: Atendido | S72: 15015085610 | T72: =VLOOKUP(RANDBETWEEN(1,17),'Auxiliar Vendas'!D:G,2,0) -> Produto 15 | U72: 150 | V72: 13.8 | W72: 0 | X72: 10.23 | Y72: 2070 | Z72: 41 | AA72: PRFL.00.0001 | AB72: 0 | AC72: 0 | AD72: HENRIQUE | AH72: 44469.382 | AI72: 0 | AJ72: 0 | AK72: =VLOOKUP(T72,'Auxiliar Vendas'!E:F,2,FALSE) -> Produto 15 | AL72: =U72*VLOOKUP(T72,'Auxiliar Vendas'!E:G,3,FALSE) -> 213
A73: 15272077365 | B73: 49 | D73: 44469 | E73: 15179581888 | F73: =VLOOKUP(RANDBETWEEN(1,20),'DBO Compras'!AA:AC,3,0) -> Comprador 17 | G73: 44.114.658/0001-08 | H73: RUA JOAO RAPHAEL MACHADO, 496 | I73: Araucaria | J73: Curitiba | K73: 81350610 | L73: PR | M73: Marcio@destak.com.br | N73: 41996849234 | O73: 0 | P73: 0 | R73: Atendido | S73: 15016043939 | T73: =VLOOKUP(RANDBETWEEN(1,17),'Auxiliar Vendas'!D:G,2,0) -> Produto 10 | U73: 7410 | V73: 13.9 | W73: 0 | X73: 10.747 | Y73: 102999 | Z73: 41 | AA73: PRFL.00.0019 | AB73: 0 | AC73: 0 | AD73: HENRIQUE | AH73: 44469.382 | AI73: 0 | AJ73: 0 | AK73: =VLOOKUP(T73,'Auxiliar Vendas'!E:F,2,FALSE) -> Produto 10 | AL73: =U73*VLOOKUP(T73,'Auxiliar Vendas'!E:G,3,FALSE) -> 8151
A74: 15272077365 | B74: 49 | D74: 44469 | E74: 15179581888 | F74: =VLOOKUP(RANDBETWEEN(1,20),'DBO Compras'!AA:AC,3,0) -> Comprador 05 | G74: 44.114.658/0001-08 | H74: RUA JOAO RAPHAEL MACHADO, 496 | I74: Araucaria | J74: Curitiba | K74: 81350610 | L74: PR | M74: Marcio@destak.com.br | N74: 41996849234 | O74: 0 | P74: 0 | R74: Atendido | S74: 15015911944 | T74: =VLOOKUP(RANDBETWEEN(1,17),'Auxiliar Vendas'!D:G,2,0) -> Produto 12 | U74: 600 | V74: 14.25 | W74: 0 | X74: 10.285 | Y74: 8550 | Z74: 41 | AA74: PRFL.00.0010 | AB74: 0 | AC74: 0 | AD74: HENRIQUE | AH74: 44469.382 | AI74: 0 | AJ74: 0 | AK74: =VLOOKUP(T74,'Auxiliar Vendas'!E:F,2,FALSE) -> Produto 12 | AL74: =U74*VLOOKUP(T74,'Auxiliar Vendas'!E:G,3,FALSE) -> 840
A75: 15272077365 | B75: 49 | D75: 44469 | E75: 15179581888 | F75: =VLOOKUP(RANDBETWEEN(1,20),'DBO Compras'!AA:AC,3,0) -> Comprador 16 | G75: 44.114.658/0001-08 | H75: RUA JOAO RAPHAEL MACHADO, 496 | I75: Araucaria | J75: Curitiba | K75: 81350610 | L75: PR | M75: Marcio@destak.com.br | N75: 41996849234 | O75: 0 | P75: 0 | R75: Atendido | S75: 15015911944 | T75: =VLOOKUP(RANDBETWEEN(1,17),'Auxiliar Vendas'!D:G,2,0) -> Produto 12 | U75: 20 | V75: 14.9 | W75: 0 | X75: 10.285 | Y75: 298 | Z75: 41 | AA75: PRFL.00.0010 | AB75: 0 | AC75: 0 | AD75: HENRIQUE | AH75: 44469.382 | AI75: 0 | AJ75: 0 | AK75: =VLOOKUP(T75,'Auxiliar Vendas'!E:F,2,FALSE) -> Produto 12 | AL75: =U75*VLOOKUP(T75,'Auxiliar Vendas'!E:G,3,FALSE) -> 28
A76: 15272077365 | B76: 49 | D76: 44469 | E76: 15179581888 | F76: =VLOOKUP(RANDBETWEEN(1,20),'DBO Compras'!AA:AC,3,0) -> Comprador 09 | G76: 44.114.658/0001-08 | H76: RUA JOAO RAPHAEL MACHADO, 496 | I76: Araucaria | J76: Curitiba | K76: 81350610 | L76: PR | M76: Marcio@destak.com.br | N76: 41996849234 | O76: 0 | P76: 0 | R76: Atendido | S76: 15015423083 | T76: =VLOOKUP(RANDBETWEEN(1,17),'Auxiliar Vendas'!D:G,2,0) -> Produto 08 | U76: 90 | V76: 15 | W76: 0 | X76: 10.23 | Y76: 1350 | Z76: 41 | AA76: PRFL.00.0004 | AB76: 0 | AC76: 0 | AD76: HENRIQUE | AH76: 44469.382 | AI76: 0 | AJ76: 0 | AK76: =VLOOKUP(T76,'Auxiliar Vendas'!E:F,2,FALSE) -> Produto 08 | AL76: =U76*VLOOKUP(T76,'Auxiliar Vendas'!E:G,3,FALSE) -> 99
A77: 15272077365 | B77: 49 | D77: 44469 | E77: 15179581888 | F77: =VLOOKUP(RANDBETWEEN(1,20),'DBO Compras'!AA:AC,3,0) -> Comprador 16 | G77: 44.114.658/0001-08 | H77: RUA JOAO RAPHAEL MACHADO, 496 | I77: Araucaria | J77: Curitiba | K77: 81350610 | L77: PR | M77: Marcio@destak.com.br | N77: 41996849234 | O77: 0 | P77: 0 | R77: Atendido | S77: 15016066088 | T77: =VLOOKUP(RANDBETWEEN(1,17),'Auxiliar Vendas'!D:G,2,0) -> Produto 05 | U77: 300 | V77: 15.2 | W77: 0 | X77: 10.747 | Y77: 4560 | Z77: 41 | AA77: PRFL.00.0022 | AB77: 0 | AC77: 0 | AD77: HENRIQUE | AH77: 44469.382 | AI77: 0 | AJ77: 0 | AK77: =VLOOKUP(T77,'Auxiliar Vendas'!E:F,2,FALSE) -> Produto 05 | AL77: =U77*VLOOKUP(T77,'Auxiliar Vendas'!E:G,3,FALSE) -> 180
A78: 15272077365 | B78: 49 | D78: 44469 | E78: 15179581888 | F78: =VLOOKUP(RANDBETWEEN(1,20),'DBO Compras'!AA:AC,3,0) -> Comprador 20 | G78: 44.114.658/0001-08 | H78: RUA JOAO RAPHAEL MACHADO, 496 | I78: Araucaria | J78: Curitiba | K78: 81350610 | L78: PR | M78: Marcio@destak.com.br | N78: 41996849234 | O78: 0 | P78: 0 | R78: Atendido | S78: 15015511068 | T78: =VLOOKUP(RANDBETWEEN(1,17),'Auxiliar Vendas'!D:G,2,0) -> Produto 09 | U78: 168 | V78: 15.5 | W78: 0 | X78: 10.23 | Y78: 2604 | Z78: 41 | AA78: PRFL.00.0005 | AB78: 0 | AC78: 0 | AD78: HENRIQUE | AH78: 44469.382 | AI78: 0 | AJ78: 0 | AK78: =VLOOKUP(T78,'Auxiliar Vendas'!E:F,2,FALSE) -> Produto 09 | AL78: =U78*VLOOKUP(T78,'Auxiliar Vendas'!E:G,3,FALSE) -> 184.8
A79: 15272077365 | B79: 49 | D79: 44469 | E79: 15179581888 | F79: =VLOOKUP(RANDBETWEEN(1,20),'DBO Compras'!AA:AC,3,0) -> Comprador 01 | G79: 44.114.658/0001-08 | H79: RUA JOAO RAPHAEL MACHADO, 496 | I79: Araucaria | J79: Curitiba | K79: 81350610 | L79: PR | M79: Marcio@destak.com.br | N79: 41996849234 | O79: 0 | P79: 0 | R79: Atendido | S79: 15015511068 | T79: =VLOOKUP(RANDBETWEEN(1,17),'Auxiliar Vendas'!D:G,2,0) -> Produto 02 | U79: 1143 | V79: 16.2 | W79: 0 | X79: 10.23 | Y79: 18516.6 | Z79: 41 | AA79: PRFL.00.0005 | AB79: 0 | AC79: 0 | AD79: HENRIQUE | AH79: 44469.382 | AI79: 0 | AJ79: 0 | AK79: =VLOOKUP(T79,'Auxiliar Vendas'!E:F,2,FALSE) -> Produto 02 | AL79: =U79*VLOOKUP(T79,'Auxiliar Vendas'!E:G,3,FALSE) -> 308.61
A80: 15272077365 | B80: 49 | D80: 44469 | E80: 15179581888 | F80: =VLOOKUP(RANDBETWEEN(1,20),'DBO Compras'!AA:AC,3,0) -> Comprador 04 | G80: 44.114.658/0001-08 | H80: RUA JOAO RAPHAEL MACHADO, 496 | I80: Araucaria | J80: Curitiba | K80: 81350610 | L80: PR | M80: Marcio@destak.com.br | N80: 41996849234 | O80: 0 | P80: 0 | R80: Atendido | S80: 15015423083 | T80: =VLOOKUP(RANDBETWEEN(1,17),'Auxiliar Vendas'!D:G,2,0) -> Produto 07 | U80: 50 | V80: 16.7 | W80: 0 | X80: 10.23 | Y80: 835 | Z80: 41 | AA80: PRFL.00.0004 | AB80: 0 | AC80: 0 | AD80: HENRIQUE | AH80: 44469.382 | AI80: 0 | AJ80: 0 | AK80: =VLOOKUP(T80,'Auxiliar Vendas'!E:F,2,FALSE) -> Produto 07 | AL80: =U80*VLOOKUP(T80,'Auxiliar Vendas'!E:G,3,FALSE) -> 55
A81: 15272077365 | B81: 49 | D81: 44469 | E81: 15179581888 | F81: =VLOOKUP(RANDBETWEEN(1,20),'DBO Compras'!AA:AC,3,0) -> Comprador 18 | G81: 44.114.658/0001-08 | H81: RUA JOAO RAPHAEL MACHADO, 496 | I81: Araucaria | J81: Curitiba | K81: 81350610 | L81: PR | M81: Marcio@destak.com.br | N81: 41996849234 | O81: 0 | P81: 0 | R81: Atendido | S81: 15015511068 | T81: =VLOOKUP(RANDBETWEEN(1,17),'Auxiliar Vendas'!D:G,2,0) -> Produto 15 | U81: 2 | V81: 17.7 | W81: 0 | X81: 10.23 | Y81: 35.4 | Z81: 41 | AA81: PRFL.00.0005 | AB81: 0 | AC81: 0 | AD81: HENRIQUE | AH81: 44469.382 | AI81: 0 | AJ81: 0 | AK81: =VLOOKUP(T81,'Auxiliar Vendas'!E:F,2,FALSE) -> Produto 15 | AL81: =U81*VLOOKUP(T81,'Auxiliar Vendas'!E:G,3,FALSE) -> 2.84
A82: 15272077365 | B82: 49 | D82: 44469 | E82: 15179581888 | F82: =VLOOKUP(RANDBETWEEN(1,20),'DBO Compras'!AA:AC,3,0) -> Comprador 02 | G82: 44.114.658/0001-08 | H82: RUA JOAO RAPHAEL MACHADO, 496 | I82: Araucaria | J82: Curitiba | K82: 81350610 | L82: PR | M82: Marcio@destak.com.br | N82: 41996849234 | O82: 0 | P82: 0 | R82: Atendido | S82: 15015918644 | T82: =VLOOKUP(RANDBETWEEN(1,17),'Auxiliar Vendas'!D:G,2,0) -> Produto 04 | U82: 5478 | V82: 8.2 | W82: 0 | X82: 5.61 | Y82: 44919.6 | Z82: 41 | AA82: PRFL.00.0011 | AB82: 0 | AC82: 0 | AD82: HENRIQUE | AH82: 44469.382 | AI82: 0 | AJ82: 0 | AK82: =VLOOKUP(T82,'Auxiliar Vendas'!E:F,2,FALSE) -> Produto 04 | AL82: =U82*VLOOKUP(T82,'Auxiliar Vendas'!E:G,3,FALSE) -> 3286.8
A83: 15272077365 | B83: 49 | D83: 44469 | E83: 15179581888 | F83: =VLOOKUP(RANDBETWEEN(1,20),'DBO Compras'!AA:AC,3,0) -> Comprador 15 | G83: 44.114.658/0001-08 | H83: RUA JOAO RAPHAEL MACHADO, 496 | I83: Araucaria | J83: Curitiba | K83: 81350610 | L83: PR | M83: Marcio@destak.com.br | N83: 41996849234 | O83: 0 | P83: 0 | R83: Atendido | S83: 15015353721 | T83: =VLOOKUP(RANDBETWEEN(1,17),'Auxiliar Vendas'!D:G,2,0) -> Produto 05 | U83: 1080 | V83: 8.38 | W83: 0 | X83: 5.58 | Y83: 9050.4 | Z83: 41 | AA83: PRFL.00.0002 | AB83: 0 | AC83: 0 | AD83: HENRIQUE | AH83: 44469.382 | AI83: 0 | AJ83: 0 | AK83: =VLOOKUP(T83,'Auxiliar Vendas'!E:F,2,FALSE) -> Produto 05 | AL83: =U83*VLOOKUP(T83,'Auxiliar Vendas'!E:G,3,FALSE) -> 648
... A99: 15272077365 | B99: 49 | D99: 44469 | E99: 15179581888 | F99: =VLOOKUP(RANDBETWEEN(1,20),'DBO Compras'!AA:AC,3,0) -> Comprador 04 | G99: 44.114.658/0001-08 | H99: RUA JOAO RAPHAEL MACHADO, 496 | I99: Araucaria | J99: Curitiba | K99: 81350610 | L99: PR | M99: Marcio@destak.com.br | N99: 41996849234 | O99: 0 | P99: 0 | R99: Atendido | S99: 15016080333 | T99: =VLOOKUP(RANDBETWEEN(1,17),'Auxiliar Vendas'!D:G,2,0) -> Produto 02 | U99: 35 | V99: 16.2 | W99: 0 | X99: 10.747 | Y99: 567 | Z99: 41 | AA99: PRFL.00.0024 | AB99: 0 | AC99: 0 | AD99: HENRIQUE | AH99: 44469.382 | AI99: 0 | AJ99: 0 | AK99: =VLOOKUP(T99,'Auxiliar Vendas'!E:F,2,FALSE) -> Produto 02 | AL99: =U99*VLOOKUP(T99,'Auxiliar Vendas'!E:G,3,FALSE) -> 9.45
A100: 15279752604 | B100: 61 | D100: 44469 | E100: 15279322250 | F100: =VLOOKUP(RANDBETWEEN(1,20),'DBO Compras'!AA:AC,3,0) -> Comprador 13 | G100: 15.651.626/0001-35 | H100: RUA BRIGADEIRO FRANCO, 5024, LOJA 01 | I100: REBOUCAS | J100: Curitiba | K100: 80220100 | L100: PR | M100: Diego@Drywall.com.br | N100: 41993330017 | O100: 0 | P100: 0 | R100: Atendido | S100: 15016043939 | T100: =VLOOKUP(RANDBETWEEN(1,17),'Auxiliar Vendas'!D:G,2,0) -> Produto 02 | U100: 1700 | V100: 13.9 | W100: 0 | X100: 10.747 | Y100: 23630 | Z100: 68 | AA100: PRFL.00.0019 | AB100: 0 | AC100: 0 | AH100: 44469.469 | AI100: 0 | AJ100: 0 | AK100: =VLOOKUP(T100,'Auxiliar Vendas'!E:F,2,FALSE) -> Produto 02 | AL100: =U100*VLOOKUP(T100,'Auxiliar Vendas'!E:G,3,FALSE) -> 459
A101: 15279752604 | B101: 61 | D101: 44469 | E101: 15279322250 | F101: =VLOOKUP(RANDBETWEEN(1,20),'DBO Compras'!AA:AC,3,0) -> Comprador 04 | G101: 15.651.626/0001-35 | H101: RUA BRIGADEIRO FRANCO, 5024, LOJA 01 | I101: REBOUCAS | J101: Curitiba | K101: 80220100 | L101: PR | M101: Diego@Drywall.com.br | N101: 41993330017 | O101: 0 | P101: 0 | R101: Atendido | S101: 15015353721 | T101: =VLOOKUP(RANDBETWEEN(1,17),'Auxiliar Vendas'!D:G,2,0) -> Produto 17 | U101: 900 | V101: 8.2 | W101: 0 | X101: 5.58 | Y101: 7380 | Z101: 68 | AA101: PRFL.00.0002 | AB101: 0 | AC101: 0 | AH101: 44469.469 | AI101: 0 | AJ101: 0 | AK101: =VLOOKUP(T101,'Auxiliar Vendas'!E:F,2,FALSE) -> Produto 17 | AL101: =U101*VLOOKUP(T101,'Auxiliar Vendas'!E:G,3,FALSE) -> 1278
A102: 15279752604 | B102: 61 | D102: 44469 | E102: 15279322250 | F102: =VLOOKUP(RANDBETWEEN(1,20),'DBO Compras'!AA:AC,3,0) -> Comprador 13 | G102: 15.651.626/0001-35 | H102: RUA BRIGADEIRO FRANCO, 5024, LOJA 01 | I102: REBOUCAS | J102: Curitiba | K102: 80220100 | L102: PR | M102: Diego@Drywall.com.br | N102: 41993330017 | O102: 0 | P102: 0 | R102: Atendido | S102: 15016080333 | T102: =VLOOKUP(RANDBETWEEN(1,17),'Auxiliar Vendas'!D:G,2,0) -> Produto 14 | U102: 400 | V102: 15.2 | W102: 0 | X102: 10.747 | Y102: 6080 | Z102: 68 | AA102: PRFL.00.0024 | AB102: 0 | AC102: 0 | AH102: 44469.469 | AI102: 0 | AJ102: 0 | AK102: =VLOOKUP(T102,'Auxiliar Vendas'!E:F,2,FALSE) -> Produto 14 | AL102: =U102*VLOOKUP(T102,'Auxiliar Vendas'!E:G,3,FALSE) -> 560
A103: 15279752604 | B103: 61 | D103: 44469 | E103: 15279322250 | F103: =VLOOKUP(RANDBETWEEN(1,20),'DBO Compras'!AA:AC,3,0) -> Comprador 18 | G103: 15.651.626/0001-35 | H103: RUA BRIGADEIRO FRANCO, 5024, LOJA 01 | I103: REBOUCAS | J103: Curitiba | K103: 80220100 | L103: PR | M103: Diego@Drywall.com.br | N103: 41993330017 | O103: 0 | P103: 0 | R103: Atendido | S103: 15016093155 | T103: =VLOOKUP(RANDBETWEEN(1,17),'Auxiliar Vendas'!D:G,2,0) -> Produto 14 | U103: 500 | V103: 18.2 | W103: 0 | X103: 14.4596 | Y103: 9100 | Z103: 68 | AA103: PRFL.00.0026 | AB103: 0 | AC103: 0 | AH103: 44469.469 | AI103: 0 | AJ103: 0 | AK103: =VLOOKUP(T103,'Auxiliar Vendas'!E:F,2,FALSE) -> Produto 14 | AL103: =U103*VLOOKUP(T103,'Auxiliar Vendas'!E:G,3,FALSE) -> 700
A104: 15279752604 | B104: 61 | D104: 44469 | E104: 15279322250 | F104: =VLOOKUP(RANDBETWEEN(1,20),'DBO Compras'!AA:AC,3,0) -> Comprador 20 | G104: 15.651.626/0001-35 | H104: RUA BRIGADEIRO FRANCO, 5024, LOJA 01 | I104: REBOUCAS | J104: Curitiba | K104: 80220100 | L104: PR | M104: Diego@Drywall.com.br | N104: 41993330017 | O104: 0 | P104: 0 | R104: Atendido | S104: 15016099089 | T104: =VLOOKUP(RANDBETWEEN(1,17),'Auxiliar Vendas'!D:G,2,0) -> Produto 13 | U104: 200 | V104: 21.3 | W104: 0 | X104: 16.8044 | Y104: 4260 | Z104: 68 | AA104: PRFL.00.0027 | AB104: 0 | AC104: 0 | AH104: 44469.469 | AI104: 0 | AJ104: 0 | AK104: =VLOOKUP(T104,'Auxiliar Vendas'!E:F,2,FALSE) -> Produto 13 | AL104: =U104*VLOOKUP(T104,'Auxiliar Vendas'!E:G,3,FALSE) -> 280
A105: 15284305943 | B105: 67 | D105: 44469 | E105: 15179629910 | F105: =VLOOKUP(RANDBETWEEN(1,20),'DBO Compras'!AA:AC,3,0) -> Comprador 19 | G105: 07.700.789/0001-32 | H105: RUA TRISTE-PIA, 20, A | I105: JARDIM PRIMAVERA | J105: ARAPONGAS | K105: 86702008 | L105: PR | O105: 0 | P105: 0 | R105: Atendido | S105: 15015353721 | T105: =VLOOKUP(RANDBETWEEN(1,17),'Auxiliar Vendas'!D:G,2,0) -> Produto 03 | U105: 100 | V105: 8.68 | W105: 0 | X105: 5.58 | Y105: 868 | Z105: 43 | AA105: PRFL.00.0002 | AB105: 0 | AC105: 0 | AH105: 44469.382 | AI105: 0 | AJ105: 0 | AK105: =VLOOKUP(T105,'Auxiliar Vendas'!E:F,2,FALSE) -> Produto 03 | AL105: =U105*VLOOKUP(T105,'Auxiliar Vendas'!E:G,3,FALSE) -> 60
A106: 15284371661 | B106: 68 | D106: 44469 | E106: 15179646317 | F106: =VLOOKUP(RANDBETWEEN(1,20),'DBO Compras'!AA:AC,3,0) -> Comprador 11 | G106: 12.510.166/0001-37 | H106: RUA CASTRO ALVES, 22, A | I106: ZONA 06 | J106: MARINGA | K106: 87015440 | L106: PR | O106: 0 | P106: 0 | R106: Atendido | S106: 15015886084 | T106: =VLOOKUP(RANDBETWEEN(1,17),'Auxiliar Vendas'!D:G,2,0) -> Produto 09 | U106: 50 | V106: 21.9 | W106: 0 | X106: 15.996 | Y106: 1095 | Z106: 44 | AA106: PRFL.00.0009 | AB106: 0 | AC106: 0 | AH106: 44469.381 | AI106: 0 | AJ106: 0 | AK106: =VLOOKUP(T106,'Auxiliar Vendas'!E:F,2,FALSE) -> Produto 09 | AL106: =U106*VLOOKUP(T106,'Auxiliar Vendas'!E:G,3,FALSE) -> 55
A107: 15288941476 | B107: 71 | D107: 44469 | E107: 15295545217 | F107: =VLOOKUP(RANDBETWEEN(1,20),'DBO Compras'!AA:AC,3,0) -> Comprador 07 | G107: 11.448.815/0001-54 | H107: RUA IZAAC FERREIRA DA CRUZ, 3920, FUNDOS | I107: SITIO CERCADO | J107: Curitiba | K107: 81910000 | L107: PR | M107: Gesso@Alvo.com.br | N107: 41998481264 | O107: 0 | P107: 0 | R107: Atendido | S107: 15016043939 | T107: =VLOOKUP(RANDBETWEEN(1,17),'Auxiliar Vendas'!D:G,2,0) -> Produto 02 | U107: 1000 | V107: 13.9 | W107: 0 | X107: 10.747 | Y107: 13900 | Z107: 78 | AA107: PRFL.00.0019 | AB107: 0 | AC107: 0 | AH107: 44469.381 | AI107: 0 | AJ107: 0 | AK107: =VLOOKUP(T107,'Auxiliar Vendas'!E:F,2,FALSE) -> Produto 02 | AL107: =U107*VLOOKUP(T107,'Auxiliar Vendas'!E:G,3,FALSE) -> 270
A108: 15288941476 | B108: 71 | D108: 44469 | E108: 15295545217 | F108: =VLOOKUP(RANDBETWEEN(1,20),'DBO Compras'!AA:AC,3,0) -> Comprador 06 | G108: 11.448.815/0001-54 | H108: RUA IZAAC FERREIRA DA CRUZ, 3920, FUNDOS | I108: SITIO CERCADO | J108: Curitiba | K108: 81910000 | L108: PR | M108: Gesso@Alvo.com.br | N108: 41998481264 | O108: 0 | P108: 0 | R108: Atendido | S108: 15015918644 | T108: =VLOOKUP(RANDBETWEEN(1,17),'Auxiliar Vendas'!D:G,2,0) -> Produto 09 | U108: 1000 | V108: 8.38 | W108: 0 | X108: 5.61 | Y108: 8380 | Z108: 78 | AA108: PRFL.00.0011 | AB108: 0 | AC108: 0 | AH108: 44469.381 | AI108: 0 | AJ108: 0 | AK108: =VLOOKUP(T108,'Auxiliar Vendas'!E:F,2,FALSE) -> Produto 09 | AL108: =U108*VLOOKUP(T108,'Auxiliar Vendas'!E:G,3,FALSE) -> 1100
A109: 15289377505 | B109: 73 | D109: 44469 | E109: 15179701182 | F109: =VLOOKUP(RANDBETWEEN(1,20),'DBO Compras'!AA:AC,3,0) -> Comprador 01 | G109: 09.171.164/0001-56 | H109: RUA MARIO LIMA DOS SANTOS, 59 | I109: ESTRELA | J109: Ponta Grossa | K109: 84050290 | L109: PR | M109: Vilavelha@vilavelha.com | N109: 42999659968 | O109: 0 | P109: 0 | R109: Atendido | S109: 15015911944 | T109: =VLOOKUP(RANDBETWEEN(1,17),'Auxiliar Vendas'!D:G,2,0) -> Produto 06 | U109: 450 | V109: 14.25 | W109: 0 | X109: 10.285 | Y109: 6412.5 | Z109: 46 | AA109: PRFL.00.0010 | AB109: 0 | AC109: 0 | AH109: 44519.381 | AI109: 0 | AJ109: 0 | AK109: =VLOOKUP(T109,'Auxiliar Vendas'!E:F,2,FALSE) -> Produto 06 | AL109: =U109*VLOOKUP(T109,'Auxiliar Vendas'!E:G,3,FALSE) -> 225
A110: 15289377505 | B110: 73 | D110: 44469 | E110: 15179701182 | F110: =VLOOKUP(RANDBETWEEN(1,20),'DBO Compras'!AA:AC,3,0) -> Comprador 10 | G110: 09.171.164/0001-56 | H110: RUA MARIO LIMA DOS SANTOS, 59 | I110: ESTRELA | J110: Ponta Grossa | K110: 84050290 | L110: PR | M110: Vilavelha@vilavelha.com | N110: 42999659968 | O110: 0 | P110: 0 | R110: Atendido | S110: 15015918644 | T110: =VLOOKUP(RANDBETWEEN(1,17),'Auxiliar Vendas'!D:G,2,0) -> Produto 06 | U110: 90 | V110: 8.38 | W110: 0 | X110: 5.61 | Y110: 754.2 | Z110: 46 | AA110: PRFL.00.0011 | AB110: 0 | AC110: 0 | AH110: 44519.381 | AI110: 0 | AJ110: 0 | AK110: =VLOOKUP(T110,'Auxiliar Vendas'!E:F,2,FALSE) -> Produto 06 | AL110: =U110*VLOOKUP(T110,'Auxiliar Vendas'!E:G,3,FALSE) -> 45
A111: 15289377505 | B111: 73 | D111: 44469 | E111: 15179701182 | F111: =VLOOKUP(RANDBETWEEN(1,20),'DBO Compras'!AA:AC,3,0) -> Comprador 07 | G111: 09.171.164/0001-56 | H111: RUA MARIO LIMA DOS SANTOS, 59 | I111: ESTRELA | J111: Ponta Grossa | K111: 84050290 | L111: PR | M111: Vilavelha@vilavelha.com | N111: 42999659968 | O111: 0 | P111: 0 | R111: Atendido | S111: 15016080333 | T111: =VLOOKUP(RANDBETWEEN(1,17),'Auxiliar Vendas'!D:G,2,0) -> Produto 09 | U111: 143 | V111: 15.5 | W111: 0 | X111: 10.747 | Y111: 2216.5 | Z111: 46 | AA111: PRFL.00.0024 | AB111: 0 | AC111: 0 | AH111: 44519.381 | AI111: 0 | AJ111: 0 | AK111: =VLOOKUP(T111,'Auxiliar Vendas'!E:F,2,FALSE) -> Produto 09 | AL111: =U111*VLOOKUP(T111,'Auxiliar Vendas'!E:G,3,FALSE) -> 157.3
A112: 15289377505 | B112: 73 | D112: 44469 | E112: 15179701182 | F112: =VLOOKUP(RANDBETWEEN(1,20),'DBO Compras'!AA:AC,3,0) -> Comprador 20 | G112: 09.171.164/0001-56 | H112: RUA MARIO LIMA DOS SANTOS, 59 | I112: ESTRELA | J112: Ponta Grossa | K112: 84050290 | L112: PR | M112: Vilavelha@vilavelha.com | N112: 42999659968 | O112: 0 | P112: 0 | R112: Atendido | S112: 15015746121 | T112: =VLOOKUP(RANDBETWEEN(1,17),'Auxiliar Vendas'!D:G,2,0) -> Produto 17 | U112: 90 | V112: 18.65 | W112: 0 | X112: 13.764 | Y112: 1678.5 | Z112: 46 | AA112: PRFL.00.0007 | AB112: 0 | AC112: 0 | AH112: 44519.381 | AI112: 0 | AJ112: 0 | AK112: =VLOOKUP(T112,'Auxiliar Vendas'!E:F,2,FALSE) -> Produto 17 | AL112: =U112*VLOOKUP(T112,'Auxiliar Vendas'!E:G,3,FALSE) -> 127.8
A113: 15289377505 | B113: 73 | D113: 44469 | E113: 15179701182 | F113: =VLOOKUP(RANDBETWEEN(1,20),'DBO Compras'!AA:AC,3,0) -> Comprador 01 | G113: 09.171.164/0001-56 | H113: RUA MARIO LIMA DOS SANTOS, 59 | I113: ESTRELA | J113: Ponta Grossa | K113: 84050290 | L113: PR | M113: Vilavelha@vilavelha.com | N113: 42999659968 | O113: 0 | P113: 0 | R113: Atendido | S113: 15139667431 | T113: =VLOOKUP(RANDBETWEEN(1,17),'Auxiliar Vendas'!D:G,2,0) -> Produto 16 | U113: 10 | V113: 21.8 | W113: 0 | X113: 0 | Y113: 218 | Z113: 46 | AA113: PRFL.00.0028 | AB113: 0 | AC113: 0 | AH113: 44519.381 | AI113: 0 | AJ113: 0 | AK113: =VLOOKUP(T113,'Auxiliar Vendas'!E:F,2,FALSE) -> Produto 16 | AL113: =U113*VLOOKUP(T113,'Auxiliar Vendas'!E:G,3,FALSE) -> 12.7
A114: 15289377505 | B114: 73 | D114: 44469 | E114: 15179701182 | F114: =VLOOKUP(RANDBETWEEN(1,20),'DBO Compras'!AA:AC,3,0) -> Comprador 13 | G114: 09.171.164/0001-56 | H114: RUA MARIO LIMA DOS SANTOS, 59 | I114: ESTRELA | J114: Ponta Grossa | K114: 84050290 | L114: PR | M114: Vilavelha@vilavelha.com | N114: 42999659968 | O114: 0 | P114: 0 | R114: Atendido | S114: 15139667431 | T114: =VLOOKUP(RANDBETWEEN(1,17),'Auxiliar Vendas'!D:G,2,0) -> Produto 13 | U114: 10 | V114: 22.1 | W114: 0 | X114: 0 | Y114: 221 | Z114: 46 | AA114: PRFL.00.0028 | AB114: 0 | AC114: 0 | AH114: 44519.381 | AI114: 0 | AJ114: 0 | AK114: =VLOOKUP(T114,'Auxiliar Vendas'!E:F,2,FALSE) -> Produto 13 | AL114: =U114*VLOOKUP(T114,'Auxiliar Vendas'!E:G,3,FALSE) -> 14
A115: 15289377505 | B115: 73 | D115: 44469 | E115: 15179701182 | F115: =VLOOKUP(RANDBETWEEN(1,20),'DBO Compras'!AA:AC,3,0) -> Comprador 13 | G115: 09.171.164/0001-56 | H115: RUA MARIO LIMA DOS SANTOS, 59 | I115: ESTRELA | J115: Ponta Grossa | K115: 84050290 | L115: PR | M115: Vilavelha@vilavelha.com | N115: 42999659968 | O115: 0 | P115: 0 | R115: Atendido | S115: 15016093155 | T115: =VLOOKUP(RANDBETWEEN(1,17),'Auxiliar Vendas'!D:G,2,0) -> Produto 07 | U115: 200 | V115: 18.65 | W115: 0 | X115: 14.4596 | Y115: 3730 | Z115: 46 | AA115: PRFL.00.0026 | AB115: 0 | AC115: 0 | AH115: 44519.381 | AI115: 0 | AJ115: 0 | AK115: =VLOOKUP(T115,'Auxiliar Vendas'!E:F,2,FALSE) -> Produto 07 | AL115: =U115*VLOOKUP(T115,'Auxiliar Vendas'!E:G,3,FALSE) -> 220
A116: 15289377505 | B116: 73 | D116: 44469 | E116: 15179701182 | F116: =VLOOKUP(RANDBETWEEN(1,20),'DBO Compras'!AA:AC,3,0) -> Comprador 14 | G116: 09.171.164/0001-56 | H116: RUA MARIO LIMA DOS SANTOS, 59 | I116: ESTRELA | J116: Ponta Grossa | K116: 84050290 | L116: PR | M116: Vilavelha@vilavelha.com | N116: 42999659968 | O116: 0 | P116: 0 | R116: Atendido | S116: 15016099089 | T116: =VLOOKUP(RANDBETWEEN(1,17),'Auxiliar Vendas'!D:G,2,0) -> Produto 03 | U116: 182 | V116: 21.75 | W116: 0 | X116: 16.8044 | Y116: 3958.5 | Z116: 46 | AA116: PRFL.00.0027 | AB116: 0 | AC116: 0 | AH116: 44519.381 | AI116: 0 | AJ116: 0 | AK116: =VLOOKUP(T116,'Auxiliar Vendas'!E:F,2,FALSE) -> Produto 03 | AL116: =U116*VLOOKUP(T116,'Auxiliar Vendas'!E:G,3,FALSE) -> 109.2
A117: 15289377505 | B117: 73 | D117: 44469 | E117: 15179701182 | F117: =VLOOKUP(RANDBETWEEN(1,20),'DBO Compras'!AA:AC,3,0) -> Comprador 02 | G117: 09.171.164/0001-56 | H117: RUA MARIO LIMA DOS SANTOS, 59 | I117: ESTRELA | J117: Ponta Grossa | K117: 84050290 | L117: PR | M117: Vilavelha@vilavelha.com | N117: 42999659968 | O117: 0 | P117: 0 | R117: Atendido | S117: 15139727614 | T117: =VLOOKUP(RANDBETWEEN(1,17),'Auxiliar Vendas'!D:G,2,0) -> Produto 09 | U117: 10 | V117: 25.5 | W117: 0 | X117: 0 | Y117: 255 | Z117: 46 | AA117: PRFL.00.0029 | AB117: 0 | AC117: 0 | AH117: 44519.381 | AI117: 0 | AJ117: 0 | AK117: =VLOOKUP(T117,'Auxiliar Vendas'!E:F,2,FALSE) -> Produto 09 | AL117: =U117*VLOOKUP(T117,'Auxiliar Vendas'!E:G,3,FALSE) -> 11
A118: 15289865360 | B118: 74 | D118: 44469 | E118: 15179724225 | F118: =VLOOKUP(RANDBETWEEN(1,20),'DBO Compras'!AA:AC,3,0) -> Comprador 03 | G118: 29.578.605/0001-46 | H118: RUA JOAO DOSZANET, 553 | I118: CONTORNO | J118: Ponta Grossa | K118: 84060872 | L118: PR | M118: comercial@perfilar.ind.br | N118: 4299550985 | O118: 0 | P118: 0 | R118: Atendido | S118: 15015085610 | T118: =VLOOKUP(RANDBETWEEN(1,17),'Auxiliar Vendas'!D:G,2,0) -> Produto 13 | U118: 120 | V118: 14.25 | W118: 0 | X118: 10.23 | Y118: 1710 | Z118: 47 | AA118: PRFL.00.0001 | AB118: 0 | AC118: 0 | AH118: 44469.411 | AI118: 0 | AJ118: 0 | AK118: =VLOOKUP(T118,'Auxiliar Vendas'!E:F,2,FALSE) -> Produto 13 | AL118: =U118*VLOOKUP(T118,'Auxiliar Vendas'!E:G,3,FALSE) -> 168
... A120: 15289865360 | B120: 74 | D120: 44469 | E120: 15179724225 | F120: =VLOOKUP(RANDBETWEEN(1,20),'DBO Compras'!AA:AC,3,0) -> Comprador 09 | G120: 29.578.605/0001-46 | H120: RUA JOAO DOSZANET, 553 | I120: CONTORNO | J120: Ponta Grossa | K120: 84060872 | L120: PR | M120: comercial@perfilar.ind.br | N120: 4299550985 | O120: 0 | P120: 0 | R120: Atendido | S120: 15015511068 | T120: =VLOOKUP(RANDBETWEEN(1,17),'Auxiliar Vendas'!D:G,2,0) -> Produto 06 | U120: 50 | V120: 16.7 | W120: 0 | X120: 10.23 | Y120: 835 | Z120: 47 | AA120: PRFL.00.0005 | AB120: 0 | AC120: 0 | AH120: 44469.411 | AI120: 0 | AJ120: 0 | AK120: =VLOOKUP(T120,'Auxiliar Vendas'!E:F,2,FALSE) -> Produto 06 | AL120: =U120*VLOOKUP(T120,'Auxiliar Vendas'!E:G,3,FALSE) -> 25
A121: 15291322589 | B121: 88 | D121: 44469 | E121: 15179746175 | F121: =VLOOKUP(RANDBETWEEN(1,20),'DBO Compras'!AA:AC,3,0) -> Comprador 19 | G121: 27.774.006/0001-72 | H121: R JOSE LINHARES, 145 | I121: MONTE ALEGRE | J121: TELEMACO BORBA | K121: 84266280 | L121: PR | O121: 0 | P121: 0 | R121: Atendido | S121: 15015511068 | T121: =VLOOKUP(RANDBETWEEN(1,17),'Auxiliar Vendas'!D:G,2,0) -> Produto 10 | U121: 170 | V121: 16.7 | W121: 0 | X121: 10.23 | Y121: 2839 | Z121: 48 | AA121: PRFL.00.0005 | AB121: 0 | AC121: 0 | AH121: 44469.363 | AI121: 0 | AJ121: 0 | AK121: =VLOOKUP(T121,'Auxiliar Vendas'!E:F,2,FALSE) -> Produto 10 | AL121: =U121*VLOOKUP(T121,'Auxiliar Vendas'!E:G,3,FALSE) -> 187
A122: 15291322589 | B122: 88 | D122: 44469 | E122: 15179746175 | F122: =VLOOKUP(RANDBETWEEN(1,20),'DBO Compras'!AA:AC,3,0) -> Comprador 15 | G122: 27.774.006/0001-72 | H122: R JOSE LINHARES, 145 | I122: MONTE ALEGRE | J122: TELEMACO BORBA | K122: 84266280 | L122: PR | O122: 0 | P122: 0 | R122: Atendido | S122: 15016093155 | T122: =VLOOKUP(RANDBETWEEN(1,17),'Auxiliar Vendas'!D:G,2,0) -> Produto 10 | U122: 70 | V122: 16.79 | W122: 0 | X122: 14.4596 | Y122: 1175.3 | Z122: 48 | AA122: PRFL.00.0026 | AB122: 0 | AC122: 0 | AH122: 44469.363 | AI122: 0 | AJ122: 0 | AK122: =VLOOKUP(T122,'Auxiliar Vendas'!E:F,2,FALSE) -> Produto 10 | AL122: =U122*VLOOKUP(T122,'Auxiliar Vendas'!E:G,3,FALSE) -> 77
A123: 15291322589 | B123: 88 | D123: 44469 | E123: 15179746175 | F123: =VLOOKUP(RANDBETWEEN(1,20),'DBO Compras'!AA:AC,3,0) -> Comprador 06 | G123: 27.774.006/0001-72 | H123: R JOSE LINHARES, 145 | I123: MONTE ALEGRE | J123: TELEMACO BORBA | K123: 84266280 | L123: PR | O123: 0 | P123: 0 | R123: Atendido | S123: 15016080333 | T123: =VLOOKUP(RANDBETWEEN(1,17),'Auxiliar Vendas'!D:G,2,0) -> Produto 02 | U123: 30 | V123: 15.5 | W123: 0 | X123: 10.747 | Y123: 465 | Z123: 48 | AA123: PRFL.00.0024 | AB123: 0 | AC123: 0 | AH123: 44469.363 | AI123: 0 | AJ123: 0 | AK123: =VLOOKUP(T123,'Auxiliar Vendas'!E:F,2,FALSE) -> Produto 02 | AL123: =U123*VLOOKUP(T123,'Auxiliar Vendas'!E:G,3,FALSE) -> 8.1
...

Sheet Ven. Peso e Valor
A1: Soma Preço | B1: 378309
A2: Soma Peso | B2: =GETPIVOTDATA("Peso",$H$5) -> 330799.05
A3: Pç por Kg | B3: =B1/B2 -> 1.1436218
A5: Rótulos de Linha | B5: Soma de Peso | D5: Rótulos de Linha | E5: Soma de Preço Total | H5: Rótulos de Linha | I5: Soma de Peso
A6: Produto 17 | B6: 23253.92 | D6: Produto 10 | E6: 206733.6 | H6: Produto 14 | I6: 32229.4
A7: Produto 16 | B7: 28747.72 | D7: Produto 12 | E7: 264394 | H7: Produto 15 | I7: 30765.72
A8: Produto 15 | B8: 30765.72 | D8: Produto 05 | E8: 263275 | H8: Produto 12 | I8: 28851.2
A9: Produto 14 | B9: 32229.4 | D9: Produto 14 | E9: 296777.05 | H9: Produto 16 | I9: 28747.72
A10: Produto 13 | B10: 23472.4 | D10: Produto 01 | E10: 194362.7 | H10: Produto 07 | I10: 27149.1
A11: Produto 12 | B11: 28851.2 | D11: Produto 11 | E11: 310675.35 | H11: Produto 09 | I11: 24271.5
A12: Produto 11 | B12: 22511.5 | D12: Produto 07 | E12: 298308.42 | H12: Produto 13 | I12: 23472.4
A13: Produto 10 | B13: 17250.2 | D13: Produto 02 | E13: 284248.35 | H13: Produto 17 | I13: 23253.92
A14: Produto 09 | B14: 24271.5 | D14: Produto 13 | E14: 228561.95 | H14: Produto 11 | I14: 22511.5
A15: Produto 08 | B15: 20969.3 | D15: Produto 06 | E15: 284027.8 | H15: Produto 08 | I15: 20969.3
A16: Produto 07 | B16: 27149.1 | D16: Produto 16 | E16: 318759.62 | H16: Produto 10 | I16: 17250.2
A17: Produto 06 | B17: 10166.5 | D17: Produto 08 | E17: 237506.71 | H17: Produto 05 | I17: 12685.2
... A23: Total Geral | B23: 330799.05 | D23: Total Geral | E23: 4407761.3 | H23: Total Geral | I23: 330799.05

Sheet Ven. Mes
A1: Soma Preço | B1: =GETPIVOTDATA("Preço Total",$E$4) -> 4407761.3
A2: Soma Peso | B2: =GETPIVOTDATA("Soma de Peso",$A$4) -> 330799.05
A4: Rótulos de Linha | B4: Soma de Peso | E4: Rótulos de Linha | F4: Soma de Preço Total
A5: jul | B5: 8298.2 | E5: jul | F5: 78981.4
A6: ago | B6: 21089.1 | E6: ago | F6: 362769.02
A7: set | B7: 36989.82 | E7: set | F7: 495508.58
A8: out | B8: 62819.56 | E8: out | F8: 813769.1
A9: nov | B9: 93453.2 | E9: nov | F9: 1225974.5
A10: dez | B10: 108149.17 | E10: dez | F10: 1430758.7
A11: Total Geral | B11: 330799.05 | E11: Total Geral | F11: 4407761.3

Sheet TOP Compradores
A1: Posição | B1: Nome | C1: Vlr | E1: Rótulos de Linha | F1: Soma de Preço Total
A2: 1 | B2: =IF(OR(E2 = "Total Geral",E2 = ""),"N/A",E2) -> Comprador 13 | C2: =GETPIVOTDATA("Preço Total",$E$1,"Nome do contato",B2) -> 224562.5 | E2: Comprador 13 | F2: 224562.5
A3: 2 | B3: =IF(OR(E3 = "Total Geral",E3 = ""),"N/A",E3) -> Comprador 06 | C3: =GETPIVOTDATA("Preço Total",$E$1,"Nome do contato",B3) -> 228470.7 | E3: Comprador 06 | F3: 228470.7
A4: 3 | B4: =IF(OR(E4 = "Total Geral",E4 = ""),"N/A",E4) -> Comprador 10 | C4: =GETPIVOTDATA("Preço Total",$E$1,"Nome do contato",B4) -> 228833.32 | E4: Comprador 10 | F4: 228833.32
A5: 4 | B5: =IF(OR(E5 = "Total Geral",E5 = ""),"N/A",E5) -> Comprador 14 | C5: =GETPIVOTDATA("Preço Total",$E$1,"Nome do contato",B5) -> 241304.3 | E5: Comprador 14 | F5: 241304.3
A6: 5 | B6: =IF(OR(E6 = "Total Geral",E6 = ""),"N/A",E6) -> Comprador 20 | C6: =GETPIVOTDATA("Preço Total",$E$1,"Nome do contato",B6) -> 286837.3 | E6: Comprador 20 | F6: 286837.3
A7: 6 | B7: =IF(OR(E7 = "Total Geral",E7 = ""),"N/A",E7) -> Comprador 09 | C7: =GETPIVOTDATA("Preço Total",$E$1,"Nome do contato",B7) -> 320063.8 | E7: Comprador 09 | F7: 320063.8
A8: 7 | B8: =IF(OR(E8 = "Total Geral",E8 = ""),"N/A",E8) -> Comprador 16 | C8: =GETPIVOTDATA("Preço Total",$E$1,"Nome do contato",B8) -> 321532.82 | E8: Comprador 16 | F8: 321532.82
A9: 8 | B9: =IF(OR(E9 = "Total Geral",E9 = ""),"N/A",E9) -> Comprador 07 | C9: =GETPIVOTDATA("Preço Total",$E$1,"Nome do contato",B9) -> 349287.48 | E9: Comprador 07 | F9: 349287.48
A10: 9 | B10: =IF(OR(E10 = "Total Geral",E10 = ""),"N/A",E10) -> Comprador 08 | C10: =GETPIVOTDATA("Preço Total",$E$1,"Nome do contato",B10) -> 416624.35 | E10: Comprador 08 | F10: 416624.35
A11: 10 | B11: =IF(OR(E11 = "Total Geral",E11 = ""),"N/A",E11) -> Comprador 12 | C11: =GETPIVOTDATA("Preço Total",$E$1,"Nome do contato",B11) -> 450368.05 | E11: Comprador 12 | F11: 450368.05
E12: Total Geral | F12: 3067884.6

Sheet Auxiliar Vendas
B2: TABELA DE PESOS POR PEÇA
B4: PRODUTO | C4: PESO | E4: PRODUTO | F4: Prod. Resum | G4: PESO
B5: F530 | C5: 1.1 | D5: 1 | E5: Produto 01 | F5: Produto 01 | G5: 0.4 | I5: 1 | J5: ="Produto 0" &I5 -> Produto 01
B6: CANTONEIRA 25 X 30 | C6: 0.6 | D6: 2 | E6: Produto 02 | F6: Produto 02 | G6: 0.27 | I6: 2 | J6: ="Produto 0" &I6 -> Produto 02
B7: CANTONEIRA 15 X 20 | C7: 0.27 | D7: 3 | E7: Produto 03 | F7: Produto 03 | G7: 0.6 | I7: 3 | J7: ="Produto 0" &I7 -> Produto 03
B8: CANTONEIRA 23 X 23 PERF | C8: 0.5 | D8: 4 | E8: Produto 04 | F8: Produto 04 | G8: 0.6 | I8: 4 | J8: ="Produto 0" &I8 -> Produto 04
B9: GUIA 48 | C9: 1.1 | D9: 5 | E9: Produto 05 | F9: Produto 05 | G9: 0.6 | I9: 5 | J9: ="Produto 0" &I9 -> Produto 05
B10: GUIA 70 | C10: 1.4 | D10: 6 | E10: Produto 06 | F10: Produto 06 | G10: 0.5 | I10: 6 | J10: ="Produto 0" &I10 -> Produto 06
B11: GUIA 90 | C11: 1.62 | D11: 7 | E11: Produto 07 | F11: Produto 07 | G11: 1.1 | I11: 7 | J11: ="Produto 0" &I11 -> Produto 07
B12: MONTANTE 48 | C12: 1.42 | D12: 8 | E12: Produto 08 | F12: Produto 08 | G12: 1.1 | I12: 8 | J12: ="Produto 0" &I12 -> Produto 08
B13: MONTANTE 48 C/ 2,7 M | C13: 1.27 | D13: 9 | E13: Produto 09 | F13: Produto 09 | G13: 1.1 | I13: 9 | J13: ="Produto 0" &I13 -> Produto 09
B14: MONTANTE 70 | C14: 1.62 | D14: 10 | E14: Produto 10 | F14: Produto 10 | G14: 1.1 | I14: 10 | J14: ="Produto " &I14 -> Produto 10
B15: MONTANTE 90 | C15: 1.92 | D15: 11 | E15: Produto 11 | F15: Produto 11 | G15: 1.1 | I15: 11 | J15: ="Produto " &I15 -> Produto 11
B16: TABICA BRANCA | C16: 1.1 | D16: 12 | E16: Produto 12 | F16: Produto 12 | G16: 1.4 | I16: 12 | J16: ="Produto " &I16 -> Produto 12
B17: TABICA GALVANIZADA | C17: 1.1 | D17: 13 | E17: Produto 13 | F17: Produto 13 | G17: 1.4 | I17: 13 | J17: ="Produto " &I17 -> Produto 13
D18: 14 | E18: Produto 14 | F18: Produto 14 | G18: 1.4 | I18: 14 | J18: ="Produto " &I18 -> Produto 14
D19: 15 | E19: Produto 15 | F19: Produto 15 | G19: 1.42 | I19: 15 | J19: ="Produto " &I19 -> Produto 15
D20: 16 | E20: Produto 16 | F20: Produto 16 | G20: 1.27 | I20: 16 | J20: ="Produto " &I20 -> Produto 16
D21: 17 | E21: Produto 17 | F21: Produto 17 | G21: 1.42 | I21: 17 | J21: ="Produto " &I21 -> Produto 17
D22: 18 | E22: Produto 18 | F22: Produto 18 | G22: 1.18 | I22: 18 | J22: ="Produto " &I22 -> Produto 18
D23: 19 | E23: Produto 19 | F23: Produto 19 | G23: 1.32 | I23: 19 | J23: ="Produto " &I23 -> Produto 19
D24: 20 | E24: Produto 20 | F24: Produto 20 | G24: 1.62 | I24: 20 | J24: ="Produto " &I24 -> Produto 20
D25: 21 | E25: Produto 21 | F25: Produto 21 | G25: 1.62 | I25: 21 | J25: ="Produto " &I25 -> Produto 21
D26: 22 | E26: Produto 22 | F26: Produto 22 | G26: 2.53 | I26: 22 | J26: ="Produto " &I26 -> Produto 22
D27: 23 | E27: Produto 23 | F27: Produto 23 | G27: 1.94 | I27: 23 | J27: ="Produto " &I27 -> Produto 23
D28: 24 | E28: Produto 24 | F28: Produto 24 | G28: 2.75 | I28: 24 | J28: ="Produto " &I28 -> Produto 24
D29: 25 | E29: Produto 25 | F29: Produto 25 | G29: 0.6 | I29: 25 | J29: ="Produto " &I29 -> Produto 25
... D36: 32 | E36: Produto 32 | F36: Produto 32 | G36: 1.1 | I36: 32 | J36: ="Produto " &I36 -> Produto 32

Sheet DashBoard Compras

Sheet DBO Compras
A1: ID | B1: N° do pedido | C1: Data | D1: ID contato | E1: Nome do contato | F1: Desconto | G1: Observações | H1: Situação | I1: ID produto | J1: Código | K1: Código no fornecedor | L1: Descrição | M1: Quantidade | N1: Valor unitário | O1: Un | P1: Frete do item | Q1: Ordem de compra | R1: Descrição Resumida | S1: Imposto | T1: Peso | U1: Peso Total | V1: Vlr Total | W1: mês | X1: ano | AB1: produto | AC1: Fornecedor
A2: 15455633497 | B2: 1 | C2: 44533 | D2: 15139603329 | E2: =VLOOKUP(RANDBETWEEN(1,20),AA:AC,3,FALSE) -> Comprador 18 | F2: 0 | H2: Atendido | I2: 15016073255 | J2: PRFL.00.0023 | L2: =VLOOKUP(RANDBETWEEN(1,16),AA:AC,2,FALSE) -> Produto 05 | M2: 2520 | N2: 14.2 | O2: PC | P2: 0 | Q2: 4713 | R2: =VLOOKUP(L2,'Auxiliar Compras'!A:B,2,FALSE) -> Produto 05 | S2: =VLOOKUP(L2,'Auxiliar Compras'!A:D,4,FALSE) -> 0 | T2: =VLOOKUP(L2,'Auxiliar Compras'!A:C,3,FALSE) -> 1.42 | U2: =T2*M2 -> 3578.4 | V2: =N2*M2+(M2*N2*S2) -> 35784 | W2: =VLOOKUP(MONTH(Tabela2[[#This Row],[Data]]),'Auxiliar Compras'!I:J,2,FALSE) -> Dez | X2: =YEAR(Tabela2[[#This Row],[Data]]) -> 2021 | AA2: 1 | AB2: ="Produto 0" &AA2 -> Produto 01 | AC2: ="Comprador 0"&AA2 -> Comprador 01
A3: 15493600861 | B3: 3 | C3: 44537 | D3: 14772821922 | E3: =VLOOKUP(RANDBETWEEN(1,20),AA:AC,3,FALSE) -> Comprador 09 | F3: 0 | H3: Atendido | I3: 14980702561 | J3: ICHP.00.0006 | L3: =VLOOKUP(RANDBETWEEN(1,16),AA:AC,2,FALSE) -> Produto 04 | M3: 13359 | N3: 7.74 | O3: KG | P3: 0 | Q3: 4982 | R3: =VLOOKUP(L3,'Auxiliar Compras'!A:B,2,FALSE) -> Produto 04 | S3: =VLOOKUP(L3,'Auxiliar Compras'!A:D,4,FALSE) -> 0 | T3: =VLOOKUP(L3,'Auxiliar Compras'!A:C,3,FALSE) -> 1.1 | U3: =T3*M3 -> 14694.9 | V3: =N3*M3+(M3*N3*S3) -> 103398.66 | W3: =VLOOKUP(MONTH(Tabela2[[#This Row],[Data]]),'Auxiliar Compras'!I:J,2,FALSE) -> Dez | X3: =YEAR(Tabela2[[#This Row],[Data]]) -> 2021 | AA3: 2 | AB3: ="Produto 0" &AA3 -> Produto 02 | AC3: ="Comprador 0"&AA3 -> Comprador 02
A4: 15531010205 | B4: 4 | C4: 44540 | D4: 15139603329 | E4: =VLOOKUP(RANDBETWEEN(1,20),AA:AC,3,FALSE) -> Comprador 10 | F4: 0 | H4: Atendido | I4: 15016043939 | J4: PRFL.00.0019 | L4: =VLOOKUP(RANDBETWEEN(1,16),AA:AC,2,FALSE) -> Produto 13 | M4: 2520 | N4: 13.75 | O4: PC | P4: 0 | Q4: 5008 | R4: =VLOOKUP(L4,'Auxiliar Compras'!A:B,2,FALSE) -> Produto 13 | S4: =VLOOKUP(L4,'Auxiliar Compras'!A:D,4,FALSE) -> 0 | T4: =VLOOKUP(L4,'Auxiliar Compras'!A:C,3,FALSE) -> 0.4 | U4: =T4*M4 -> 1008 | V4: =N4*M4+(M4*N4*S4) -> 34650 | W4: =VLOOKUP(MONTH(Tabela2[[#This Row],[Data]]),'Auxiliar Compras'!I:J,2,FALSE) -> Dez | X4: =YEAR(Tabela2[[#This Row],[Data]]) -> 2021 | AA4: 3 | AB4: ="Produto 0" &AA4 -> Produto 03 | AC4: ="Comprador 0"&AA4 -> Comprador 03
A5: 15531010205 | B5: 4 | C5: 44540 | D5: 15139603329 | E5: =VLOOKUP(RANDBETWEEN(1,20),AA:AC,3,FALSE) -> Comprador 19 | F5: 0 | H5: Atendido | I5: 15016093155 | J5: PRFL.00.0026 | L5: =VLOOKUP(RANDBETWEEN(1,16),AA:AC,2,FALSE) -> Produto 13 | M5: 300 | N5: 21.1 | O5: PC | P5: 0 | Q5: 5008 | R5: =VLOOKUP(L5,'Auxiliar Compras'!A:B,2,FALSE) -> Produto 13 | S5: =VLOOKUP(L5,'Auxiliar Compras'!A:D,4,FALSE) -> 0 | T5: =VLOOKUP(L5,'Auxiliar Compras'!A:C,3,FALSE) -> 0.4 | U5: =T5*M5 -> 120 | V5: =N5*M5+(M5*N5*S5) -> 6330 | W5: =VLOOKUP(MONTH(Tabela2[[#This Row],[Data]]),'Auxiliar Compras'!I:J,2,FALSE) -> Dez | X5: =YEAR(Tabela2[[#This Row],[Data]]) -> 2021 | AA5: 4 | AB5: ="Produto 0" &AA5 -> Produto 04 | AC5: ="Comprador 0"&AA5 -> Comprador 04
A6: 15583785440 | B6: 5 | C6: 44540 | D6: 14772821922 | E6: =VLOOKUP(RANDBETWEEN(1,20),AA:AC,3,FALSE) -> Comprador 10 | F6: 0 | H6: Atendido | I6: 14980702561 | J6: ICHP.00.0006 | L6: =VLOOKUP(RANDBETWEEN(1,16),AA:AC,2,FALSE) -> Produto 01 | M6: 24620 | N6: 9.15 | O6: KG | P6: 0 | R6: =VLOOKUP(L6,'Auxiliar Compras'!A:B,2,FALSE) -> Produto 01 | S6: =VLOOKUP(L6,'Auxiliar Compras'!A:D,4,FALSE) -> 0 | T6: =VLOOKUP(L6,'Auxiliar Compras'!A:C,3,FALSE) -> 1.1 | U6: =T6*M6 -> 27082 | V6: =N6*M6+(M6*N6*S6) -> 225273 | W6: =VLOOKUP(MONTH(Tabela2[[#This Row],[Data]]),'Auxiliar Compras'!I:J,2,FALSE) -> Dez | X6: =YEAR(Tabela2[[#This Row],[Data]]) -> 2021 | AA6: 5 | AB6: ="Produto 0" &AA6 -> Produto 05 | AC6: ="Comprador 0"&AA6 -> Comprador 05
A7: 15634553057 | B7: 6 | C7: 44550 | D7: 15139603329 | E7: =VLOOKUP(RANDBETWEEN(1,20),AA:AC,3,FALSE) -> Comprador 10 | F7: 0 | H7: Atendido | I7: 15016073255 | J7: PRFL.00.0023 | L7: =VLOOKUP(RANDBETWEEN(1,16),AA:AC,2,FALSE) -> Produto 12 | M7: 2520 | N7: 13.9 | O7: PC | P7: 0 | Q7: 4955 | R7: =VLOOKUP(L7,'Auxiliar Compras'!A:B,2,FALSE) -> Produto 12 | S7: =VLOOKUP(L7,'Auxiliar Compras'!A:D,4,FALSE) -> 0 | T7: =VLOOKUP(L7,'Auxiliar Compras'!A:C,3,FALSE) -> 1 | U7: =T7*M7 -> 2520 | V7: =N7*M7+(M7*N7*S7) -> 35028 | W7: =VLOOKUP(MONTH(Tabela2[[#This Row],[Data]]),'Auxiliar Compras'!I:J,2,FALSE) -> Dez | X7: =YEAR(Tabela2[[#This Row],[Data]]) -> 2021 | AA7: 6 | AB7: ="Produto 0" &AA7 -> Produto 06 | AC7: ="Comprador 0"&AA7 -> Comprador 06
A8: 15634593361 | B8: 7 | C8: 44550 | D8: 15478914765 | E8: =VLOOKUP(RANDBETWEEN(1,20),AA:AC,3,FALSE) -> Comprador 17 | F8: 0 | H8: Atendido | I8: 15395751673 | J8: PRFL.00.0039 | L8: =VLOOKUP(RANDBETWEEN(1,16),AA:AC,2,FALSE) -> Produto 01 | M8: 700 | N8: 7.14 | O8: PC | P8: 0 | Q8: 5094 | R8: =VLOOKUP(L8,'Auxiliar Compras'!A:B,2,FALSE) -> Produto 01 | S8: =VLOOKUP(L8,'Auxiliar Compras'!A:D,4,FALSE) -> 0 | T8: =VLOOKUP(L8,'Auxiliar Compras'!A:C,3,FALSE) -> 1.1 | U8: =T8*M8 -> 770 | V8: =N8*M8+(M8*N8*S8) -> 4998 | W8: =VLOOKUP(MONTH(Tabela2[[#This Row],[Data]]),'Auxiliar Compras'!I:J,2,FALSE) -> Dez | X8: =YEAR(Tabela2[[#This Row],[Data]]) -> 2021 | AA8: 7 | AB8: ="Produto 0" &AA8 -> Produto 07 | AC8: ="Comprador 0"&AA8 -> Comprador 07
A9: 15634894365 | B9: 8 | C9: 44550 | D9: 15603445654 | E9: =VLOOKUP(RANDBETWEEN(1,20),AA:AC,3,FALSE) -> Comprador 15 | F9: 0 | H9: Atendido | I9: 14981306750 | J9: MTUC.00.0003 | L9: =VLOOKUP(RANDBETWEEN(1,16),AA:AC,2,FALSE) -> Produto 14 | M9: 2 | N9: 213.26 | O9: RL | P9: 0 | Q9: 5082 | R9: =VLOOKUP(L9,'Auxiliar Compras'!A:B,2,FALSE) -> Produto 14 | S9: =VLOOKUP(L9,'Auxiliar Compras'!A:D,4,FALSE) -> 0 | T9: =VLOOKUP(L9,'Auxiliar Compras'!A:C,3,FALSE) -> 1.68 | U9: =T9*M9 -> 3.36 | V9: =N9*M9+(M9*N9*S9) -> 426.52 | W9: =VLOOKUP(MONTH(Tabela2[[#This Row],[Data]]),'Auxiliar Compras'!I:J,2,FALSE) -> Dez | X9: =YEAR(Tabela2[[#This Row],[Data]]) -> 2021 | AA9: 8 | AB9: ="Produto 0" &AA9 -> Produto 08 | AC9: ="Comprador 0"&AA9 -> Comprador 08
A10: 15635001792 | B10: 9 | C10: 44550 | D10: 15603436233 | E10: =VLOOKUP(RANDBETWEEN(1,20),AA:AC,3,FALSE) -> Comprador 13 | F10: 0 | H10: Atendido | I10: 15634854583 | J10: SRV0.00.0012 | L10: =VLOOKUP(RANDBETWEEN(1,16),AA:AC,2,FALSE) -> Produto 14 | M10: 1 | N10: 1600 | P10: 0 | Q10: 5085 | R10: =VLOOKUP(L10,'Auxiliar Compras'!A:B,2,FALSE) -> Produto 14 | S10: =VLOOKUP(L10,'Auxiliar Compras'!A:D,4,FALSE) -> 0 | T10: =VLOOKUP(L10,'Auxiliar Compras'!A:C,3,FALSE) -> 1.68 | U10: =T10*M10 -> 1.68 | V10: =N10*M10+(M10*N10*S10) -> 1600 | W10: =VLOOKUP(MONTH(Tabela2[[#This Row],[Data]]),'Auxiliar Compras'!I:J,2,FALSE) -> Dez | X10: =YEAR(Tabela2[[#This Row],[Data]]) -> 2021 | AA10: 9 | AB10: ="Produto 0" &AA10 -> Produto 09 | AC10: ="Comprador 0"&AA10 -> Comprador 09
A11: 15635057711 | B11: 10 | C11: 44550 | D11: 15603436233 | E11: =VLOOKUP(RANDBETWEEN(1,20),AA:AC,3,FALSE) -> Comprador 06 | F11: 0 | H11: Atendido | I11: 15634854583 | J11: SRV0.00.0012 | L11: =VLOOKUP(RANDBETWEEN(1,16),AA:AC,2,FALSE) -> Produto 05 | M11: 2 | N11: 1950 | P11: 0 | Q11: 5085 | R11: =VLOOKUP(L11,'Auxiliar Compras'!A:B,2,FALSE) -> Produto 05 | S11: =VLOOKUP(L11,'Auxiliar Compras'!A:D,4,FALSE) -> 0 | T11: =VLOOKUP(L11,'Auxiliar Compras'!A:C,3,FALSE) -> 1.42 | U11: =T11*M11 -> 2.84 | V11: =N11*M11+(M11*N11*S11) -> 3900 | W11: =VLOOKUP(MONTH(Tabela2[[#This Row],[Data]]),'Auxiliar Compras'!I:J,2,FALSE) -> Dez | X11: =YEAR(Tabela2[[#This Row],[Data]]) -> 2021 | AA11: 10 | AB11: ="Produto " &AA11 -> Produto 10 | AC11: ="Comprador "&AA11 -> Comprador 10
A12: 15656137428 | B12: 11 | C12: 44552 | D12: 15130445011 | E12: =VLOOKUP(RANDBETWEEN(1,20),AA:AC,3,FALSE) -> Comprador 06 | F12: 0 | H12: Atendido | I12: 14981313809 | J12: ICHP.00.0001 | L12: =VLOOKUP(RANDBETWEEN(1,16),AA:AC,2,FALSE) -> Produto 04 | M12: 20402 | N12: 9.2 | O12: KG | P12: 0 | R12: =VLOOKUP(L12,'Auxiliar Compras'!A:B,2,FALSE) -> Produto 04 | S12: =VLOOKUP(L12,'Auxiliar Compras'!A:D,4,FALSE) -> 0 | T12: =VLOOKUP(L12,'Auxiliar Compras'!A:C,3,FALSE) -> 1.1 | U12: =T12*M12 -> 22442.2 | V12: =N12*M12+(M12*N12*S12) -> 187698.4 | W12: =VLOOKUP(MONTH(Tabela2[[#This Row],[Data]]),'Auxiliar Compras'!I:J,2,FALSE) -> Dez | X12: =YEAR(Tabela2[[#This Row],[Data]]) -> 2021 | AA12: 11 | AB12: ="Produto " &AA12 -> Produto 11 | AC12: ="Comprador "&AA12 -> Comprador 11
A13: 15656216577 | B13: 12 | C13: 44552 | D13: 15139603329 | E13: =VLOOKUP(RANDBETWEEN(1,20),AA:AC,3,FALSE) -> Comprador 18 | F13: 0 | H13: Atendido | I13: 15016073255 | J13: PRFL.00.0023 | L13: =VLOOKUP(RANDBETWEEN(1,16),AA:AC,2,FALSE) -> Produto 08 | M13: 4620 | N13: 13.9 | O13: PC | P13: 0 | Q13: 5095 | R13: =VLOOKUP(L13,'Auxiliar Compras'!A:B,2,FALSE) -> Produto 08 | S13: =VLOOKUP(L13,'Auxiliar Compras'!A:D,4,FALSE) -> 0 | T13: =VLOOKUP(L13,'Auxiliar Compras'!A:C,3,FALSE) -> 1 | U13: =T13*M13 -> 4620 | V13: =N13*M13+(M13*N13*S13) -> 64218 | W13: =VLOOKUP(MONTH(Tabela2[[#This Row],[Data]]),'Auxiliar Compras'!I:J,2,FALSE) -> Dez | X13: =YEAR(Tabela2[[#This Row],[Data]]) -> 2021 | AA13: 12 | AB13: ="Produto " &AA13 -> Produto 12 | AC13: ="Comprador "&AA13 -> Comprador 12
A14: 15656216577 | B14: 12 | C14: 44552 | D14: 15139603329 | E14: =VLOOKUP(RANDBETWEEN(1,20),AA:AC,3,FALSE) -> Comprador 05 | F14: 0 | H14: Atendido | I14: 15016093155 | J14: PRFL.00.0026 | L14: =VLOOKUP(RANDBETWEEN(1,16),AA:AC,2,FALSE) -> Produto 02 | M14: 900 | N14: 21.1 | O14: PC | P14: 0 | Q14: 5095 | R14: =VLOOKUP(L14,'Auxiliar Compras'!A:B,2,FALSE) -> Produto 02 | S14: =VLOOKUP(L14,'Auxiliar Compras'!A:D,4,FALSE) -> 0.05 | T14: =VLOOKUP(L14,'Auxiliar Compras'!A:C,3,FALSE) -> 1 | U14: =T14*M14 -> 900 | V14: =N14*M14+(M14*N14*S14) -> 19939.5 | W14: =VLOOKUP(MONTH(Tabela2[[#This Row],[Data]]),'Auxiliar Compras'!I:J,2,FALSE) -> Dez | X14: =YEAR(Tabela2[[#This Row],[Data]]) -> 2021 | AA14: 13 | AB14: ="Produto " &AA14 -> Produto 13 | AC14: ="Comprador "&AA14 -> Comprador 13
A15: 15656379350 | B15: 13 | C15: 44552 | D15: 15018323304 | E15: =VLOOKUP(RANDBETWEEN(1,20),AA:AC,3,FALSE) -> Comprador 13 | F15: 0 | H15: Atendido | I15: 14981313809 | J15: ICHP.00.0001 | L15: =VLOOKUP(RANDBETWEEN(1,16),AA:AC,2,FALSE) -> Produto 05 | M15: 25497 | N15: 9.38 | O15: KG | P15: 0 | R15: =VLOOKUP(L15,'Auxiliar Compras'!A:B,2,FALSE) -> Produto 05 | S15: =VLOOKUP(L15,'Auxiliar Compras'!A:D,4,FALSE) -> 0 | T15: =VLOOKUP(L15,'Auxiliar Compras'!A:C,3,FALSE) -> 1.42 | U15: =T15*M15 -> 36205.74 | V15: =N15*M15+(M15*N15*S15) -> 239161.86 | W15: =VLOOKUP(MONTH(Tabela2[[#This Row],[Data]]),'Auxiliar Compras'!I:J,2,FALSE) -> Dez | X15: =YEAR(Tabela2[[#This Row],[Data]]) -> 2021 | AA15: 14 | AB15: ="Produto " &AA15 -> Produto 14 | AC15: ="Comprador "&AA15 -> Comprador 14
A16: 15656392237 | B16: 14 | C16: 44552 | D16: 15018323304 | E16: =VLOOKUP(RANDBETWEEN(1,20),AA:AC,3,FALSE) -> Comprador 11 | F16: 0 | H16: Atendido | I16: 14981313809 | J16: ICHP.00.0001 | L16: =VLOOKUP(RANDBETWEEN(1,16),AA:AC,2,FALSE) -> Produto 09 | M16: 7100 | N16: 9.65 | O16: KG | P16: 0 | R16: =VLOOKUP(L16,'Auxiliar Compras'!A:B,2,FALSE) -> Produto 09 | S16: =VLOOKUP(L16,'Auxiliar Compras'!A:D,4,FALSE) -> 0 | T16: =VLOOKUP(L16,'Auxiliar Compras'!A:C,3,FALSE) -> 1 | U16: =T16*M16 -> 7100 | V16: =N16*M16+(M16*N16*S16) -> 68515 | W16: =VLOOKUP(MONTH(Tabela2[[#This Row],[Data]]),'Auxiliar Compras'!I:J,2,FALSE) -> Dez | X16: =YEAR(Tabela2[[#This Row],[Data]]) -> 2021 | AA16: 15 | AB16: ="Produto " &AA16 -> Produto 15 | AC16: ="Comprador "&AA16 -> Comprador 15
A17: 15656403917 | B17: 15 | C17: 44552 | D17: 15018323304 | E17: =VLOOKUP(RANDBETWEEN(1,20),AA:AC,3,FALSE) -> Comprador 03 | F17: 0 | H17: Atendido | I17: 14981313809 | J17: ICHP.00.0001 | L17: =VLOOKUP(RANDBETWEEN(1,16),AA:AC,2,FALSE) -> Produto 07 | M17: 7510 | N17: 9.35 | O17: KG | P17: 0 | R17: =VLOOKUP(L17,'Auxiliar Compras'!A:B,2,FALSE) -> Produto 07 | S17: =VLOOKUP(L17,'Auxiliar Compras'!A:D,4,FALSE) -> 0 | T17: =VLOOKUP(L17,'Auxiliar Compras'!A:C,3,FALSE) -> 0.5 | U17: =T17*M17 -> 3755 | V17: =N17*M17+(M17*N17*S17) -> 70218.5 | W17: =VLOOKUP(MONTH(Tabela2[[#This Row],[Data]]),'Auxiliar Compras'!I:J,2,FALSE) -> Dez | X17: =YEAR(Tabela2[[#This Row],[Data]]) -> 2021 | AA17: 16 | AB17: ="Produto " &AA17 -> Produto 16 | AC17: ="Comprador "&AA17 -> Comprador 16
A18: 15656417923 | B18: 16 | C18: 44552 | D18: 15018323304 | E18: =VLOOKUP(RANDBETWEEN(1,20),AA:AC,3,FALSE) -> Comprador 02 | F18: 0 | H18: Atendido | I18: 14981313809 | J18: ICHP.00.0001 | L18: =VLOOKUP(RANDBETWEEN(1,16),AA:AC,2,FALSE) -> Produto 02 | M18: 23476 | N18: 9.48 | O18: KG | P18: 0 | R18: =VLOOKUP(L18,'Auxiliar Compras'!A:B,2,FALSE) -> Produto 02 | S18: =VLOOKUP(L18,'Auxiliar Compras'!A:D,4,FALSE) -> 0.05 | T18: =VLOOKUP(L18,'Auxiliar Compras'!A:C,3,FALSE) -> 1 | U18: =T18*M18 -> 23476 | V18: =N18*M18+(M18*N18*S18) -> 233680.1 | W18: =VLOOKUP(MONTH(Tabela2[[#This Row],[Data]]),'Auxiliar Compras'!I:J,2,FALSE) -> Dez | X18: =YEAR(Tabela2[[#This Row],[Data]]) -> 2021 | AA18: 17 | AC18: ="Comprador "&AA18 -> Comprador 17
A19: 15656431575 | B19: 17 | C19: 44552 | D19: 15018323304 | E19: =VLOOKUP(RANDBETWEEN(1,20),AA:AC,3,FALSE) -> Comprador 20 | F19: 0 | H19: Atendido | I19: 14981313809 | J19: ICHP.00.0001 | L19: =VLOOKUP(RANDBETWEEN(1,16),AA:AC,2,FALSE) -> Produto 09 | M19: 26808 | N19: 9.2 | O19: KG | P19: 0 | R19: =VLOOKUP(L19,'Auxiliar Compras'!A:B,2,FALSE) -> Produto 09 | S19: =VLOOKUP(L19,'Auxiliar Compras'!A:D,4,FALSE) -> 0 | T19: =VLOOKUP(L19,'Auxiliar Compras'!A:C,3,FALSE) -> 1 | U19: =T19*M19 -> 26808 | V19: =N19*M19+(M19*N19*S19) -> 246633.6 | W19: =VLOOKUP(MONTH(Tabela2[[#This Row],[Data]]),'Auxiliar Compras'!I:J,2,FALSE) -> Dez | X19: =YEAR(Tabela2[[#This Row],[Data]]) -> 2021 | AA19: 18 | AC19: ="Comprador "&AA19 -> Comprador 18
A20: 15656455702 | B20: 18 | C20: 44552 | D20: 15478914765 | E20: =VLOOKUP(RANDBETWEEN(1,20),AA:AC,3,FALSE) -> Comprador 07 | F20: 0 | H20: Atendido | I20: 15395751673 | J20: PRFL.00.0039 | L20: =VLOOKUP(RANDBETWEEN(1,16),AA:AC,2,FALSE) -> Produto 11 | M20: 1700 | N20: 7.14 | O20: PC | P20: 0 | Q20: 5094 | R20: =VLOOKUP(L20,'Auxiliar Compras'!A:B,2,FALSE) -> Produto 11 | S20: =VLOOKUP(L20,'Auxiliar Compras'!A:D,4,FALSE) -> 0 | T20: =VLOOKUP(L20,'Auxiliar Compras'!A:C,3,FALSE) -> 1 | U20: =T20*M20 -> 1700 | V20: =N20*M20+(M20*N20*S20) -> 12138 | W20: =VLOOKUP(MONTH(Tabela2[[#This Row],[Data]]),'Auxiliar Compras'!I:J,2,FALSE) -> Dez | X20: =YEAR(Tabela2[[#This Row],[Data]]) -> 2021 | AA20: 19 | AC20: ="Comprador "&AA20 -> Comprador 19
A21: 15656725936 | B21: 19 | C21: 44552 | D21: 14772821922 | E21: =VLOOKUP(RANDBETWEEN(1,20),AA:AC,3,FALSE) -> Comprador 10 | F21: 0 | H21: Atendido | I21: 14980702561 | J21: ICHP.00.0006 | L21: =VLOOKUP(RANDBETWEEN(1,16),AA:AC,2,FALSE) -> Produto 02 | M21: 23968 | N21: 9.77 | O21: KG | P21: 0 | Q21: 3646 | R21: =VLOOKUP(L21,'Auxiliar Compras'!A:B,2,FALSE) -> Produto 02 | S21: =VLOOKUP(L21,'Auxiliar Compras'!A:D,4,FALSE) -> 0.05 | T21: =VLOOKUP(L21,'Auxiliar Compras'!A:C,3,FALSE) -> 1 | U21: =T21*M21 -> 23968 | V21: =N21*M21+(M21*N21*S21) -> 245875.73 | W21: =VLOOKUP(MONTH(Tabela2[[#This Row],[Data]]),'Auxiliar Compras'!I:J,2,FALSE) -> Dez | X21: =YEAR(Tabela2[[#This Row],[Data]]) -> 2021 | AA21: 20 | AC21: ="Comprador "&AA21 -> Comprador 20
A22: 15656740402 | B22: 20 | C22: 44552 | D22: 14772821922 | E22: =VLOOKUP(RANDBETWEEN(1,20),AA:AC,3,FALSE) -> Comprador 08 | F22: 0 | H22: Atendido | I22: 14980702561 | J22: ICHP.00.0006 | L22: =VLOOKUP(RANDBETWEEN(1,16),AA:AC,2,FALSE) -> Produto 05 | M22: 13440 | N22: 9.3 | O22: KG | P22: 0 | Q22: 3977 | R22: =VLOOKUP(L22,'Auxiliar Compras'!A:B,2,FALSE) -> Produto 05 | S22: =VLOOKUP(L22,'Auxiliar Compras'!A:D,4,FALSE) -> 0 | T22: =VLOOKUP(L22,'Auxiliar Compras'!A:C,3,FALSE) -> 1.42 | U22: =T22*M22 -> 19084.8 | V22: =N22*M22+(M22*N22*S22) -> 124992 | W22: =VLOOKUP(MONTH(Tabela2[[#This Row],[Data]]),'Auxiliar Compras'!I:J,2,FALSE) -> Dez | X22: =YEAR(Tabela2[[#This Row],[Data]]) -> 2021
A23: 15656778040 | B23: 21 | C23: 44552 | D23: 14772821922 | E23: =VLOOKUP(RANDBETWEEN(1,20),AA:AC,3,FALSE) -> Comprador 16 | F23: 0 | H23: Atendido | I23: 14980702561 | J23: ICHP.00.0006 | L23: =VLOOKUP(RANDBETWEEN(1,16),AA:AC,2,FALSE) -> Produto 13 | M23: 11818 | N23: 9.3 | O23: KG | P23: 0 | Q23: 4013 | R23: =VLOOKUP(L23,'Auxiliar Compras'!A:B,2,FALSE) -> Produto 13 | S23: =VLOOKUP(L23,'Auxiliar Compras'!A:D,4,FALSE) -> 0 | T23: =VLOOKUP(L23,'Auxiliar Compras'!A:C,3,FALSE) -> 0.4 | U23: =T23*M23 -> 4727.2 | V23: =N23*M23+(M23*N23*S23) -> 109907.4 | W23: =VLOOKUP(MONTH(Tabela2[[#This Row],[Data]]),'Auxiliar Compras'!I:J,2,FALSE) -> Dez | X23: =YEAR(Tabela2[[#This Row],[Data]]) -> 2021
A24: 15656795929 | B24: 22 | C24: 44552 | D24: 14772821922 | E24: =VLOOKUP(RANDBETWEEN(1,20),AA:AC,3,FALSE) -> Comprador 07 | F24: 0 | H24: Atendido | I24: 14980702561 | J24: ICHP.00.0006 | L24: =VLOOKUP(RANDBETWEEN(1,16),AA:AC,2,FALSE) -> Produto 15 | M24: 8588 | N24: 9.3 | O24: KG | P24: 0 | Q24: 4118 | R24: =VLOOKUP(L24,'Auxiliar Compras'!A:B,2,FALSE) -> Produto 15 | S24: =VLOOKUP(L24,'Auxiliar Compras'!A:D,4,FALSE) -> 0 | T24: =VLOOKUP(L24,'Auxiliar Compras'!A:C,3,FALSE) -> 1.1 | U24: =T24*M24 -> 9446.8 | V24: =N24*M24+(M24*N24*S24) -> 79868.4 | W24: =VLOOKUP(MONTH(Tabela2[[#This Row],[Data]]),'Auxiliar Compras'!I:J,2,FALSE) -> Dez | X24: =YEAR(Tabela2[[#This Row],[Data]]) -> 2021
A25: 15656813379 | B25: 23 | C25: 44552 | D25: 14772821922 | E25: =VLOOKUP(RANDBETWEEN(1,20),AA:AC,3,FALSE) -> Comprador 20 | F25: 0 | H25: Atendido | I25: 14980702561 | J25: ICHP.00.0006 | L25: =VLOOKUP(RANDBETWEEN(1,16),AA:AC,2,FALSE) -> Produto 06 | M25: 14106 | N25: 7.93 | O25: KG | P25: 0 | Q25: 4606 | R25: =VLOOKUP(L25,'Auxiliar Compras'!A:B,2,FALSE) -> Produto 06 | S25: =VLOOKUP(L25,'Auxiliar Compras'!A:D,4,FALSE) -> 0 | T25: =VLOOKUP(L25,'Auxiliar Compras'!A:C,3,FALSE) -> 1.1 | U25: =T25*M25 -> 15516.6 | V25: =N25*M25+(M25*N25*S25) -> 111860.58 | W25: =VLOOKUP(MONTH(Tabela2[[#This Row],[Data]]),'Auxiliar Compras'!I:J,2,FALSE) -> Dez | X25: =YEAR(Tabela2[[#This Row],[Data]]) -> 2021
A26: 15656822711 | B26: 24 | C26: 44552 | D26: 14772821922 | E26: =VLOOKUP(RANDBETWEEN(1,20),AA:AC,3,FALSE) -> Comprador 14 | F26: 0 | H26: Atendido | I26: 14980702561 | J26: ICHP.00.0006 | L26: =VLOOKUP(RANDBETWEEN(1,16),AA:AC,2,FALSE) -> Produto 08 | M26: 27695 | N26: 8.98 | O26: KG | P26: 0 | Q26: 4606 | R26: =VLOOKUP(L26,'Auxiliar Compras'!A:B,2,FALSE) -> Produto 08 | S26: =VLOOKUP(L26,'Auxiliar Compras'!A:D,4,FALSE) -> 0 | T26: =VLOOKUP(L26,'Auxiliar Compras'!A:C,3,FALSE) -> 1 | U26: =T26*M26 -> 27695 | V26: =N26*M26+(M26*N26*S26) -> 248701.1 | W26: =VLOOKUP(MONTH(Tabela2[[#This Row],[Data]]),'Auxiliar Compras'!I:J,2,FALSE) -> Dez | X26: =YEAR(Tabela2[[#This Row],[Data]]) -> 2021
A27: 15656842731 | B27: 25 | C27: 44552 | D27: 14772821922 | E27: =VLOOKUP(RANDBETWEEN(1,20),AA:AC,3,FALSE) -> Comprador 06 | F27: 0 | H27: Atendido | I27: 14980702561 | J27: ICHP.00.0006 | L27: =VLOOKUP(RANDBETWEEN(1,16),AA:AC,2,FALSE) -> Produto 09 | M27: 25188 | N27: 9.5 | O27: KG | P27: 0 | Q27: 4730 | R27: =VLOOKUP(L27,'Auxiliar Compras'!A:B,2,FALSE) -> Produto 09 | S27: =VLOOKUP(L27,'Auxiliar Compras'!A:D,4,FALSE) -> 0 | T27: =VLOOKUP(L27,'Auxiliar Compras'!A:C,3,FALSE) -> 1 | U27: =T27*M27 -> 25188 | V27: =N27*M27+(M27*N27*S27) -> 239286 | W27: =VLOOKUP(MONTH(Tabela2[[#This Row],[Data]]),'Auxiliar Compras'!I:J,2,FALSE) -> Dez | X27: =YEAR(Tabela2[[#This Row],[Data]]) -> 2021
A28: 15656853363 | B28: 26 | C28: 44552 | D28: 14772821922 | E28: =VLOOKUP(RANDBETWEEN(1,20),AA:AC,3,FALSE) -> Comprador 11 | F28: 0 | H28: Atendido | I28: 14980702561 | J28: ICHP.00.0006 | L28: =VLOOKUP(RANDBETWEEN(1,16),AA:AC,2,FALSE) -> Produto 16 | M28: 25043 | N28: 9.4 | O28: KG | P28: 0 | Q28: 4748 | R28: =VLOOKUP(L28,'Auxiliar Compras'!A:B,2,FALSE) -> Produto 16 | S28: =VLOOKUP(L28,'Auxiliar Compras'!A:D,4,FALSE) -> 0.05 | T28: =VLOOKUP(L28,'Auxiliar Compras'!A:C,3,FALSE) -> 1 | U28: =T28*M28 -> 25043 | V28: =N28*M28+(M28*N28*S28) -> 247174.41 | W28: =VLOOKUP(MONTH(Tabela2[[#This Row],[Data]]),'Auxiliar Compras'!I:J,2,FALSE) -> Dez | X28: =YEAR(Tabela2[[#This Row],[Data]]) -> 2021
A29: 15656876602 | B29: 27 | C29: 44552 | D29: 15450924520 | E29: =VLOOKUP(RANDBETWEEN(1,20),AA:AC,3,FALSE) -> Comprador 19 | F29: 0 | H29: Atendido | I29: 14980702561 | J29: ICHP.00.0006 | L29: =VLOOKUP(RANDBETWEEN(1,16),AA:AC,2,FALSE) -> Produto 02 | M29: 22885 | N29: 8.75 | O29: KG | P29: 0 | Q29: 4842 | R29: =VLOOKUP(L29,'Auxiliar Compras'!A:B,2,FALSE) -> Produto 02 | S29: =VLOOKUP(L29,'Auxiliar Compras'!A:D,4,FALSE) -> 0.05 | T29: =VLOOKUP(L29,'Auxiliar Compras'!A:C,3,FALSE) -> 1 | U29: =T29*M29 -> 22885 | V29: =N29*M29+(M29*N29*S29) -> 210255.94 | W29: =VLOOKUP(MONTH(Tabela2[[#This Row],[Data]]),'Auxiliar Compras'!I:J,2,FALSE) -> Dez | X29: =YEAR(Tabela2[[#This Row],[Data]]) -> 2021
A30: 15657069663 | B30: 28 | C30: 44552 | D30: 14979221560 | E30: =VLOOKUP(RANDBETWEEN(1,20),AA:AC,3,FALSE) -> Comprador 08 | F30: 0 | H30: Atendido | I30: 14979354095 | J30: INDS.00.0001 | K30: 50790031 | L30: =VLOOKUP(RANDBETWEEN(1,16),AA:AC,2,FALSE) -> Produto 07 | M30: 23968 | N30: 0.18 | O30: TO | P30: 0 | Q30: 3682 | R30: =VLOOKUP(L30,'Auxiliar Compras'!A:B,2,FALSE) -> Produto 07 | S30: =VLOOKUP(L30,'Auxiliar Compras'!A:D,4,FALSE) -> 0 | T30: =VLOOKUP(L30,'Auxiliar Compras'!A:C,3,FALSE) -> 0.5 | U30: =T30*M30 -> 11984 | V30: =N30*M30+(M30*N30*S30) -> 4314.24 | W30: =VLOOKUP(MONTH(Tabela2[[#This Row],[Data]]),'Auxiliar Compras'!I:J,2,FALSE) -> Dez | X30: =YEAR(Tabela2[[#This Row],[Data]]) -> 2021
A31: 15657078733 | B31: 29 | C31: 44552 | D31: 14979221560 | E31: =VLOOKUP(RANDBETWEEN(1,20),AA:AC,3,FALSE) -> Comprador 02 | F31: 0 | H31: Atendido | I31: 14979354095 | J31: INDS.00.0001 | K31: 50790031 | L31: =VLOOKUP(RANDBETWEEN(1,16),AA:AC,2,FALSE) -> Produto 10 | M31: 30773 | N31: 0.18 | O31: TO | P31: 0 | Q31: 3983/4041/4132 | R31: =VLOOKUP(L31,'Auxiliar Compras'!A:B,2,FALSE) -> Produto 10 | S31: =VLOOKUP(L31,'Auxiliar Compras'!A:D,4,FALSE) -> 0 | T31: =VLOOKUP(L31,'Auxiliar Compras'!A:C,3,FALSE) -> 1 | U31: =T31*M31 -> 30773 | V31: =N31*M31+(M31*N31*S31) -> 5539.14 | W31: =VLOOKUP(MONTH(Tabela2[[#This Row],[Data]]),'Auxiliar Compras'!I:J,2,FALSE) -> Dez | X31: =YEAR(Tabela2[[#This Row],[Data]]) -> 2021
A32: 15657087809 | B32: 30 | C32: 44552 | D32: 14979221560 | E32: =VLOOKUP(RANDBETWEEN(1,20),AA:AC,3,FALSE) -> Comprador 02 | F32: 0 | H32: Atendido | I32: 14979354095 | J32: INDS.00.0001 | K32: 50790031 | L32: =VLOOKUP(RANDBETWEEN(1,16),AA:AC,2,FALSE) -> Produto 02 | M32: 42704 | N32: 0.18 | O32: TO | P32: 0 | Q32: 4235/4287/4348 | R32: =VLOOKUP(L32,'Auxiliar Compras'!A:B,2,FALSE) -> Produto 02 | S32: =VLOOKUP(L32,'Auxiliar Compras'!A:D,4,FALSE) -> 0.05 | T32: =VLOOKUP(L32,'Auxiliar Compras'!A:C,3,FALSE) -> 1 | U32: =T32*M32 -> 42704 | V32: =N32*M32+(M32*N32*S32) -> 8071.056 | W32: =VLOOKUP(MONTH(Tabela2[[#This Row],[Data]]),'Auxiliar Compras'!I:J,2,FALSE) -> Dez | X32: =YEAR(Tabela2[[#This Row],[Data]]) -> 2021
A33: 15657095851 | B33: 31 | C33: 44552 | D33: 14979221560 | E33: =VLOOKUP(RANDBETWEEN(1,20),AA:AC,3,FALSE) -> Comprador 01 | F33: 0 | H33: Atendido | I33: 14979354095 | J33: INDS.00.0001 | K33: 50790031 | L33: =VLOOKUP(RANDBETWEEN(1,16),AA:AC,2,FALSE) -> Produto 15 | M33: 59789 | N33: 0.18 | O33: TO | P33: 0 | Q33: 4541/4563/4579/4600/4617/4626 | R33: =VLOOKUP(L33,'Auxiliar Compras'!A:B,2,FALSE) -> Produto 15 | S33: =VLOOKUP(L33,'Auxiliar Compras'!A:D,4,FALSE) -> 0 | T33: =VLOOKUP(L33,'Auxiliar Compras'!A:C,3,FALSE) -> 1.1 | U33: =T33*M33 -> 65767.9 | V33: =N33*M33+(M33*N33*S33) -> 10762.02 | W33: =VLOOKUP(MONTH(Tabela2[[#This Row],[Data]]),'Auxiliar Compras'!I:J,2,FALSE) -> Dez | X33: =YEAR(Tabela2[[#This Row],[Data]]) -> 2021
A34: 15657105737 | B34: 32 | C34: 44552 | D34: 14979221560 | E34: =VLOOKUP(RANDBETWEEN(1,20),AA:AC,3,FALSE) -> Comprador 10 | F34: 0 | H34: Atendido | I34: 14979354095 | J34: INDS.00.0001 | K34: 50790031 | L34: =VLOOKUP(RANDBETWEEN(1,16),AA:AC,2,FALSE) -> Produto 03 | M34: 87863 | N34: 0.18 | O34: TO | P34: 0 | Q34: 4706/4723/4745/4763/4770/4836/ | R34: =VLOOKUP(L34,'Auxiliar Compras'!A:B,2,FALSE) -> Produto 03 | S34: =VLOOKUP(L34,'Auxiliar Compras'!A:D,4,FALSE) -> 0.05 | T34: =VLOOKUP(L34,'Auxiliar Compras'!A:C,3,FALSE) -> 1 | U34: =T34*M34 -> 87863 | V34: =N34*M34+(M34*N34*S34) -> 16606.107 | W34: =VLOOKUP(MONTH(Tabela2[[#This Row],[Data]]),'Auxiliar Compras'!I:J,2,FALSE) -> Dez | X34: =YEAR(Tabela2[[#This Row],[Data]]) -> 2021
A35: 15657118424 | B35: 33 | C35: 44552 | D35: 14979221560 | E35: =VLOOKUP(RANDBETWEEN(1,20),AA:AC,3,FALSE) -> Comprador 11 | F35: 0 | H35: Atendido | I35: 14979354095 | J35: INDS.00.0001 | K35: 50790031 | L35: =VLOOKUP(RANDBETWEEN(1,16),AA:AC,2,FALSE) -> Produto 01 | M35: 97789 | N35: 0.18 | O35: TO | P35: 0 | Q35: 4954/4957/4966/5009/5060/5062 | R35: =VLOOKUP(L35,'Auxiliar Compras'!A:B,2,FALSE) -> Produto 01 | S35: =VLOOKUP(L35,'Auxiliar Compras'!A:D,4,FALSE) -> 0 | T35: =VLOOKUP(L35,'Auxiliar Compras'!A:C,3,FALSE) -> 1.1 | U35: =T35*M35 -> 107567.9 | V35: =N35*M35+(M35*N35*S35) -> 17602.02 | W35: =VLOOKUP(MONTH(Tabela2[[#This Row],[Data]]),'Auxiliar Compras'!I:J,2,FALSE) -> Dez | X35: =YEAR(Tabela2[[#This Row],[Data]]) -> 2021
A36: 15657154163 | B36: 34 | C36: 44552 | D36: 15130445011 | E36: =VLOOKUP(RANDBETWEEN(1,20),AA:AC,3,FALSE) -> Comprador 10 | F36: 0 | H36: Atendido | I36: 14981313809 | J36: ICHP.00.0001 | L36: =VLOOKUP(RANDBETWEEN(1,16),AA:AC,2,FALSE) -> Produto 08 | M36: 20690 | N36: 9.35 | O36: KG | P36: 0 | Q36: 4597 | R36: =VLOOKUP(L36,'Auxiliar Compras'!A:B,2,FALSE) -> Produto 08 | S36: =VLOOKUP(L36,'Auxiliar Compras'!A:D,4,FALSE) -> 0 | T36: =VLOOKUP(L36,'Auxiliar Compras'!A:C,3,FALSE) -> 1 | U36: =T36*M36 -> 20690 | V36: =N36*M36+(M36*N36*S36) -> 193451.5 | W36: =VLOOKUP(MONTH(Tabela2[[#This Row],[Data]]),'Auxiliar Compras'!I:J,2,FALSE) -> Dez | X36: =YEAR(Tabela2[[#This Row],[Data]]) -> 2021
A37: 15657181694 | B37: 35 | C37: 44552 | D37: 15603436233 | E37: =VLOOKUP(RANDBETWEEN(1,20),AA:AC,3,FALSE) -> Comprador 05 | F37: 0 | H37: Atendido | I37: 15634854583 | J37: SRV0.00.0012 | L37: =VLOOKUP(RANDBETWEEN(1,16),AA:AC,2,FALSE) -> Produto 07 | M37: 1 | N37: 700 | O37: KG | P37: 0 | Q37: 5016 | R37: =VLOOKUP(L37,'Auxiliar Compras'!A:B,2,FALSE) -> Produto 07 | S37: =VLOOKUP(L37,'Auxiliar Compras'!A:D,4,FALSE) -> 0 | T37: =VLOOKUP(L37,'Auxiliar Compras'!A:C,3,FALSE) -> 0.5 | U37: =T37*M37 -> 0.5 | V37: =N37*M37+(M37*N37*S37) -> 700 | W37: =VLOOKUP(MONTH(Tabela2[[#This Row],[Data]]),'Auxiliar Compras'!I:J,2,FALSE) -> Dez | X37: =YEAR(Tabela2[[#This Row],[Data]]) -> 2021
A38: 15657200117 | B38: 36 | C38: 44552 | D38: 15603436233 | E38: =VLOOKUP(RANDBETWEEN(1,20),AA:AC,3,FALSE) -> Comprador 12 | F38: 0 | H38: Atendido | I38: 15634854583 | J38: SRV0.00.0012 | L38: =VLOOKUP(RANDBETWEEN(1,16),AA:AC,2,FALSE) -> Produto 14 | M38: 6 | N38: 1600 | O38: KG | P38: 0 | Q38: 4568/4674/4737/4820/4212 | R38: =VLOOKUP(L38,'Auxiliar Compras'!A:B,2,FALSE) -> Produto 14 | S38: =VLOOKUP(L38,'Auxiliar Compras'!A:D,4,FALSE) -> 0 | T38: =VLOOKUP(L38,'Auxiliar Compras'!A:C,3,FALSE) -> 1.68 | U38: =T38*M38 -> 10.08 | V38: =N38*M38+(M38*N38*S38) -> 9600 | W38: =VLOOKUP(MONTH(Tabela2[[#This Row],[Data]]),'Auxiliar Compras'!I:J,2,FALSE) -> Dez | X38: =YEAR(Tabela2[[#This Row],[Data]]) -> 2021
A39: 15657200117 | B39: 36 | C39: 44552 | D39: 15603436233 | E39: =VLOOKUP(RANDBETWEEN(1,20),AA:AC,3,FALSE) -> Comprador 20 | F39: 0 | H39: Atendido | I39: 15634854583 | J39: SRV0.00.0012 | L39: =VLOOKUP(RANDBETWEEN(1,16),AA:AC,2,FALSE) -> Produto 13 | M39: 1 | N39: 1532.22 | O39: KG | P39: 0 | Q39: 4568/4674/4737/4820/4212 | R39: =VLOOKUP(L39,'Auxiliar Compras'!A:B,2,FALSE) -> Produto 13 | S39: =VLOOKUP(L39,'Auxiliar Compras'!A:D,4,FALSE) -> 0 | T39: =VLOOKUP(L39,'Auxiliar Compras'!A:C,3,FALSE) -> 0.4 | U39: =T39*M39 -> 0.4 | V39: =N39*M39+(M39*N39*S39) -> 1532.22 | W39: =VLOOKUP(MONTH(Tabela2[[#This Row],[Data]]),'Auxiliar Compras'!I:J,2,FALSE) -> Dez | X39: =YEAR(Tabela2[[#This Row],[Data]]) -> 2021
A40: 15657315090 | B40: 37 | C40: 44552 | D40: 15506057572 | E40: =VLOOKUP(RANDBETWEEN(1,20),AA:AC,3,FALSE) -> Comprador 02 | F40: 0 | H40: Atendido | I40: 15657228743 | J40: INDS.00.0003 | L40: =VLOOKUP(RANDBETWEEN(1,16),AA:AC,2,FALSE) -> Produto 10 | M40: 1 | N40: 5460 | O40: KG | P40: 0 | Q40: 4538/4833 | R40: =VLOOKUP(L40,'Auxiliar Compras'!A:B,2,FALSE) -> Produto 10 | S40: =VLOOKUP(L40,'Auxiliar Compras'!A:D,4,FALSE) -> 0 | T40: =VLOOKUP(L40,'Auxiliar Compras'!A:C,3,FALSE) -> 1 | U40: =T40*M40 -> 1 | V40: =N40*M40+(M40*N40*S40) -> 5460 | W40: =VLOOKUP(MONTH(Tabela2[[#This Row],[Data]]),'Auxiliar Compras'!I:J,2,FALSE) -> Dez | X40: =YEAR(Tabela2[[#This Row],[Data]]) -> 2021
A41: 15657315090 | B41: 37 | C41: 44552 | D41: 15506057572 | E41: =VLOOKUP(RANDBETWEEN(1,20),AA:AC,3,FALSE) -> Comprador 02 | F41: 0 | H41: Atendido | I41: 15657228743 | J41: INDS.00.0003 | L41: =VLOOKUP(RANDBETWEEN(1,16),AA:AC,2,FALSE) -> Produto 10 | M41: 1 | N41: 2940 | O41: KG | P41: 0 | Q41: 4538/4833 | R41: =VLOOKUP(L41,'Auxiliar Compras'!A:B,2,FALSE) -> Produto 10 | S41: =VLOOKUP(L41,'Auxiliar Compras'!A:D,4,FALSE) -> 0 | T41: =VLOOKUP(L41,'Auxiliar Compras'!A:C,3,FALSE) -> 1 | U41: =T41*M41 -> 1 | V41: =N41*M41+(M41*N41*S41) -> 2940 | W41: =VLOOKUP(MONTH(Tabela2[[#This Row],[Data]]),'Auxiliar Compras'!I:J,2,FALSE) -> Dez | X41: =YEAR(Tabela2[[#This Row],[Data]]) -> 2021
A42: 15664190124 | B42: 38 | C42: 44553 | D42: 14772821922 | E42: =VLOOKUP(RANDBETWEEN(1,20),AA:AC,3,FALSE) -> Comprador 16 | F42: 0 | H42: Atendido | I42: 14980702561 | J42: ICHP.00.0006 | L42: =VLOOKUP(RANDBETWEEN(1,16),AA:AC,2,FALSE) -> Produto 08 | M42: 15214 | N42: 9.1 | O42: KG | P42: 0 | Q42: 5138 | R42: =VLOOKUP(L42,'Auxiliar Compras'!A:B,2,FALSE) -> Produto 08 | S42: =VLOOKUP(L42,'Auxiliar Compras'!A:D,4,FALSE) -> 0 | T42: =VLOOKUP(L42,'Auxiliar Compras'!A:C,3,FALSE) -> 1 | U42: =T42*M42 -> 15214 | V42: =N42*M42+(M42*N42*S42) -> 138447.4 | W42: =VLOOKUP(MONTH(Tabela2[[#This Row],[Data]]),'Auxiliar Compras'!I:J,2,FALSE) -> Dez | X42: =YEAR(Tabela2[[#This Row],[Data]]) -> 2021
A43: 15765793815 | B43: 39 | C43: 44568 | D43: 15612894064 | E43: =VLOOKUP(RANDBETWEEN(1,20),AA:AC,3,FALSE) -> Comprador 06 | F43: 0 | H43: Atendido | I43: 15505704439 | J43: SRV0.00.0001 | L43: =VLOOKUP(RANDBETWEEN(1,16),AA:AC,2,FALSE) -> Produto 01 | M43: 20402 | N43: 0.25 | O43: KG | P43: 0 | Q43: 005157 / 005192 | R43: =VLOOKUP(L43,'Auxiliar Compras'!A:B,2,FALSE) -> Produto 01 | S43: =VLOOKUP(L43,'Auxiliar Compras'!A:D,4,FALSE) -> 0 | T43: =VLOOKUP(L43,'Auxiliar Compras'!A:C,3,FALSE) -> 1.1 | U43: =T43*M43 -> 22442.2 | V43: =N43*M43+(M43*N43*S43) -> 5100.5 | W43: =VLOOKUP(MONTH(Tabela2[[#This Row],[Data]]),'Auxiliar Compras'!I:J,2,FALSE) -> Jan | X43: =YEAR(Tabela2[[#This Row],[Data]]) -> 2022
A44: 15765833563 | B44: 40 | C44: 44568 | D44: 15615465528 | E44: =VLOOKUP(RANDBETWEEN(1,20),AA:AC,3,FALSE) -> Comprador 08 | F44: 0 | H44: Atendido | I44: 14981306750 | J44: MTUC.00.0003 | L44: =VLOOKUP(RANDBETWEEN(1,16),AA:AC,2,FALSE) -> Produto 12 | M44: 4 | N44: 150 | O44: RL | P44: 0 | Q44: 5191 | R44: =VLOOKUP(L44,'Auxiliar Compras'!A:B,2,FALSE) -> Produto 12 | S44: =VLOOKUP(L44,'Auxiliar Compras'!A:D,4,FALSE) -> 0 | T44: =VLOOKUP(L44,'Auxiliar Compras'!A:C,3,FALSE) -> 1 | U44: =T44*M44 -> 4 | V44: =N44*M44+(M44*N44*S44) -> 600 | W44: =VLOOKUP(MONTH(Tabela2[[#This Row],[Data]]),'Auxiliar Compras'!I:J,2,FALSE) -> Jan | X44: =YEAR(Tabela2[[#This Row],[Data]]) -> 2022
A45: 15767585396 | B45: 41 | C45: 44568 | D45: 15615669447 | E45: =VLOOKUP(RANDBETWEEN(1,20),AA:AC,3,FALSE) -> Comprador 17 | F45: 0 | H45: Atendido | I45: 15515026542 | J45: PMV0.00.0010 | L45: =VLOOKUP(RANDBETWEEN(1,16),AA:AC,2,FALSE) -> Produto 01 | M45: 2 | N45: 335 | O45: UN | P45: 0 | Q45: 5193 | R45: =VLOOKUP(L45,'Auxiliar Compras'!A:B,2,FALSE) -> Produto 01 | S45: =VLOOKUP(L45,'Auxiliar Compras'!A:D,4,FALSE) -> 0 | T45: =VLOOKUP(L45,'Auxiliar Compras'!A:C,3,FALSE) -> 1.1 | U45: =T45*M45 -> 2.2 | V45: =N45*M45+(M45*N45*S45) -> 670 | W45: =VLOOKUP(MONTH(Tabela2[[#This Row],[Data]]),'Auxiliar Compras'!I:J,2,FALSE) -> Jan | X45: =YEAR(Tabela2[[#This Row],[Data]]) -> 2022
A46: 15786585521 | B46: 42 | C46: 44571 | D46: 15478914765 | E46: =VLOOKUP(RANDBETWEEN(1,20),AA:AC,3,FALSE) -> Comprador 18 | F46: 0 | H46: Atendido | I46: 15290493701 | J46: PRFL.00.0030 | L46: =VLOOKUP(RANDBETWEEN(1,16),AA:AC,2,FALSE) -> Produto 01 | M46: 500 | N46: 6.46 | O46: PC | P46: 0 | Q46: 5213 | R46: =VLOOKUP(L46,'Auxiliar Compras'!A:B,2,FALSE) -> Produto 01 | S46: =VLOOKUP(L46,'Auxiliar Compras'!A:D,4,FALSE) -> 0 | T46: =VLOOKUP(L46,'Auxiliar Compras'!A:C,3,FALSE) -> 1.1 | U46: =T46*M46 -> 550 | V46: =N46*M46+(M46*N46*S46) -> 3230 | W46: =VLOOKUP(MONTH(Tabela2[[#This Row],[Data]]),'Auxiliar Compras'!I:J,2,FALSE) -> Jan | X46: =YEAR(Tabela2[[#This Row],[Data]]) -> 2022
A47: 15786585521 | B47: 42 | C47: 44571 | D47: 15478914765 | E47: =VLOOKUP(RANDBETWEEN(1,20),AA:AC,3,FALSE) -> Comprador 05 | F47: 0 | H47: Atendido | I47: 15395751673 | J47: PRFL.00.0039 | L47: =VLOOKUP(RANDBETWEEN(1,16),AA:AC,2,FALSE) -> Produto 11 | M47: 1000 | N47: 7.14 | O47: PC | P47: 0 | Q47: 5213 | R47: =VLOOKUP(L47,'Auxiliar Compras'!A:B,2,FALSE) -> Produto 11 | S47: =VLOOKUP(L47,'Auxiliar Compras'!A:D,4,FALSE) -> 0 | T47: =VLOOKUP(L47,'Auxiliar Compras'!A:C,3,FALSE) -> 1 | U47: =T47*M47 -> 1000 | V47: =N47*M47+(M47*N47*S47) -> 7140 | W47: =VLOOKUP(MONTH(Tabela2[[#This Row],[Data]]),'Auxiliar Compras'!I:J,2,FALSE) -> Jan | X47: =YEAR(Tabela2[[#This Row],[Data]]) -> 2022
A48: 15786665795 | B48: 43 | C48: 44571 | D48: 14979221560 | E48: =VLOOKUP(RANDBETWEEN(1,20),AA:AC,3,FALSE) -> Comprador 13 | F48: 0 | H48: Atendido | I48: 14979354095 | J48: INDS.00.0001 | K48: 50790031 | L48: =VLOOKUP(RANDBETWEEN(1,16),AA:AC,2,FALSE) -> Produto 03 | M48: 15214 | N48: 0.18 | O48: TO | P48: 0 | Q48: 5215 | R48: =VLOOKUP(L48,'Auxiliar Compras'!A:B,2,FALSE) -> Produto 03 | S48: =VLOOKUP(L48,'Auxiliar Compras'!A:D,4,FALSE) -> 0.05 | T48: =VLOOKUP(L48,'Auxiliar Compras'!A:C,3,FALSE) -> 1 | U48: =T48*M48 -> 15214 | V48: =N48*M48+(M48*N48*S48) -> 2875.446 | W48: =VLOOKUP(MONTH(Tabela2[[#This Row],[Data]]),'Auxiliar Compras'!I:J,2,FALSE) -> Jan | X48: =YEAR(Tabela2[[#This Row],[Data]]) -> 2022
A49: 15804839090 | B49: 44 | C49: 44573 | D49: 15139603329 | E49: =VLOOKUP(RANDBETWEEN(1,20),AA:AC,3,FALSE) -> Comprador 05 | F49: 0 | H49: Atendido | I49: 15016073255 | J49: PRFL.00.0023 | L49: =VLOOKUP(RANDBETWEEN(1,16),AA:AC,2,FALSE) -> Produto 01 | M49: 6720 | N49: 13.9 | O49: PC | P49: 0 | Q49: 5225 | R49: =VLOOKUP(L49,'Auxiliar Compras'!A:B,2,FALSE) -> Produto 01 | S49: =VLOOKUP(L49,'Auxiliar Compras'!A:D,4,FALSE) -> 0 | T49: =VLOOKUP(L49,'Auxiliar Compras'!A:C,3,FALSE) -> 1.1 | U49: =T49*M49 -> 7392 | V49: =N49*M49+(M49*N49*S49) -> 93408 | W49: =VLOOKUP(MONTH(Tabela2[[#This Row],[Data]]),'Auxiliar Compras'!I:J,2,FALSE) -> Jan | X49: =YEAR(Tabela2[[#This Row],[Data]]) -> 2022
A50: 15804839090 | B50: 44 | C50: 44573 | D50: 15139603329 | E50: =VLOOKUP(RANDBETWEEN(1,20),AA:AC,3,FALSE) -> Comprador 01 | F50: 0 | H50: Atendido | I50: 15016093155 | J50: PRFL.00.0026 | L50: =VLOOKUP(RANDBETWEEN(1,16),AA:AC,2,FALSE) -> Produto 14 | M50: 350 | N50: 21.1 | O50: PC | P50: 0 | Q50: 5225 | R50: =VLOOKUP(L50,'Auxiliar Compras'!A:B,2,FALSE) -> Produto 14 | S50: =VLOOKUP(L50,'Auxiliar Compras'!A:D,4,FALSE) -> 0 | T50: =VLOOKUP(L50,'Auxiliar Compras'!A:C,3,FALSE) -> 1.68 | U50: =T50*M50 -> 588 | V50: =N50*M50+(M50*N50*S50) -> 7385 | W50: =VLOOKUP(MONTH(Tabela2[[#This Row],[Data]]),'Auxiliar Compras'!I:J,2,FALSE) -> Jan | X50: =YEAR(Tabela2[[#This Row],[Data]]) -> 2022
A51: 15804839090 | B51: 44 | C51: 44573 | D51: 15139603329 | E51: =VLOOKUP(RANDBETWEEN(1,20),AA:AC,3,FALSE) -> Comprador 18 | F51: 0 | H51: Atendido | I51: 15139667431 | J51: PRFL.00.0028 | L51: =VLOOKUP(RANDBETWEEN(1,16),AA:AC,2,FALSE) -> Produto 10 | M51: 300 | N51: 23.5 | O51: PC | P51: 0 | Q51: 5225 | R51: =VLOOKUP(L51,'Auxiliar Compras'!A:B,2,FALSE) -> Produto 10 | S51: =VLOOKUP(L51,'Auxiliar Compras'!A:D,4,FALSE) -> 0 | T51: =VLOOKUP(L51,'Auxiliar Compras'!A:C,3,FALSE) -> 1 | U51: =T51*M51 -> 300 | V51: =N51*M51+(M51*N51*S51) -> 7050 | W51: =VLOOKUP(MONTH(Tabela2[[#This Row],[Data]]),'Auxiliar Compras'!I:J,2,FALSE) -> Jan | X51: =YEAR(Tabela2[[#This Row],[Data]]) -> 2022
A52: 15824177907 | B52: 45 | C52: 44575 | D52: 15139603329 | E52: =VLOOKUP(RANDBETWEEN(1,20),AA:AC,3,FALSE) -> Comprador 09 | F52: 0 | H52: Atendido | I52: 15016073255 | J52: PRFL.00.0023 | L52: =VLOOKUP(RANDBETWEEN(1,16),AA:AC,2,FALSE) -> Produto 03 | M52: 840 | N52: 14.2 | O52: PC | P52: 0 | Q52: 4594 | R52: =VLOOKUP(L52,'Auxiliar Compras'!A:B,2,FALSE) -> Produto 03 | S52: =VLOOKUP(L52,'Auxiliar Compras'!A:D,4,FALSE) -> 0.05 | T52: =VLOOKUP(L52,'Auxiliar Compras'!A:C,3,FALSE) -> 1 | U52: =T52*M52 -> 840 | V52: =N52*M52+(M52*N52*S52) -> 12524.4 | W52: =VLOOKUP(MONTH(Tabela2[[#This Row],[Data]]),'Auxiliar Compras'!I:J,2,FALSE) -> Jan | X52: =YEAR(Tabela2[[#This Row],[Data]]) -> 2022
A53: 15824177907 | B53: 45 | C53: 44575 | D53: 15139603329 | E53: =VLOOKUP(RANDBETWEEN(1,20),AA:AC,3,FALSE) -> Comprador 19 | F53: 0 | H53: Atendido | I53: 15016093155 | J53: PRFL.00.0026 | L53: =VLOOKUP(RANDBETWEEN(1,16),AA:AC,2,FALSE) -> Produto 01 | M53: 1200 | N53: 22.25 | O53: PC | P53: 0 | Q53: 4594 | R53: =VLOOKUP(L53,'Auxiliar Compras'!A:B,2,FALSE) -> Produto 01 | S53: =VLOOKUP(L53,'Auxiliar Compras'!A:D,4,FALSE) -> 0 | T53: =VLOOKUP(L53,'Auxiliar Compras'!A:C,3,FALSE) -> 1.1 | U53: =T53*M53 -> 1320 | V53: =N53*M53+(M53*N53*S53) -> 26700 | W53: =VLOOKUP(MONTH(Tabela2[[#This Row],[Data]]),'Auxiliar Compras'!I:J,2,FALSE) -> Jan | X53: =YEAR(Tabela2[[#This Row],[Data]]) -> 2022
A54: 15824177907 | B54: 45 | C54: 44575 | D54: 15139603329 | E54: =VLOOKUP(RANDBETWEEN(1,20),AA:AC,3,FALSE) -> Comprador 05 | F54: 0 | H54: Atendido | I54: 15139667431 | J54: PRFL.00.0028 | L54: =VLOOKUP(RANDBETWEEN(1,16),AA:AC,2,FALSE) -> Produto 05 | M54: 1400 | N54: 19.85 | O54: PC | P54: 0 | Q54: 4594 | R54: =VLOOKUP(L54,'Auxiliar Compras'!A:B,2,FALSE) -> Produto 05 | S54: =VLOOKUP(L54,'Auxiliar Compras'!A:D,4,FALSE) -> 0 | T54: =VLOOKUP(L54,'Auxiliar Compras'!A:C,3,FALSE) -> 1.42 | U54: =T54*M54 -> 1988 | V54: =N54*M54+(M54*N54*S54) -> 27790 | W54: =VLOOKUP(MONTH(Tabela2[[#This Row],[Data]]),'Auxiliar Compras'!I:J,2,FALSE) -> Jan | X54: =YEAR(Tabela2[[#This Row],[Data]]) -> 2022
A55: 15824177907 | B55: 45 | C55: 44575 | D55: 15139603329 | E55: =VLOOKUP(RANDBETWEEN(1,20),AA:AC,3,FALSE) -> Comprador 18 | F55: 0 | H55: Atendido | I55: 15016066088 | J55: PRFL.00.0022 | L55: =VLOOKUP(RANDBETWEEN(1,16),AA:AC,2,FALSE) -> Produto 12 | M55: 840 | N55: 13 | O55: PC | P55: 0 | Q55: 4594 | R55: =VLOOKUP(L55,'Auxiliar Compras'!A:B,2,FALSE) -> Produto 12 | S55: =VLOOKUP(L55,'Auxiliar Compras'!A:D,4,FALSE) -> 0 | T55: =VLOOKUP(L55,'Auxiliar Compras'!A:C,3,FALSE) -> 1 | U55: =T55*M55 -> 840 | V55: =N55*M55+(M55*N55*S55) -> 10920 | W55: =VLOOKUP(MONTH(Tabela2[[#This Row],[Data]]),'Auxiliar Compras'!I:J,2,FALSE) -> Jan | X55: =YEAR(Tabela2[[#This Row],[Data]]) -> 2022
A56: 15824237214 | B56: 46 | C56: 44575 | D56: 15139603329 | E56: =VLOOKUP(RANDBETWEEN(1,20),AA:AC,3,FALSE) -> Comprador 16 | F56: 0 | H56: Atendido | I56: 15016073255 | J56: PRFL.00.0023 | L56: =VLOOKUP(RANDBETWEEN(1,16),AA:AC,2,FALSE) -> Produto 08 | M56: 2520 | N56: 14.2 | O56: PC | P56: 0 | Q56: 4741 | R56: =VLOOKUP(L56,'Auxiliar Compras'!A:B,2,FALSE) -> Produto 08 | S56: =VLOOKUP(L56,'Auxiliar Compras'!A:D,4,FALSE) -> 0 | T56: =VLOOKUP(L56,'Auxiliar Compras'!A:C,3,FALSE) -> 1 | U56: =T56*M56 -> 2520 | V56: =N56*M56+(M56*N56*S56) -> 35784 | W56: =VLOOKUP(MONTH(Tabela2[[#This Row],[Data]]),'Auxiliar Compras'!I:J,2,FALSE) -> Jan | X56: =YEAR(Tabela2[[#This Row],[Data]]) -> 2022
A57: 15824299611 | B57: 47 | C57: 44575 | D57: 14772879804 | E57: =VLOOKUP(RANDBETWEEN(1,20),AA:AC,3,FALSE) -> Comprador 05 | F57: 0 | H57: Atendido | I57: 14981313809 | J57: ICHP.00.0001 | L57: =VLOOKUP(RANDBETWEEN(1,16),AA:AC,2,FALSE) -> Produto 06 | M57: 2349 | N57: 10.5 | O57: KG | P57: 0 | Q57: 4317 | R57: =VLOOKUP(L57,'Auxiliar Compras'!A:B,2,FALSE) -> Produto 06 | S57: =VLOOKUP(L57,'Auxiliar Compras'!A:D,4,FALSE) -> 0 | T57: =VLOOKUP(L57,'Auxiliar Compras'!A:C,3,FALSE) -> 1.1 | U57: =T57*M57 -> 2583.9 | V57: =N57*M57+(M57*N57*S57) -> 24664.5 | W57: =VLOOKUP(MONTH(Tabela2[[#This Row],[Data]]),'Auxiliar Compras'!I:J,2,FALSE) -> Jan | X57: =YEAR(Tabela2[[#This Row],[Data]]) -> 2022
A58: 15824299611 | B58: 47 | C58: 44575 | D58: 14772879804 | E58: =VLOOKUP(RANDBETWEEN(1,20),AA:AC,3,FALSE) -> Comprador 10 | F58: 0 | H58: Atendido | I58: 14981313809 | J58: ICHP.00.0001 | L58: =VLOOKUP(RANDBETWEEN(1,16),AA:AC,2,FALSE) -> Produto 16 | M58: 6270 | N58: 10.6 | O58: KG | P58: 0 | Q58: 4317 | R58: =VLOOKUP(L58,'Auxiliar Compras'!A:B,2,FALSE) -> Produto 16 | S58: =VLOOKUP(L58,'Auxiliar Compras'!A:D,4,FALSE) -> 0.05 | T58: =VLOOKUP(L58,'Auxiliar Compras'!A:C,3,FALSE) -> 1 | U58: =T58*M58 -> 6270 | V58: =N58*M58+(M58*N58*S58) -> 69785.1 | W58: =VLOOKUP(MONTH(Tabela2[[#This Row],[Data]]),'Auxiliar Compras'!I:J,2,FALSE) -> Jan | X58: =YEAR(Tabela2[[#This Row],[Data]]) -> 2022
A59: 15824311715 | B59: 48 | C59: 44575 | D59: 14981313759 | E59: =VLOOKUP(RANDBETWEEN(1,20),AA:AC,3,FALSE) -> Comprador 03 | F59: 0 | H59: Atendido | I59: 14981313809 | J59: ICHP.00.0001 | K59: 1277 | L59: =VLOOKUP(RANDBETWEEN(1,16),AA:AC,2,FALSE) -> Produto 16 | M59: 7732 | N59: 9.35 | O59: KG | P59: 0 | Q59: 4397 | R59: =VLOOKUP(L59,'Auxiliar Compras'!A:B,2,FALSE) -> Produto 16 | S59: =VLOOKUP(L59,'Auxiliar Compras'!A:D,4,FALSE) -> 0.05 | T59: =VLOOKUP(L59,'Auxiliar Compras'!A:C,3,FALSE) -> 1 | U59: =T59*M59 -> 7732 | V59: =N59*M59+(M59*N59*S59) -> 75908.91 | W59: =VLOOKUP(MONTH(Tabela2[[#This Row],[Data]]),'Auxiliar Compras'!I:J,2,FALSE) -> Jan | X59: =YEAR(Tabela2[[#This Row],[Data]]) -> 2022
A60: 15824338077 | B60: 49 | C60: 44575 | D60: 14981313759 | E60: =VLOOKUP(RANDBETWEEN(1,20),AA:AC,3,FALSE) -> Comprador 20 | F60: 0 | H60: Atendido | I60: 14980996381 | J60: ICHP.00.0005 | L60: =VLOOKUP(RANDBETWEEN(1,16),AA:AC,2,FALSE) -> Produto 12 | M60: 8378 | N60: 8.99 | O60: KG | P60: 0 | Q60: 4540 | R60: =VLOOKUP(L60,'Auxiliar Compras'!A:B,2,FALSE) -> Produto 12 | S60: =VLOOKUP(L60,'Auxiliar Compras'!A:D,4,FALSE) -> 0 | T60: =VLOOKUP(L60,'Auxiliar Compras'!A:C,3,FALSE) -> 1 | U60: =T60*M60 -> 8378 | V60: =N60*M60+(M60*N60*S60) -> 75318.22 | W60: =VLOOKUP(MONTH(Tabela2[[#This Row],[Data]]),'Auxiliar Compras'!I:J,2,FALSE) -> Jan | X60: =YEAR(Tabela2[[#This Row],[Data]]) -> 2022
A61: 15824466620 | B61: 50 | C61: 44575 | D61: 15622257299 | E61: =VLOOKUP(RANDBETWEEN(1,20),AA:AC,3,FALSE) -> Comprador 06 | F61: 0 | H61: Atendido | I61: 14981313809 | J61: ICHP.00.0001 | L61: =VLOOKUP(RANDBETWEEN(1,16),AA:AC,2,FALSE) -> Produto 16 | M61: 4210 | N61: 9.2 | O61: KG | P61: 0 | Q61: 4814 | R61: =VLOOKUP(L61,'Auxiliar Compras'!A:B,2,FALSE) -> Produto 16 | S61: =VLOOKUP(L61,'Auxiliar Compras'!A:D,4,FALSE) -> 0.05 | T61: =VLOOKUP(L61,'Auxiliar Compras'!A:C,3,FALSE) -> 1 | U61: =T61*M61 -> 4210 | V61: =N61*M61+(M61*N61*S61) -> 40668.6 | W61: =VLOOKUP(MONTH(Tabela2[[#This Row],[Data]]),'Auxiliar Compras'!I:J,2,FALSE) -> Jan | X61: =YEAR(Tabela2[[#This Row],[Data]]) -> 2022
B62: 51 | C62: 44698 | E62: =VLOOKUP(RANDBETWEEN(1,20),AA:AC,3,FALSE) -> Comprador 16 | L62: =VLOOKUP(RANDBETWEEN(1,16),AA:AC,2,FALSE) -> Produto 03 | M62: 6071 | N62: 16 | O62: PC | R62: =VLOOKUP(L62,'Auxiliar Compras'!A:B,2,FALSE) -> Produto 03 | S62: =VLOOKUP(L62,'Auxiliar Compras'!A:D,4,FALSE) -> 0.05 | T62: =VLOOKUP(L62,'Auxiliar Compras'!A:C,3,FALSE) -> 1 | U62: =T62*M62 -> 6071 | V62: =N62*M62+(M62*N62*S62) -> 101992.8 | W62: =VLOOKUP(MONTH(Tabela2[[#This Row],[Data]]),'Auxiliar Compras'!I:J,2,FALSE) -> Mai | X62: =YEAR(Tabela2[[#This Row],[Data]]) -> 2022
B63: 52 | C63: 44582 | E63: =VLOOKUP(RANDBETWEEN(1,20),AA:AC,3,FALSE) -> Comprador 12 | L63: =VLOOKUP(RANDBETWEEN(1,16),AA:AC,2,FALSE) -> Produto 10 | M63: 6150 | N63: 23 | O63: PC | R63: =VLOOKUP(L63,'Auxiliar Compras'!A:B,2,FALSE) -> Produto 10 | S63: =VLOOKUP(L63,'Auxiliar Compras'!A:D,4,FALSE) -> 0 | T63: =VLOOKUP(L63,'Auxiliar Compras'!A:C,3,FALSE) -> 1 | U63: =T63*M63 -> 6150 | V63: =N63*M63+(M63*N63*S63) -> 141450 | W63: =VLOOKUP(MONTH(Tabela2[[#This Row],[Data]]),'Auxiliar Compras'!I:J,2,FALSE) -> Jan | X63: =YEAR(Tabela2[[#This Row],[Data]]) -> 2022
B64: 53 | C64: 44661 | E64: =VLOOKUP(RANDBETWEEN(1,20),AA:AC,3,FALSE) -> Comprador 01 | L64: =VLOOKUP(RANDBETWEEN(1,16),AA:AC,2,FALSE) -> Produto 04 | M64: 4159 | N64: 17 | O64: PC | R64: =VLOOKUP(L64,'Auxiliar Compras'!A:B,2,FALSE) -> Produto 04 | S64: =VLOOKUP(L64,'Auxiliar Compras'!A:D,4,FALSE) -> 0 | T64: =VLOOKUP(L64,'Auxiliar Compras'!A:C,3,FALSE) -> 1.1 | U64: =T64*M64 -> 4574.9 | V64: =N64*M64+(M64*N64*S64) -> 70703 | W64: =VLOOKUP(MONTH(Tabela2[[#This Row],[Data]]),'Auxiliar Compras'!I:J,2,FALSE) -> Abr | X64: =YEAR(Tabela2[[#This Row],[Data]]) -> 2022
B65: 54 | C65: 44646 | E65: =VLOOKUP(RANDBETWEEN(1,20),AA:AC,3,FALSE) -> Comprador 02 | L65: =VLOOKUP(RANDBETWEEN(1,16),AA:AC,2,FALSE) -> Produto 09 | M65: 1772 | N65: 22 | O65: PC | R65: =VLOOKUP(L65,'Auxiliar Compras'!A:B,2,FALSE) -> Produto 09 | S65: =VLOOKUP(L65,'Auxiliar Compras'!A:D,4,FALSE) -> 0 | T65: =VLOOKUP(L65,'Auxiliar Compras'!A:C,3,FALSE) -> 1 | U65: =T65*M65 -> 1772 | V65: =N65*M65+(M65*N65*S65) -> 38984 | W65: =VLOOKUP(MONTH(Tabela2[[#This Row],[Data]]),'Auxiliar Compras'!I:J,2,FALSE) -> Mar | X65: =YEAR(Tabela2[[#This Row],[Data]]) -> 2022
B66: 55 | C66: 44589 | E66: =VLOOKUP(RANDBETWEEN(1,20),AA:AC,3,FALSE) -> Comprador 01 | L66: =VLOOKUP(RANDBETWEEN(1,16),AA:AC,2,FALSE) -> Produto 06 | M66: 1568 | N66: 20 | O66: PC | R66: =VLOOKUP(L66,'Auxiliar Compras'!A:B,2,FALSE) -> Produto 06 | S66: =VLOOKUP(L66,'Auxiliar Compras'!A:D,4,FALSE) -> 0 | T66: =VLOOKUP(L66,'Auxiliar Compras'!A:C,3,FALSE) -> 1.1 | U66: =T66*M66 -> 1724.8 | V66: =N66*M66+(M66*N66*S66) -> 31360 | W66: =VLOOKUP(MONTH(Tabela2[[#This Row],[Data]]),'Auxiliar Compras'!I:J,2,FALSE) -> Jan | X66: =YEAR(Tabela2[[#This Row],[Data]]) -> 2022
B67: 56 | C67: 44594 | E67: =VLOOKUP(RANDBETWEEN(1,20),AA:AC,3,FALSE) -> Comprador 02 | L67: =VLOOKUP(RANDBETWEEN(1,16),AA:AC,2,FALSE) -> Produto 04 | M67: 4265 | N67: 12 | O67: PC | R67: =VLOOKUP(L67,'Auxiliar Compras'!A:B,2,FALSE) -> Produto 04 | S67: =VLOOKUP(L67,'Auxiliar Compras'!A:D,4,FALSE) -> 0 | T67: =VLOOKUP(L67,'Auxiliar Compras'!A:C,3,FALSE) -> 1.1 | U67: =T67*M67 -> 4691.5 | V67: =N67*M67+(M67*N67*S67) -> 51180 | W67: =VLOOKUP(MONTH(Tabela2[[#This Row],[Data]]),'Auxiliar Compras'!I:J,2,FALSE) -> Fev | X67: =YEAR(Tabela2[[#This Row],[Data]]) -> 2022
B68: 57 | C68: 44704 | E68: =VLOOKUP(RANDBETWEEN(1,20),AA:AC,3,FALSE) -> Comprador 05 | L68: =VLOOKUP(RANDBETWEEN(1,16),AA:AC,2,FALSE) -> Produto 05 | M68: 5280 | N68: 18 | O68: PC | R68: =VLOOKUP(L68,'Auxiliar Compras'!A:B,2,FALSE) -> Produto 05 | S68: =VLOOKUP(L68,'Auxiliar Compras'!A:D,4,FALSE) -> 0 | T68: =VLOOKUP(L68,'Auxiliar Compras'!A:C,3,FALSE) -> 1.42 | U68: =T68*M68 -> 7497.6 | V68: =N68*M68+(M68*N68*S68) -> 95040 | W68: =VLOOKUP(MONTH(Tabela2[[#This Row],[Data]]),'Auxiliar Compras'!I:J,2,FALSE) -> Mai | X68: =YEAR(Tabela2[[#This Row],[Data]]) -> 2022
B69: 58 | C69: 44654 | E69: =VLOOKUP(RANDBETWEEN(1,20),AA:AC,3,FALSE) -> Comprador 03 | L69: =VLOOKUP(RANDBETWEEN(1,16),AA:AC,2,FALSE) -> Produto 07 | M69: 5367 | N69: 16 | O69: PC | R69: =VLOOKUP(L69,'Auxiliar Compras'!A:B,2,FALSE) -> Produto 07 | S69: =VLOOKUP(L69,'Auxiliar Compras'!A:D,4,FALSE) -> 0 | T69: =VLOOKUP(L69,'Auxiliar Compras'!A:C,3,FALSE) -> 0.5 | U69: =T69*M69 -> 2683.5 | V69: =N69*M69+(M69*N69*S69) -> 85872 | W69: =VLOOKUP(MONTH(Tabela2[[#This Row],[Data]]),'Auxiliar Compras'!I:J,2,FALSE) -> Abr | X69: =YEAR(Tabela2[[#This Row],[Data]]) -> 2022
B70: 59 | C70: 44648 | E70: =VLOOKUP(RANDBETWEEN(1,20),AA:AC,3,FALSE) -> Comprador 07 | L70: =VLOOKUP(RANDBETWEEN(1,16),AA:AC,2,FALSE) -> Produto 16 | M70: 1706 | N70: 14 | O70: KG | R70: =VLOOKUP(L70,'Auxiliar Compras'!A:B,2,FALSE) -> Produto 16 | S70: =VLOOKUP(L70,'Auxiliar Compras'!A:D,4,FALSE) -> 0.05 | T70: =VLOOKUP(L70,'Auxiliar Compras'!A:C,3,FALSE) -> 1 | U70: =T70*M70 -> 1706 | V70: =N70*M70+(M70*N70*S70) -> 25078.2 | W70: =VLOOKUP(MONTH(Tabela2[[#This Row],[Data]]),'Auxiliar Compras'!I:J,2,FALSE) -> Mar | X70: =YEAR(Tabela2[[#This Row],[Data]]) -> 2022
B71: 60 | C71: 44630 | E71: =VLOOKUP(RANDBETWEEN(1,20),AA:AC,3,FALSE) -> Comprador 13 | L71: =VLOOKUP(RANDBETWEEN(1,16),AA:AC,2,FALSE) -> Produto 01 | M71: 2645 | N71: 3 | O71: KG | R71: =VLOOKUP(L71,'Auxiliar Compras'!A:B,2,FALSE) -> Produto 01 | S71: =VLOOKUP(L71,'Auxiliar Compras'!A:D,4,FALSE) -> 0 | T71: =VLOOKUP(L71,'Auxiliar Compras'!A:C,3,FALSE) -> 1.1 | U71: =T71*M71 -> 2909.5 | V71: =N71*M71+(M71*N71*S71) -> 7935 | W71: =VLOOKUP(MONTH(Tabela2[[#This Row],[Data]]),'Auxiliar Compras'!I:J,2,FALSE) -> Mar | X71: =YEAR(Tabela2[[#This Row],[Data]]) -> 2022
B72: 61 | C72: 44709 | E72: =VLOOKUP(RANDBETWEEN(1,20),AA:AC,3,FALSE) -> Comprador 02 | L72: =VLOOKUP(RANDBETWEEN(1,16),AA:AC,2,FALSE) -> Produto 02 | M72: 2032 | N72: 3 | O72: KG | R72: =VLOOKUP(L72,'Auxiliar Compras'!A:B,2,FALSE) -> Produto 02 | S72: =VLOOKUP(L72,'Auxiliar Compras'!A:D,4,FALSE) -> 0.05 | T72: =VLOOKUP(L72,'Auxiliar Compras'!A:C,3,FALSE) -> 1 | U72: =T72*M72 -> 2032 | V72: =N72*M72+(M72*N72*S72) -> 6400.8 | W72: =VLOOKUP(MONTH(Tabela2[[#This Row],[Data]]),'Auxiliar Compras'!I:J,2,FALSE) -> Mai | X72: =YEAR(Tabela2[[#This Row],[Data]]) -> 2022
B73: 62 | C73: 44605 | E73: =VLOOKUP(RANDBETWEEN(1,20),AA:AC,3,FALSE) -> Comprador 01 | L73: =VLOOKUP(RANDBETWEEN(1,16),AA:AC,2,FALSE) -> Produto 05 | M73: 5849 | N73: 3 | O73: KG | R73: =VLOOKUP(L73,'Auxiliar Compras'!A:B,2,FALSE) -> Produto 05 | S73: =VLOOKUP(L73,'Auxiliar Compras'!A:D,4,FALSE) -> 0 | T73: =VLOOKUP(L73,'Auxiliar Compras'!A:C,3,FALSE) -> 1.42 | U73: =T73*M73 -> 8305.58 | V73: =N73*M73+(M73*N73*S73) -> 17547 | W73: =VLOOKUP(MONTH(Tabela2[[#This Row],[Data]]),'Auxiliar Compras'!I:J,2,FALSE) -> Fev | X73: =YEAR(Tabela2[[#This Row],[Data]]) -> 2022
... B161: 150 | C161: 44644 | E161: =VLOOKUP(RANDBETWEEN(1,20),AA:AC,3,FALSE) -> Comprador 05 | L161: =VLOOKUP(RANDBETWEEN(1,16),AA:AC,2,FALSE) -> Produto 04 | M161: 2049 | N161: 23 | O161: KG | R161: =VLOOKUP(L161,'Auxiliar Compras'!A:B,2,FALSE) -> Produto 04 | S161: =VLOOKUP(L161,'Auxiliar Compras'!A:D,4,FALSE) -> 0 | T161: =VLOOKUP(L161,'Auxiliar Compras'!A:C,3,FALSE) -> 1.1 | U161: =T161*M161 -> 2253.9 | V161: =N161*M161+(M161*N161*S161) -> 47127 | W161: =VLOOKUP(MONTH(Tabela2[[#This Row],[Data]]),'Auxiliar Compras'!I:J,2,FALSE) -> Mar | X161: =YEAR(Tabela2[[#This Row],[Data]]) -> 2022

Sheet Com. Vlr
A1: Valor comprado | B1: =GETPIVOTDATA("Vlr Total",$A$4) -> 427425.22 | E1: Peso total | F1: =GETPIVOTDATA("Peso Total",$E$4) -> 33788.7
A4: Rótulos de Linha | B4: Soma de Vlr Total | E4: Rótulos de Linha | F4: Soma de Peso Total | I4: Rótulos de Linha | J4: Soma de Vlr Total
A5: Produto 04 | B5: 427425.22 | E5: Produto 04 | F5: 33788.7 | I5: Produto 01 | J5: 780968.2
A6: Total Geral | B6: 427425.22 | E6: Total Geral | F6: 33788.7 | I6: Produto 02 | J6: 59649.45
I7: Produto 03 | J7: 582498.78
I8: Produto 04 | J8: 744641.32
I9: Produto 05 | J9: 549704.46
I10: Produto 06 | J10: 191987
I11: Produto 07 | J11: 62057.74
I12: Produto 08 | J12: 521299
I13: Produto 09 | J13: 270451.4
I14: Produto 10 | J14: 1029292.9
I15: Produto 11 | J15: 658144.22
I16: Produto 12 | J16: 517721.27
I17: Produto 13 | J17: 613096.6
I18: Produto 14 | J18: 500522
... I21: Total Geral | J21: 7730425

Sheet Top 10 Compras
A3: Rótulos de Linha | B3: Soma de Vlr Total
A4: Produto 16 | B4: 55816.95
A5: Produto 15 | B5: 152383
A6: Produto 14 | B6: 261236
A7: Produto 13 | B7: 409360.2
A8: Produto 12 | B8: 317051
A9: Produto 11 | B9: 644127.5
A10: Produto 10 | B10: 206717
A11: Produto 09 | B11: 126544
A12: Produto 08 | B12: 467281
A13: Produto 07 | B13: 60525.52
A14: Produto 06 | B14: 189047
A15: Produto 05 | B15: 135423
... A20: Total Geral | B20: 4141867.8

Sheet Com. Mes
A3: Rótulos de Linha | B3: Soma de Vlr Total | D3: Rótulos de Linha | E3: Soma de Peso Total
A4: Jan | B4: 254602.22 | D4: Jan | E4: 21203.6
A5: Fev | B5: 133308 | D5: Fev | E5: 6375.6
A6: Mar | B6: 39515 | D6: Mar | E6: 6209.5
A7: Total Geral | B7: 427425.22 | D7: Total Geral | E7: 33788.7

Sheet Auxiliar Compras
A1: Descrição | B1: Descrição Resumida | C1: Peso | D1: Imposto | I1: 1 | J1: Jan
A2: Produto 01 | B2: Produto 01 | C2: 1.1 | D2: 0 | I2: 2 | J2: Fev
A3: Produto 02 | B3: Produto 02 | C3: 1 | D3: 0.05 | I3: 3 | J3: Mar
A4: Produto 03 | B4: Produto 03 | C4: 1 | D4: 0.05 | I4: 4 | J4: Abr
A5: Produto 04 | B5: Produto 04 | C5: 1.1 | D5: 0 | I5: 5 | J5: Mai
A6: Produto 05 | B6: Produto 05 | C6: 1.42 | D6: 0 | I6: 6 | J6: Jun
A7: Produto 06 | B7: Produto 06 | C7: 1.1 | D7: 0 | I7: 7 | J7: Jul
A8: Produto 07 | B8: Produto 07 | C8: 0.5 | D8: 0 | I8: 8 | J8: Ago
A9: Produto 08 | B9: Produto 08 | C9: 1 | D9: 0 | I9: 9 | J9: Set
A10: Produto 09 | B10: Produto 09 | C10: 1 | D10: 0 | I10: 10 | J10: Out
A11: Produto 10 | B11: Produto 10 | C11: 1 | D11: 0 | I11: 11 | J11: Nov
A12: Produto 11 | B12: Produto 11 | C12: 1 | D12: 0 | I12: 12 | J12: Dez
A13: Produto 12 | B13: Produto 12 | C13: 1 | D13: 0
A14: Produto 13 | B14: Produto 13 | C14: 0.4 | D14: 0
A15: Produto 14 | B15: Produto 14 | C15: 1.68 | D15: 0
A16: Produto 15 | B16: Produto 15 | C16: 1.1 | D16: 0
A17: Produto 16 | B17: Produto 16 | C17: 1 | D17: 0.05

Sheet A pagar Semanal
A1: FORNECEDOR | B1: VENCIMENTOS | C1: VALOR | D1: SEMANA | E1: SOMA DA SEMANA | G1: Valor a pagar | H1: =GETPIVOTDATA("VALOR",$G$3) -> 9075
A2: =VLOOKUP(RANDBETWEEN(1,5),$G$21:$H$25,2,0) -> Fornecedor 2 | B2: 44569 | C2: 5911 | D2: 1
A3: =VLOOKUP(RANDBETWEEN(1,5),$G$21:$H$25,2,0) -> Fornecedor 1 | B3: 44570 | C3: 1972 | D3: 1 | G3: Soma de VALOR | H3: Rótulos de Coluna
A4: =VLOOKUP(RANDBETWEEN(1,5),$G$21:$H$25,2,0) -> Fornecedor 2 | B4: 44570 | C4: 1192 | D4: 1 | G4: Rótulos de Linha | H4: 1 | I4: Total Geral
A5: =VLOOKUP(RANDBETWEEN(1,5),$G$21:$H$25,2,0) -> Fornecedor 3 | B5: 44571 | C5: 4187 | D5: 2 | G5: Fornecedor 4 | H5: 1972 | I5: 1972
A6: =VLOOKUP(RANDBETWEEN(1,5),$G$21:$H$25,2,0) -> Fornecedor 5 | B6: 44571 | C6: 4187 | D6: 2 | G6: Fornecedor 2 | H6: 7103 | I6: 7103
A7: =VLOOKUP(RANDBETWEEN(1,5),$G$21:$H$25,2,0) -> Fornecedor 3 | B7: 44573 | C7: 1192 | D7: 2 | G7: Total Geral | H7: 9075 | I7: 9075
A8: =VLOOKUP(RANDBETWEEN(1,5),$G$21:$H$25,2,0) -> Fornecedor 4 | B8: 44575 | C8: 1365 | D8: 2
A9: =VLOOKUP(RANDBETWEEN(1,5),$G$21:$H$25,2,0) -> Fornecedor 5 | B9: 44574 | C9: 5256 | D9: 2
A10: =VLOOKUP(RANDBETWEEN(1,5),$G$21:$H$25,2,0) -> Fornecedor 1 | B10: 44578 | C10: 2547 | D10: 3
A11: =VLOOKUP(RANDBETWEEN(1,5),$G$21:$H$25,2,0) -> Fornecedor 5 | B11: 44578 | C11: 2530 | D11: 3
A12: =VLOOKUP(RANDBETWEEN(1,5),$G$21:$H$25,2,0) -> Fornecedor 2 | B12: 44578 | C12: 1167 | D12: 3
A13: =VLOOKUP(RANDBETWEEN(1,5),$G$21:$H$25,2,0) -> Fornecedor 1 | B13: 44580 | C13: 4927 | D13: 3
A14: =VLOOKUP(RANDBETWEEN(1,5),$G$21:$H$25,2,0) -> Fornecedor 2 | B14: 44580 | C14: 7789 | D14: 3
A15: =VLOOKUP(RANDBETWEEN(1,5),$G$21:$H$25,2,0) -> Fornecedor 1 | B15: 44582 | C15: 4085 | D15: 3
A16: =VLOOKUP(RANDBETWEEN(1,5),$G$21:$H$25,2,0) -> Fornecedor 2 | B16: 44582 | C16: 4153 | D16: 3
A17: =VLOOKUP(RANDBETWEEN(1,5),$G$21:$H$25,2,0) -> Fornecedor 2 | B17: 44582 | C17: 3618 | D17: 3
A18: =VLOOKUP(RANDBETWEEN(1,5),$G$21:$H$25,2,0) -> Fornecedor 1 | B18: 44584 | C18: 5911 | D18: 3
A19: =VLOOKUP(RANDBETWEEN(1,5),$G$21:$H$25,2,0) -> Fornecedor 1 | B19: 44585 | C19: 1972 | D19: 4
A20: =VLOOKUP(RANDBETWEEN(1,5),$G$21:$H$25,2,0) -> Fornecedor 2 | B20: 44587 | C20: 4927 | D20: 4
A21: =VLOOKUP(RANDBETWEEN(1,5),$G$21:$H$25,2,0) -> Fornecedor 4 | B21: 44590 | C21: 1365 | D21: 4 | G21: 1 | H21: Fornecedor 1
A22: =VLOOKUP(RANDBETWEEN(1,5),$G$21:$H$25,2,0) -> Fornecedor 4 | B22: 44590 | C22: 4845 | D22: 4 | G22: 2 | H22: Fornecedor 2
A23: =VLOOKUP(RANDBETWEEN(1,5),$G$21:$H$25,2,0) -> Fornecedor 3 | B23: 44589 | C23: 5256 | D23: 4 | G23: 3 | H23: Fornecedor 3
A24: =VLOOKUP(RANDBETWEEN(1,5),$G$21:$H$25,2,0) -> Fornecedor 5 | B24: 44593 | C24: 1167 | D24: 5 | G24: 4 | H24: Fornecedor 4
A25: =VLOOKUP(RANDBETWEEN(1,5),$G$21:$H$25,2,0) -> Fornecedor 5 | B25: 44594 | C25: 4927 | D25: 5 | G25: 5 | H25: Fornecedor 5
A26: =VLOOKUP(RANDBETWEEN(1,5),$G$21:$H$25,2,0) -> Fornecedor 3 | B26: 44597 | C26: 3619 | D26: 5
A27: =VLOOKUP(RANDBETWEEN(1,5),$G$21:$H$25,2,0) -> Fornecedor 5 | B27: 44597 | C27: 2773 | D27: 5
A28: =VLOOKUP(RANDBETWEEN(1,5),$G$21:$H$25,2,0) -> Fornecedor 2 | B28: 44599 | C28: 5911 | D28: 6
A29: =VLOOKUP(RANDBETWEEN(1,5),$G$21:$H$25,2,0) -> Fornecedor 4 | B29: 44600 | C29: 1972 | D29: 6
A30: =VLOOKUP(RANDBETWEEN(1,5),$G$21:$H$25,2,0) -> Fornecedor 5 | B30: 44601 | C30: 4927 | D30: 6
A31: =VLOOKUP(RANDBETWEEN(1,5),$G$21:$H$25,2,0) -> Fornecedor 1 | B31: 44605 | C31: 4845 | D31: 6
A32: =VLOOKUP(RANDBETWEEN(1,5),$G$21:$H$25,2,0) -> Fornecedor 1 | B32: 44604 | C32: 5256 | D32: 6
A33: =VLOOKUP(RANDBETWEEN(1,5),$G$21:$H$25,2,0) -> Fornecedor 1 | B33: 44605 | C33: 1366 | D33: 6
A34: =VLOOKUP(RANDBETWEEN(1,5),$G$21:$H$25,2,0) -> Fornecedor 5 | B34: 44612 | C34: 2773 | D34: 7
A35: =VLOOKUP(RANDBETWEEN(1,5),$G$21:$H$25,2,0) -> Fornecedor 1 | B35: 44620 | C35: 4845 | D35: 8
A36: =VLOOKUP(RANDBETWEEN(1,5),$G$21:$H$25,2,0) -> Fornecedor 3 | B36: 44630 | C36: 2773 | D36: 10

Sheet DashBoard Receber

Sheet DBO Receber
A1: Cliente | B1: Data | C1: Sit | D1: Valor | E1: Dias Faltantes | F1: A receber | G1: Atrasado | H1: Mês | I1: Ano | J1: Sit 2 | M1: Aux. DBO Receber | O1: Situação
A2: Cliente H | B2: 44656 | C2: Parcial | D2: 2605 | E2: 6 | F2: 15D | G2: N/A | H2: Abr | I2: 2022 | J2: parcial | M2: Vlr Min | N2: 139 | O2: 1 | P2: Aberto
A3: Cliente C | B3: 44701 | C3: Aberto | D3: 180 | E3: 51 | F3: 45D+ | G3: N/A | H3: Mai | I3: 2022 | J3: aberto | M3: Vlr Max | N3: 2698.25 | O3: 2 | P3: Atrasado
A4: Cliente J | B4: 44537 | C4: Parcial | D4: 273 | E4: -113 | F4: N/A | G4: 45D+ | H4: Dez | I4: 2021 | J4: parcial | M4: Data min | N4: 44531 | O4: 3 | P4: Pago
A5: Cliente E | B5: 44662 | C5: Parcial | D5: 1710 | E5: 12 | F5: 15D | G5: N/A | H5: Abr | I5: 2022 | J5: parcial | M5: Data max | N5: 44711 | O5: 4 | P5: Parcial
A6: Cliente G | B6: 44643 | C6: Pago | D6: 875 | E6: -7 | F6: N/A | G6: N/A | H6: Mar | I6: 2022 | J6: pago
A7: Cliente G | B7: 44667 | C7: Atrasado | D7: 870 | E7: 17 | F7: 30D | G7: N/A | H7: Abr | I7: 2022 | J7: aberto | M7: 1 | N7: Cliente A
A8: Cliente C | B8: 44597 | C8: Aberto | D8: 903 | E8: -53 | F8: N/A | G8: 45D+ | H8: Fev | I8: 2022 | J8: atrasada | M8: 2 | N8: Cliente B
A9: Cliente C | B9: 44706 | C9: Aberto | D9: 667 | E9: 56 | F9: 45D+ | G9: N/A | H9: Mai | I9: 2022 | J9: aberto | M9: 3 | N9: Cliente C
A10: Cliente H | B10: 44687 | C10: Atrasado | D10: 952 | E10: 37 | F10: 45D | G10: N/A | H10: Mai | I10: 2022 | J10: aberto | M10: 4 | N10: Cliente D
A11: Cliente B | B11: 44655 | C11: Aberto | D11: 1962 | E11: 5 | F11: 15D | G11: N/A | H11: Abr | I11: 2022 | J11: aberto | M11: 5 | N11: Cliente E
A12: Cliente C | B12: 44552 | C12: Aberto | D12: 2412 | E12: -98 | F12: N/A | G12: 45D+ | H12: Dez | I12: 2021 | J12: atrasada | M12: 6 | N12: Cliente F
A13: Cliente J | B13: 44553 | C13: Atrasado | D13: 1371 | E13: -97 | F13: N/A | G13: 45D+ | H13: Dez | I13: 2021 | J13: atrasada | M13: 7 | N13: Cliente G
A14: Cliente C | B14: 44624 | C14: Parcial | D14: 596 | E14: -26 | F14: N/A | G14: 30D | H14: Mar | I14: 2022 | J14: parcial | M14: 8 | N14: Cliente H
A15: Cliente A | B15: 44566 | C15: Parcial | D15: 2545 | E15: -84 | F15: N/A | G15: 45D+ | H15: Jan | I15: 2022 | J15: parcial | M15: 9 | N15: Cliente I
A16: Cliente F | B16: 44617 | C16: Pago | D16: 1681 | E16: -33 | F16: N/A | G16: N/A | H16: Fev | I16: 2022 | J16: pago | M16: 10 | N16: Cliente J
A17: Cliente I | B17: 44600 | C17: Aberto | D17: 2584 | E17: -50 | F17: N/A | G17: 45D+ | H17: Fev | I17: 2022 | J17: atrasada
A18: Cliente H | B18: 44560 | C18: Aberto | D18: 901 | E18: -90 | F18: N/A | G18: 45D+ | H18: Dez | I18: 2021 | J18: atrasada
A19: Cliente G | B19: 44674 | C19: Parcial | D19: 1933 | E19: 24 | F19: 30D | G19: N/A | H19: Abr | I19: 2022 | J19: parcial
A20: Cliente J | B20: 44679 | C20: Atrasado | D20: 2321 | E20: 29 | F20: 30D | G20: N/A | H20: Abr | I20: 2022 | J20: aberto
A21: Cliente B | B21: 44688 | C21: Aberto | D21: 2270 | E21: 38 | F21: 45D | G21: N/A | H21: Mai | I21: 2022 | J21: aberto
A22: Cliente A | B22: 44685 | C22: Parcial | D22: 1602 | E22: 35 | F22: 45D | G22: N/A | H22: Mai | I22: 2022 | J22: parcial
A23: Cliente B | B23: 44540 | C23: Parcial | D23: 1527 | E23: -110 | F23: N/A | G23: 45D+ | H23: Dez | I23: 2021 | J23: parcial
A24: Cliente E | B24: 44619 | C24: Pago | D24: 1619 | E24: -31 | F24: N/A | G24: N/A | H24: Fev | I24: 2022 | J24: pago
A25: Cliente F | B25: 44547 | C25: Pago | D25: 2234 | E25: -103 | F25: N/A | G25: N/A | H25: Dez | I25: 2021 | J25: pago
A26: Cliente G | B26: 44619 | C26: Pago | D26: 1414 | E26: -31 | F26: N/A | G26: N/A | H26: Fev | I26: 2022 | J26: pago
A27: Cliente B | B27: 44612 | C27: Pago | D27: 680 | E27: -38 | F27: N/A | G27: N/A | H27: Fev | I27: 2022 | J27: pago
A28: Cliente E | B28: 44633 | C28: Pago | D28: 683 | E28: -17 | F28: N/A | G28: N/A | H28: Mar | I28: 2022 | J28: pago
... A321: Cliente D | B321: 44678 | C321: Atrasado | D321: 1703 | E321: 28 | F321: 30D | G321: N/A | H321: Abr | I321: 2022 | J321: aberto

Sheet Prazo
N1: Vlr. Total atraso | O1: =SUMIF('DBO Receber'!C:C,"Atrasada",'DBO Receber'!D:D)+SUMIF('DBO Receber'!C:C,"Parcial",'DBO Receber'!D:D) -> 121085
A3: Sit 2 | B3: aberto | G3: ATRASADOS POR DIA
G4: Soma de Valor | H4: Rótulos de Coluna
A5: Soma de Valor | B5: Rótulos de Coluna | G5: Rótulos de Linha | H5: 15D | I5: 30D | J5: 45D | K5: 45D+ | L5: Total Geral
A6: Rótulos de Linha | B6: 45D | C6: Total Geral | G6: atrasada | H6: 24198 | I6: 33381 | J6: 14082 | K6: 53351 | L6: 125012
A7: Aberto | B7: 9238 | C7: 9238 | G7: parcial | H7: 7789 | I7: 4184 | J7: 4486 | K7: 31547 | L7: 48006
A8: Atrasado | B8: 7099 | C8: 7099 | G8: Total Geral | H8: 31987 | I8: 37565 | J8: 18568 | K8: 84898 | L8: 173018
A9: Total Geral | B9: 16337 | C9: 16337
A13: NO PRAZO (A RECEBER)
A14: Sit 2 | B14: aberto
G15: Sit 2 | H15: (Vários itens)
A16: Rótulos de Linha | B16: Soma de Valor
A17: Cliente J | B17: 1610 | G17: Rótulos de Linha | H17: Soma de Valor
A18: Cliente H | B18: 952 | G18: Cliente J | H18: 11120
A19: Cliente G | B19: 3958 | G19: Cliente I | H19: 13803
A20: Cliente F | B20: 2268 | G20: Cliente H | H20: 18652
A21: Cliente E | B21: 3331 | G21: Cliente G | H21: 18465
A22: Cliente C | B22: 967 | G22: Cliente F | H22: 25157
A23: Cliente B | B23: 3251 | G23: Cliente E | H23: 10204
A24: Total Geral | B24: 16337 | G24: Cliente D | H24: 11602
G25: Cliente C | H25: 31085
G26: Cliente B | H26: 13406
G27: Cliente A | H27: 19524
G28: Total Geral | H28: 173018

Sheet Auxiliar a Receber
A1: 1 | B1: Jan | D1: Vlr total pago | E1: =SUMIF('DBO Receber'!C:C,"pago",'DBO Receber'!D:D) -> 107478
A2: 2 | B2: Fev | D2: Vlr total em aberto | E2: =SUMIF('DBO Receber'!C:C,"aberto",'DBO Receber'!D:D) -> 149746
A3: 3 | B3: Mar | D3: Vlr atrasado | E3: =SUMIF('DBO Receber'!C:C,"atrasada",'DBO Receber'!D:D)+SUMIF('DBO Receber'!C:C,"parcial",'DBO Receber'!D:D) -> 121085
A4: 4 | B4: Abr | D4: Vlr A RECEBER | E4: =SUM(E2:E3) -> 270831
A5: 5 | B5: Mai
A6: 6 | B6: Jun
A7: 7 | B7: Jul
A8: 8 | B8: Ago
A9: 9 | B9: Set
A10: 10 | B10: Out
A11: 11 | B11: Nov
A12: 12 | B12: Dez
